Workbook

Sheet Entregas
A1: ID | B1: Nº | C1: CLIENTE | D1: OPERACIÓN | E1: DESPACHO | F1: CONTENEDOR | G1: TIPO | H1: PESO | I1: LUGAR RETIRO | J1: FECHA ENTREGA | K1: HORA ENTREGA | L1: Ubicación Vacio | M1: CONDUCTOR | N1: CONTACTO | O1: EQUIPO | P1: Rampla | Q1: Dirección Entrega | R1: DEPOSITO DEVOLUCION | S1: Conductor Devolución | T1: Equipo Devolución | U1: Fecha devolución | V1: Estado Devolución | W1: FOLIO | X1: NOTA | Y1: Estado de entrega | Z1: RC_NE | AA1: Hora Real Entrega | AB1: Hora Salida | AC1: Fecha Real Entrega | AD1: OTD | AE1: Validador | AF1: Mensaje | AG1: Link | AH1: Validador2 | AI1: Op | AJ1: VAL | AK1: Concat | AL1: URL
A2: =ROW(A1) -> 1 | B2: =IF(J2=J1,B1+1,1) -> 1 | C2: EL CONTAINER SPA | D2: IMPO | E2: 303965 | F2: CAAU4530857 | G2: 40 HC | H2: 26800 | I2: FRAGUA | J2: 46028 | N2: =IFERROR(VLOOKUP(M2,Data!$J$1:$K$58,2,0),"") | AD2: =IF(Tabla2[[#This Row],[HORA ENTREGA]]="DIRECTO","On time", IF(AA2<>"",IF(Tabla2[[#This Row],[Fecha Real Entrega]]<Tabla2[[#This Row],[FECHA ENTREGA]],"On time",IF(Tabla2[[#This Row],[Hora Real Entrega]]<=Tabla2[[#This Row],[HORA ENTREGA]]+(15/1440),"On time","Off time")),"Sin llegada")) -> Sin llegada | AE2: =MID(Tabla2[[#This Row],[TIPO]],1,3) -> 40 | AF2: ="Hola!" & "%0A" & "Servicio del día " &TEXT(Tabla2[[#This Row],[FECHA ENTREGA]],"dd-mm") & "%0A" & " *Cliente:* " &Tabla2[[#This Row],[CLIENTE]] & " */ Cont: * "&Tabla2[[#This Row],[CONTENEDOR]] & "*/ HR Entrega: *" & TEXT(Tabla2[[#This Row],[HORA ENTREGA]],"hh:mm") & "* /Dirección: *" & Tabla2[[#This Row],[Dirección Entrega]] -> Hola!%0AServicio del día 06-01%0A *Cliente:* EL CONTAINER SPA */ Cont: * CAAU4530857*/ HR Entrega: *00:00* /Dirección: * | AG2: =IFERROR(HYPERLINK("https://wa.me/"&Tabla2[[#This Row],[CONTACTO]]&"?text="&Tabla2[[#This Row],[Mensaje]],"Enviar mensaje"),"") -> Enviar mensaje | AH2: =CONCATENATE(A2,F2) -> 1CAAU4530857 | AI2: =CONCATENATE("ENT-",A2) -> ENT-1 | AJ2: =IF(Tabla2[[#This Row],[Op]]<>"","ENTREGA","") -> ENTREGA | AK2: =(Tabla2[[#This Row],[FECHA ENTREGA]]&Tabla2[[#This Row],[HORA ENTREGA]]) -> 46028 | AL2: =IFERROR(HYPERLINK("https://wa.me/"&Tabla2[[#This Row],[CONTACTO]]&"?text="&Tabla2[[#This Row],[Mensaje]]),"") -> https://wa.me/?text=Hola!%0AServicio del día 06-01%0A *Cliente:* EL CONTAINER SPA */ Cont: * CAAU4530857*/ HR Entrega: *00:00* /Dirección: *
A3: =ROW(A2) -> 2 | B3: =IF(J3=J2,B2+1,1) -> 1 | C3: ALCA SPA | D3: IMPO | E3: 297289 | F3: CGMU5741499 | G3: 40 HC | H3: 32000 | I3: FRAGUA | J3: 46055 | K3: 0.33333333 | M3: SAMUEL SALAS | N3: =IFERROR(VLOOKUP(M3,Data!$J$1:$K$58,2,0),"") -> 56950981572 | O3: THYG-63 | Q3: BERNARDO O"HIGGINS 158 COLINA | R3: CIS | Y3: ENTREGADO | AA3: 0.33333333 | AC3: 46055 | AD3: =IF(Tabla2[[#This Row],[HORA ENTREGA]]="DIRECTO","On time", IF(AA3<>"",IF(Tabla2[[#This Row],[Fecha Real Entrega]]<Tabla2[[#This Row],[FECHA ENTREGA]],"On time",IF(Tabla2[[#This Row],[Hora Real Entrega]]<=Tabla2[[#This Row],[HORA ENTREGA]]+(15/1440),"On time","Off time")),"Sin llegada")) -> On time | AE3: =MID(Tabla2[[#This Row],[TIPO]],1,3) -> 40 | AF3: ="Hola!" & "%0A" & "Servicio del día " &TEXT(Tabla2[[#This Row],[FECHA ENTREGA]],"dd-mm") & "%0A" & " *Cliente:* " &Tabla2[[#This Row],[CLIENTE]] & " */ Cont: * "&Tabla2[[#This Row],[CONTENEDOR]] & "*/ HR Entrega: *" & TEXT(Tabla2[[#This Row],[HORA ENTREGA]],"hh:mm") & "* /Dirección: *" & Tabla2[[#This Row],[Dirección Entrega]] -> Hola!%0AServicio del día 02-02%0A *Cliente:* ALCA SPA */ Cont: * CGMU5741499*/ HR Entrega: *08:00* /Dirección: *BERNARDO O"HIGGINS 158 COLINA | AG3: =IFERROR(HYPERLINK("https://wa.me/"&Tabla2[[#This Row],[CONTACTO]]&"?text="&Tabla2[[#This Row],[Mensaje]],"Enviar mensaje"),"") -> Enviar mensaje | AH3: =CONCATENATE(A3,F3) -> 2CGMU5741499 | AI3: =CONCATENATE("ENT-",A3) -> ENT-2 | AJ3: =IF(Tabla2[[#This Row],[Op]]<>"","ENTREGA","") -> ENTREGA | AK3: =(Tabla2[[#This Row],[FECHA ENTREGA]]&Tabla2[[#This Row],[HORA ENTREGA]]) -> 460550,333333333333333 | AL3: =IFERROR(HYPERLINK("https://wa.me/"&Tabla2[[#This Row],[CONTACTO]]&"?text="&Tabla2[[#This Row],[Mensaje]]),"") -> https://wa.me/56950981572?text=Hola!%0AServicio del día 02-02%0A *Cliente:* ALCA SPA */ Cont: * CGMU5741499*/ HR Entrega: *08:00* /Dirección: *BERNARDO O"HIGGINS 158 COLINA
A4: =ROW(A3) -> 3 | B4: =IF(J4=J3,B3+1,1) -> 2 | C4: ALCA SPA | D4: IMPO | E4: 297289 | F4: SEGU9527603 | G4: 40 HC | H4: 32000 | I4: FRAGUA | J4: 46055 | K4: 0.41666667 | M4: HELBERTH CASTRO | N4: =IFERROR(VLOOKUP(M4,Data!$J$1:$K$58,2,0),"") -> 56967256951 | O4: RFZW-96 | Q4: BERNARDO O"HIGGINS 158 COLINA | R4: CIS | Y4: ENTREGADO | AA4: 0.39930556 | AC4: 46055 | AD4: =IF(Tabla2[[#This Row],[HORA ENTREGA]]="DIRECTO","On time", IF(AA4<>"",IF(Tabla2[[#This Row],[Fecha Real Entrega]]<Tabla2[[#This Row],[FECHA ENTREGA]],"On time",IF(Tabla2[[#This Row],[Hora Real Entrega]]<=Tabla2[[#This Row],[HORA ENTREGA]]+(15/1440),"On time","Off time")),"Sin llegada")) -> On time | AE4: =MID(Tabla2[[#This Row],[TIPO]],1,3) -> 40 | AF4: ="Hola!" & "%0A" & "Servicio del día " &TEXT(Tabla2[[#This Row],[FECHA ENTREGA]],"dd-mm") & "%0A" & " *Cliente:* " &Tabla2[[#This Row],[CLIENTE]] & " */ Cont: * "&Tabla2[[#This Row],[CONTENEDOR]] & "*/ HR Entrega: *" & TEXT(Tabla2[[#This Row],[HORA ENTREGA]],"hh:mm") & "* /Dirección: *" & Tabla2[[#This Row],[Dirección Entrega]] -> Hola!%0AServicio del día 02-02%0A *Cliente:* ALCA SPA */ Cont: * SEGU9527603*/ HR Entrega: *10:00* /Dirección: *BERNARDO O"HIGGINS 158 COLINA | AG4: =IFERROR(HYPERLINK("https://wa.me/"&Tabla2[[#This Row],[CONTACTO]]&"?text="&Tabla2[[#This Row],[Mensaje]],"Enviar mensaje"),"") -> Enviar mensaje | AH4: =CONCATENATE(A4,F4) -> 3SEGU9527603 | AI4: =CONCATENATE("ENT-",A4) -> ENT-3 | AJ4: =IF(Tabla2[[#This Row],[Op]]<>"","ENTREGA","") -> ENTREGA | AK4: =(Tabla2[[#This Row],[FECHA ENTREGA]]&Tabla2[[#This Row],[HORA ENTREGA]]) -> 460550,416666666666667 | AL4: =IFERROR(HYPERLINK("https://wa.me/"&Tabla2[[#This Row],[CONTACTO]]&"?text="&Tabla2[[#This Row],[Mensaje]]),"") -> https://wa.me/56967256951?text=Hola!%0AServicio del día 02-02%0A *Cliente:* ALCA SPA */ Cont: * SEGU9527603*/ HR Entrega: *10:00* /Dirección: *BERNARDO O"HIGGINS 158 COLINA
A5: =ROW(A4) -> 4 | B5: =IF(J5=J4,B4+1,1) -> 3 | C5: ALCA SPA | D5: IMPO | E5: 366856 | F5: HLBU9689467 | G5: 40 RF | H5: 20000 | I5: 46053 | J5: 46055 | K5: 0.47916667 | M5: RODRIGO AÑAZCO | N5: =IFERROR(VLOOKUP(M5,Data!$J$1:$K$58,2,0),"") -> 56992164782 | O5: LGGR-14 | Q5: Camino del Cerro 4868 Huechuraba | R5: DYC VALP | Y5: ENTREGADO | AA5: 0.51388889 | AC5: 46055 | AD5: =IF(Tabla2[[#This Row],[HORA ENTREGA]]="DIRECTO","On time", IF(AA5<>"",IF(Tabla2[[#This Row],[Fecha Real Entrega]]<Tabla2[[#This Row],[FECHA ENTREGA]],"On time",IF(Tabla2[[#This Row],[Hora Real Entrega]]<=Tabla2[[#This Row],[HORA ENTREGA]]+(15/1440),"On time","Off time")),"Sin llegada")) -> Off time | AE5: =MID(Tabla2[[#This Row],[TIPO]],1,3) -> 40 | AF5: ="Hola!" & "%0A" & "Servicio del día " &TEXT(Tabla2[[#This Row],[FECHA ENTREGA]],"dd-mm") & "%0A" & " *Cliente:* " &Tabla2[[#This Row],[CLIENTE]] & " */ Cont: * "&Tabla2[[#This Row],[CONTENEDOR]] & "*/ HR Entrega: *" & TEXT(Tabla2[[#This Row],[HORA ENTREGA]],"hh:mm") & "* /Dirección: *" & Tabla2[[#This Row],[Dirección Entrega]] -> Hola!%0AServicio del día 02-02%0A *Cliente:* ALCA SPA */ Cont: * HLBU9689467*/ HR Entrega: *11:30* /Dirección: *Camino del Cerro 4868 Huechuraba | AG5: =IFERROR(HYPERLINK("https://wa.me/"&Tabla2[[#This Row],[CONTACTO]]&"?text="&Tabla2[[#This Row],[Mensaje]],"Enviar mensaje"),"") -> Enviar mensaje | AH5: =CONCATENATE(A5,F5) -> 4HLBU9689467 | AI5: =CONCATENATE("ENT-",A5) -> ENT-4 | AJ5: =IF(Tabla2[[#This Row],[Op]]<>"","ENTREGA","") -> ENTREGA | AK5: =(Tabla2[[#This Row],[FECHA ENTREGA]]&Tabla2[[#This Row],[HORA ENTREGA]]) -> 460550,479166666666667 | AL5: =IFERROR(HYPERLINK("https://wa.me/"&Tabla2[[#This Row],[CONTACTO]]&"?text="&Tabla2[[#This Row],[Mensaje]]),"") -> https://wa.me/56992164782?text=Hola!%0AServicio del día 02-02%0A *Cliente:* ALCA SPA */ Cont: * HLBU9689467*/ HR Entrega: *11:30* /Dirección: *Camino del Cerro 4868 Huechuraba
A6: =ROW(A5) -> 5 | B6: =IF(J6=J5,B5+1,1) -> 4 | C6: ALCA SPA | D6: IMPO | E6: 297289 | F6: CGMU5298919 | G6: 40 HC | H6: 32000 | I6: FRAGUA | J6: 46055 | K6: 0.5 | M6: FELIPE CATALAN | N6: =IFERROR(VLOOKUP(M6,Data!$J$1:$K$58,2,0),"") -> 56957438415 | O6: RRVF-72 | Q6: BERNARDO O"HIGGINS 158 COLINA | R6: CIS | Y6: ENTREGADO | AA6: 0.55694444 | AC6: 46055 | AD6: =IF(Tabla2[[#This Row],[HORA ENTREGA]]="DIRECTO","On time", IF(AA6<>"",IF(Tabla2[[#This Row],[Fecha Real Entrega]]<Tabla2[[#This Row],[FECHA ENTREGA]],"On time",IF(Tabla2[[#This Row],[Hora Real Entrega]]<=Tabla2[[#This Row],[HORA ENTREGA]]+(15/1440),"On time","Off time")),"Sin llegada")) -> Off time | AE6: =MID(Tabla2[[#This Row],[TIPO]],1,3) -> 40 | AF6: ="Hola!" & "%0A" & "Servicio del día " &TEXT(Tabla2[[#This Row],[FECHA ENTREGA]],"dd-mm") & "%0A" & " *Cliente:* " &Tabla2[[#This Row],[CLIENTE]] & " */ Cont: * "&Tabla2[[#This Row],[CONTENEDOR]] & "*/ HR Entrega: *" & TEXT(Tabla2[[#This Row],[HORA ENTREGA]],"hh:mm") & "* /Dirección: *" & Tabla2[[#This Row],[Dirección Entrega]] -> Hola!%0AServicio del día 02-02%0A *Cliente:* ALCA SPA */ Cont: * CGMU5298919*/ HR Entrega: *12:00* /Dirección: *BERNARDO O"HIGGINS 158 COLINA | AG6: =IFERROR(HYPERLINK("https://wa.me/"&Tabla2[[#This Row],[CONTACTO]]&"?text="&Tabla2[[#This Row],[Mensaje]],"Enviar mensaje"),"") -> Enviar mensaje | AH6: =CONCATENATE(A6,F6) -> 5CGMU5298919 | AI6: =CONCATENATE("ENT-",A6) -> ENT-5 | AJ6: =IF(Tabla2[[#This Row],[Op]]<>"","ENTREGA","") -> ENTREGA | AK6: =(Tabla2[[#This Row],[FECHA ENTREGA]]&Tabla2[[#This Row],[HORA ENTREGA]]) -> 460550,5 | AL6: =IFERROR(HYPERLINK("https://wa.me/"&Tabla2[[#This Row],[CONTACTO]]&"?text="&Tabla2[[#This Row],[Mensaje]]),"") -> https://wa.me/56957438415?text=Hola!%0AServicio del día 02-02%0A *Cliente:* ALCA SPA */ Cont: * CGMU5298919*/ HR Entrega: *12:00* /Dirección: *BERNARDO O"HIGGINS 158 COLINA
A7: =ROW(A6) -> 6 | B7: =IF(J7=J6,B6+1,1) -> 5 | C7: BATERIAS TUBULAR S.A. | D7: IMPO | E7: 297933 | F7: FTAU2361050 | G7: 20 DV | H7: 6000 | I7: 31/01 - 11:14 | J7: 46055 | K7: 0.33333333 | M7: DANIEL GOMEZ | N7: =IFERROR(VLOOKUP(M7,Data!$J$1:$K$58,2,0),"") -> 56993389870 | O7: LPYG-89 | Q7: AV. CHENA PONIENTE 12624, SAN BERNARDO | R7: DYC SAI | Y7: ENTREGADO | AA7: 0.29513889 | AC7: 46055 | AD7: =IF(Tabla2[[#This Row],[HORA ENTREGA]]="DIRECTO","On time", IF(AA7<>"",IF(Tabla2[[#This Row],[Fecha Real Entrega]]<Tabla2[[#This Row],[FECHA ENTREGA]],"On time",IF(Tabla2[[#This Row],[Hora Real Entrega]]<=Tabla2[[#This Row],[HORA ENTREGA]]+(15/1440),"On time","Off time")),"Sin llegada")) -> On time | AE7: =MID(Tabla2[[#This Row],[TIPO]],1,3) -> 20 | AF7: ="Hola!" & "%0A" & "Servicio del día " &TEXT(Tabla2[[#This Row],[FECHA ENTREGA]],"dd-mm") & "%0A" & " *Cliente:* " &Tabla2[[#This Row],[CLIENTE]] & " */ Cont: * "&Tabla2[[#This Row],[CONTENEDOR]] & "*/ HR Entrega: *" & TEXT(Tabla2[[#This Row],[HORA ENTREGA]],"hh:mm") & "* /Dirección: *" & Tabla2[[#This Row],[Dirección Entrega]] -> Hola!%0AServicio del día 02-02%0A *Cliente:* BATERIAS TUBULAR S.A. */ Cont: * FTAU2361050*/ HR Entrega: *08:00* /Dirección: *AV. CHENA PONIENTE 12624, SAN BERNARDO | AG7: =IFERROR(HYPERLINK("https://wa.me/"&Tabla2[[#This Row],[CONTACTO]]&"?text="&Tabla2[[#This Row],[Mensaje]],"Enviar mensaje"),"") -> Enviar mensaje | AH7: =CONCATENATE(A7,F7) -> 6FTAU2361050 | AI7: =CONCATENATE("ENT-",A7) -> ENT-6 | AJ7: =IF(Tabla2[[#This Row],[Op]]<>"","ENTREGA","") -> ENTREGA | AK7: =(Tabla2[[#This Row],[FECHA ENTREGA]]&Tabla2[[#This Row],[HORA ENTREGA]]) -> 460550,333333333333333 | AL7: =IFERROR(HYPERLINK("https://wa.me/"&Tabla2[[#This Row],[CONTACTO]]&"?text="&Tabla2[[#This Row],[Mensaje]]),"") -> https://wa.me/56993389870?text=Hola!%0AServicio del día 02-02%0A *Cliente:* BATERIAS TUBULAR S.A. */ Cont: * FTAU2361050*/ HR Entrega: *08:00* /Dirección: *AV. CHENA PONIENTE 12624, SAN BERNARDO
A8: =ROW(A7) -> 7 | B8: =IF(J8=J7,B7+1,1) -> 6 | C8: BATERIAS TUBULAR S.A. | D8: IMPO | E8: 297464 | F8: BEAU4281752 | G8: 40 HC | H8: 27000 | I8: 31/01 - 9:16 | J8: 46055 | K8: 0.41666667 | M8: JUAN SALINAS | N8: =IFERROR(VLOOKUP(M8,Data!$J$1:$K$58,2,0),"") -> 56978089148 | O8: HSWP-41 | Q8: AV. CHENA PONIENTE 12624, SAN BERNARDO | R8: MEDLOG SAI | Y8: ENTREGADO | AA8: 0.32986111 | AC8: 46055 | AD8: =IF(Tabla2[[#This Row],[HORA ENTREGA]]="DIRECTO","On time", IF(AA8<>"",IF(Tabla2[[#This Row],[Fecha Real Entrega]]<Tabla2[[#This Row],[FECHA ENTREGA]],"On time",IF(Tabla2[[#This Row],[Hora Real Entrega]]<=Tabla2[[#This Row],[HORA ENTREGA]]+(15/1440),"On time","Off time")),"Sin llegada")) -> On time | AE8: =MID(Tabla2[[#This Row],[TIPO]],1,3) -> 40 | AF8: ="Hola!" & "%0A" & "Servicio del día " &TEXT(Tabla2[[#This Row],[FECHA ENTREGA]],"dd-mm") & "%0A" & " *Cliente:* " &Tabla2[[#This Row],[CLIENTE]] & " */ Cont: * "&Tabla2[[#This Row],[CONTENEDOR]] & "*/ HR Entrega: *" & TEXT(Tabla2[[#This Row],[HORA ENTREGA]],"hh:mm") & "* /Dirección: *" & Tabla2[[#This Row],[Dirección Entrega]] -> Hola!%0AServicio del día 02-02%0A *Cliente:* BATERIAS TUBULAR S.A. */ Cont: * BEAU4281752*/ HR Entrega: *10:00* /Dirección: *AV. CHENA PONIENTE 12624, SAN BERNARDO | AG8: =IFERROR(HYPERLINK("https://wa.me/"&Tabla2[[#This Row],[CONTACTO]]&"?text="&Tabla2[[#This Row],[Mensaje]],"Enviar mensaje"),"") -> Enviar mensaje | AH8: =CONCATENATE(A8,F8) -> 7BEAU4281752 | AI8: =CONCATENATE("ENT-",A8) -> ENT-7 | AJ8: =IF(Tabla2[[#This Row],[Op]]<>"","ENTREGA","") -> ENTREGA | AK8: =(Tabla2[[#This Row],[FECHA ENTREGA]]&Tabla2[[#This Row],[HORA ENTREGA]]) -> 460550,416666666666667 | AL8: =IFERROR(HYPERLINK("https://wa.me/"&Tabla2[[#This Row],[CONTACTO]]&"?text="&Tabla2[[#This Row],[Mensaje]]),"") -> https://wa.me/56978089148?text=Hola!%0AServicio del día 02-02%0A *Cliente:* BATERIAS TUBULAR S.A. */ Cont: * BEAU4281752*/ HR Entrega: *10:00* /Dirección: *AV. CHENA PONIENTE 12624, SAN BERNARDO
A9: =ROW(A8) -> 8 | B9: =IF(J9=J8,B8+1,1) -> 7 | C9: BAYONA SPA | D9: IMPO | E9: 297776 | F9: CMAU7238042 | G9: 40 HC | H9: 7000 | I9: FRAGUA | J9: 46055 | K9: 0.33333333 | M9: ROBERTO CARREÑO | N9: =IFERROR(VLOOKUP(M9,Data!$J$1:$K$58,2,0),"") -> 56967384794 | O9: RVFP-32 | Q9: BOULEVAR 1313 BODENOR FLEX CENTER ENEA, PUDAHUEL | R9: CIS | Y9: ENTREGADO | AA9: 0.31944444 | AC9: 46055 | AD9: =IF(Tabla2[[#This Row],[HORA ENTREGA]]="DIRECTO","On time", IF(AA9<>"",IF(Tabla2[[#This Row],[Fecha Real Entrega]]<Tabla2[[#This Row],[FECHA ENTREGA]],"On time",IF(Tabla2[[#This Row],[Hora Real Entrega]]<=Tabla2[[#This Row],[HORA ENTREGA]]+(15/1440),"On time","Off time")),"Sin llegada")) -> On time | AE9: =MID(Tabla2[[#This Row],[TIPO]],1,3) -> 40 | AF9: ="Hola!" & "%0A" & "Servicio del día " &TEXT(Tabla2[[#This Row],[FECHA ENTREGA]],"dd-mm") & "%0A" & " *Cliente:* " &Tabla2[[#This Row],[CLIENTE]] & " */ Cont: * "&Tabla2[[#This Row],[CONTENEDOR]] & "*/ HR Entrega: *" & TEXT(Tabla2[[#This Row],[HORA ENTREGA]],"hh:mm") & "* /Dirección: *" & Tabla2[[#This Row],[Dirección Entrega]] -> Hola!%0AServicio del día 02-02%0A *Cliente:* BAYONA SPA */ Cont: * CMAU7238042*/ HR Entrega: *08:00* /Dirección: * BOULEVAR 1313 BODENOR FLEX CENTER ENEA, PUDAHUEL | AG9: =IFERROR(HYPERLINK("https://wa.me/"&Tabla2[[#This Row],[CONTACTO]]&"?text="&Tabla2[[#This Row],[Mensaje]],"Enviar mensaje"),"") -> Enviar mensaje | AH9: =CONCATENATE(A9,F9) -> 8CMAU7238042 | AI9: =CONCATENATE("ENT-",A9) -> ENT-8 | AJ9: =IF(Tabla2[[#This Row],[Op]]<>"","ENTREGA","") -> ENTREGA | AK9: =(Tabla2[[#This Row],[FECHA ENTREGA]]&Tabla2[[#This Row],[HORA ENTREGA]]) -> 460550,333333333333333 | AL9: =IFERROR(HYPERLINK("https://wa.me/"&Tabla2[[#This Row],[CONTACTO]]&"?text="&Tabla2[[#This Row],[Mensaje]]),"") -> https://wa.me/56967384794?text=Hola!%0AServicio del día 02-02%0A *Cliente:* BAYONA SPA */ Cont: * CMAU7238042*/ HR Entrega: *08:00* /Dirección: * BOULEVAR 1313 BODENOR FLEX CENTER ENEA, PUDAHUEL
A10: =ROW(A9) -> 9 | B10: =IF(J10=J9,B9+1,1) -> 8 | C10: BAYONA SPA | D10: IMPO | E10: 297771 | F10: UETU7315402 | G10: 40 HC | H10: 9000 | I10: FRAGUA | J10: 46055 | K10: 0.45833333 | M10: JUAN BARRAZA | N10: =IFERROR(VLOOKUP(M10,Data!$J$1:$K$58,2,0),"") -> 56944277110 | O10: LFHK-35 | Q10: BOULEVAR 1313 BODENOR FLEX CENTER ENEA, PUDAHUEL | R10: CIS | Y10: ENTREGADO | AA10: 0.52986111 | AC10: 46055 | AD10: =IF(Tabla2[[#This Row],[HORA ENTREGA]]="DIRECTO","On time", IF(AA10<>"",IF(Tabla2[[#This Row],[Fecha Real Entrega]]<Tabla2[[#This Row],[FECHA ENTREGA]],"On time",IF(Tabla2[[#This Row],[Hora Real Entrega]]<=Tabla2[[#This Row],[HORA ENTREGA]]+(15/1440),"On time","Off time")),"Sin llegada")) -> Off time | AE10: =MID(Tabla2[[#This Row],[TIPO]],1,3) -> 40 | AF10: ="Hola!" & "%0A" & "Servicio del día " &TEXT(Tabla2[[#This Row],[FECHA ENTREGA]],"dd-mm") & "%0A" & " *Cliente:* " &Tabla2[[#This Row],[CLIENTE]] & " */ Cont: * "&Tabla2[[#This Row],[CONTENEDOR]] & "*/ HR Entrega: *" & TEXT(Tabla2[[#This Row],[HORA ENTREGA]],"hh:mm") & "* /Dirección: *" & Tabla2[[#This Row],[Dirección Entrega]] -> Hola!%0AServicio del día 02-02%0A *Cliente:* BAYONA SPA */ Cont: * UETU7315402*/ HR Entrega: *11:00* /Dirección: * BOULEVAR 1313 BODENOR FLEX CENTER ENEA, PUDAHUEL | AG10: =IFERROR(HYPERLINK("https://wa.me/"&Tabla2[[#This Row],[CONTACTO]]&"?text="&Tabla2[[#This Row],[Mensaje]],"Enviar mensaje"),"") -> Enviar mensaje | AH10: =CONCATENATE(A10,F10) -> 9UETU7315402 | AI10: =CONCATENATE("ENT-",A10) -> ENT-9 | AJ10: =IF(Tabla2[[#This Row],[Op]]<>"","ENTREGA","") -> ENTREGA | AK10: =(Tabla2[[#This Row],[FECHA ENTREGA]]&Tabla2[[#This Row],[HORA ENTREGA]]) -> 460550,458333333333333 | AL10: =IFERROR(HYPERLINK("https://wa.me/"&Tabla2[[#This Row],[CONTACTO]]&"?text="&Tabla2[[#This Row],[Mensaje]]),"") -> https://wa.me/56944277110?text=Hola!%0AServicio del día 02-02%0A *Cliente:* BAYONA SPA */ Cont: * UETU7315402*/ HR Entrega: *11:00* /Dirección: * BOULEVAR 1313 BODENOR FLEX CENTER ENEA, PUDAHUEL
A11: =ROW(A10) -> 10 | B11: =IF(J11=J10,B10+1,1) -> 9 | C11: CANONTEX | D11: IMPO | E11: 312044 | F11: TCLU6542028 | G11: 20 DV | H11: 17000 | I11: FRAGUA | J11: 46055 | K11: 0.375 | M11: JAIME PINTO YAÑEZ | N11: =IFERROR(VLOOKUP(M11,Data!$J$1:$K$58,2,0),"") -> 56956654384 | O11: LPYG-88 | Q11: Patricia Viñuela N°334, Lampa (BODEGA MPR) | R11: CIS | Y11: ENTREGADO | AA11: 0.375 | AC11: 46055 | AD11: =IF(Tabla2[[#This Row],[HORA ENTREGA]]="DIRECTO","On time", IF(AA11<>"",IF(Tabla2[[#This Row],[Fecha Real Entrega]]<Tabla2[[#This Row],[FECHA ENTREGA]],"On time",IF(Tabla2[[#This Row],[Hora Real Entrega]]<=Tabla2[[#This Row],[HORA ENTREGA]]+(15/1440),"On time","Off time")),"Sin llegada")) -> On time | AE11: =MID(Tabla2[[#This Row],[TIPO]],1,3) -> 20 | AF11: ="Hola!" & "%0A" & "Servicio del día " &TEXT(Tabla2[[#This Row],[FECHA ENTREGA]],"dd-mm") & "%0A" & " *Cliente:* " &Tabla2[[#This Row],[CLIENTE]] & " */ Cont: * "&Tabla2[[#This Row],[CONTENEDOR]] & "*/ HR Entrega: *" & TEXT(Tabla2[[#This Row],[HORA ENTREGA]],"hh:mm") & "* /Dirección: *" & Tabla2[[#This Row],[Dirección Entrega]] -> Hola!%0AServicio del día 02-02%0A *Cliente:* CANONTEX */ Cont: * TCLU6542028*/ HR Entrega: *09:00* /Dirección: *Patricia Viñuela N°334, Lampa (BODEGA MPR) | AG11: =IFERROR(HYPERLINK("https://wa.me/"&Tabla2[[#This Row],[CONTACTO]]&"?text="&Tabla2[[#This Row],[Mensaje]],"Enviar mensaje"),"") -> Enviar mensaje | AH11: =CONCATENATE(A11,F11) -> 10TCLU6542028 | AI11: =CONCATENATE("ENT-",A11) -> ENT-10 | AJ11: =IF(Tabla2[[#This Row],[Op]]<>"","ENTREGA","") -> ENTREGA | AK11: =(Tabla2[[#This Row],[FECHA ENTREGA]]&Tabla2[[#This Row],[HORA ENTREGA]]) -> 460550,375 | AL11: =IFERROR(HYPERLINK("https://wa.me/"&Tabla2[[#This Row],[CONTACTO]]&"?text="&Tabla2[[#This Row],[Mensaje]]),"") -> https://wa.me/56956654384?text=Hola!%0AServicio del día 02-02%0A *Cliente:* CANONTEX */ Cont: * TCLU6542028*/ HR Entrega: *09:00* /Dirección: *Patricia Viñuela N°334, Lampa (BODEGA MPR)
A12: =ROW(A11) -> 11 | B12: =IF(J12=J11,B11+1,1) -> 10 | C12: CANONTEX | D12: IMPO | E12: 311937 | F12: FFAU7478843 | G12: 40 HC | H12: 12000 | I12: FRAGUA | J12: 46055 | K12: 0.375 | M12: JAVIER LOPEZ | N12: =IFERROR(VLOOKUP(M12,Data!$J$1:$K$58,2,0),"") -> 56987557136 | O12: TRKJ-63 | Q12: Patricia Viñuela N°334, Lampa (BODEGA CDC) | R12: CONTOPSA VALP | Y12: ENTREGADO | AA12: 0.38055556 | AC12: 46055 | AD12: =IF(Tabla2[[#This Row],[HORA ENTREGA]]="DIRECTO","On time", IF(AA12<>"",IF(Tabla2[[#This Row],[Fecha Real Entrega]]<Tabla2[[#This Row],[FECHA ENTREGA]],"On time",IF(Tabla2[[#This Row],[Hora Real Entrega]]<=Tabla2[[#This Row],[HORA ENTREGA]]+(15/1440),"On time","Off time")),"Sin llegada")) -> On time | AE12: =MID(Tabla2[[#This Row],[TIPO]],1,3) -> 40 | AF12: ="Hola!" & "%0A" & "Servicio del día " &TEXT(Tabla2[[#This Row],[FECHA ENTREGA]],"dd-mm") & "%0A" & " *Cliente:* " &Tabla2[[#This Row],[CLIENTE]] & " */ Cont: * "&Tabla2[[#This Row],[CONTENEDOR]] & "*/ HR Entrega: *" & TEXT(Tabla2[[#This Row],[HORA ENTREGA]],"hh:mm") & "* /Dirección: *" & Tabla2[[#This Row],[Dirección Entrega]] -> Hola!%0AServicio del día 02-02%0A *Cliente:* CANONTEX */ Cont: * FFAU7478843*/ HR Entrega: *09:00* /Dirección: *Patricia Viñuela N°334, Lampa (BODEGA CDC) | AG12: =IFERROR(HYPERLINK("https://wa.me/"&Tabla2[[#This Row],[CONTACTO]]&"?text="&Tabla2[[#This Row],[Mensaje]],"Enviar mensaje"),"") -> Enviar mensaje | AH12: =CONCATENATE(A12,F12) -> 11FFAU7478843 | AI12: =CONCATENATE("ENT-",A12) -> ENT-11 | AJ12: =IF(Tabla2[[#This Row],[Op]]<>"","ENTREGA","") -> ENTREGA | AK12: =(Tabla2[[#This Row],[FECHA ENTREGA]]&Tabla2[[#This Row],[HORA ENTREGA]]) -> 460550,375 | AL12: =IFERROR(HYPERLINK("https://wa.me/"&Tabla2[[#This Row],[CONTACTO]]&"?text="&Tabla2[[#This Row],[Mensaje]]),"") -> https://wa.me/56987557136?text=Hola!%0AServicio del día 02-02%0A *Cliente:* CANONTEX */ Cont: * FFAU7478843*/ HR Entrega: *09:00* /Dirección: *Patricia Viñuela N°334, Lampa (BODEGA CDC)
A13: =ROW(A12) -> 12 | B13: =IF(J13=J12,B12+1,1) -> 11 | C13: COMERCIAL E INDUSTRIAL PLASTICOS HOFFENS S.A. | D13: IMPO | E13: 296856 | F13: ONEU6023062 | G13: 40 HC | H13: 24000 | I13: 31/01 - 01:10 | J13: 46055 | K13: 0.33333333 | M13: JORGE CARDENAS | N13: =IFERROR(VLOOKUP(M13,Data!$J$1:$K$58,2,0),"") -> 56944540732 | O13: KBKZ-28 | Q13: Hoffens: Camino Lonquén 10.707, Maipú | R13: SITRANS VALP | Y13: ENTREGADO | AA13: 0.32430556 | AC13: 46055 | AD13: =IF(Tabla2[[#This Row],[HORA ENTREGA]]="DIRECTO","On time", IF(AA13<>"",IF(Tabla2[[#This Row],[Fecha Real Entrega]]<Tabla2[[#This Row],[FECHA ENTREGA]],"On time",IF(Tabla2[[#This Row],[Hora Real Entrega]]<=Tabla2[[#This Row],[HORA ENTREGA]]+(15/1440),"On time","Off time")),"Sin llegada")) -> On time | AE13: =MID(Tabla2[[#This Row],[TIPO]],1,3) -> 40 | AF13: ="Hola!" & "%0A" & "Servicio del día " &TEXT(Tabla2[[#This Row],[FECHA ENTREGA]],"dd-mm") & "%0A" & " *Cliente:* " &Tabla2[[#This Row],[CLIENTE]] & " */ Cont: * "&Tabla2[[#This Row],[CONTENEDOR]] & "*/ HR Entrega: *" & TEXT(Tabla2[[#This Row],[HORA ENTREGA]],"hh:mm") & "* /Dirección: *" & Tabla2[[#This Row],[Dirección Entrega]] -> Hola!%0AServicio del día 02-02%0A *Cliente:* COMERCIAL E INDUSTRIAL PLASTICOS HOFFENS S.A. */ Cont: * ONEU6023062*/ HR Entrega: *08:00* /Dirección: *Hoffens: Camino Lonquén 10.707, Maipú | AG13: =IFERROR(HYPERLINK("https://wa.me/"&Tabla2[[#This Row],[CONTACTO]]&"?text="&Tabla2[[#This Row],[Mensaje]],"Enviar mensaje"),"") -> Enviar mensaje | AH13: =CONCATENATE(A13,F13) -> 12ONEU6023062 | AI13: =CONCATENATE("ENT-",A13) -> ENT-12 | AJ13: =IF(Tabla2[[#This Row],[Op]]<>"","ENTREGA","") -> ENTREGA | AK13: =(Tabla2[[#This Row],[FECHA ENTREGA]]&Tabla2[[#This Row],[HORA ENTREGA]]) -> 460550,333333333333333 | AL13: =IFERROR(HYPERLINK("https://wa.me/"&Tabla2[[#This Row],[CONTACTO]]&"?text="&Tabla2[[#This Row],[Mensaje]]),"") -> https://wa.me/56944540732?text=Hola!%0AServicio del día 02-02%0A *Cliente:* COMERCIAL E INDUSTRIAL PLASTICOS HOFFENS S.A. */ Cont: * ONEU6023062*/ HR Entrega: *08:00* /Dirección: *Hoffens: Camino Lonquén 10.707, Maipú
A14: =ROW(A13) -> 13 | B14: =IF(J14=J13,B13+1,1) -> 12 | C14: COMERCIAL PICHARA SPA | D14: IMPO | E14: 141564 | F14: MSNU3058984 | G14: 20 DV | H14: 5000 | I14: 30/01 - 18:00 | J14: 46055 | K14: 0.35416667 | M14: JORGE PACHECO PLAZA | N14: =IFERROR(VLOOKUP(M14,Data!$J$1:$K$58,2,0),"") -> 56966749395 | O14: LPYJ-43 | Q14: Olivo 672, Recoleta | R14: MEDLOG SAI | Y14: ENTREGADO | AA14: 0.3125 | AC14: 46055 | AD14: =IF(Tabla2[[#This Row],[HORA ENTREGA]]="DIRECTO","On time", IF(AA14<>"",IF(Tabla2[[#This Row],[Fecha Real Entrega]]<Tabla2[[#This Row],[FECHA ENTREGA]],"On time",IF(Tabla2[[#This Row],[Hora Real Entrega]]<=Tabla2[[#This Row],[HORA ENTREGA]]+(15/1440),"On time","Off time")),"Sin llegada")) -> On time | AE14: =MID(Tabla2[[#This Row],[TIPO]],1,3) -> 20 | AF14: ="Hola!" & "%0A" & "Servicio del día " &TEXT(Tabla2[[#This Row],[FECHA ENTREGA]],"dd-mm") & "%0A" & " *Cliente:* " &Tabla2[[#This Row],[CLIENTE]] & " */ Cont: * "&Tabla2[[#This Row],[CONTENEDOR]] & "*/ HR Entrega: *" & TEXT(Tabla2[[#This Row],[HORA ENTREGA]],"hh:mm") & "* /Dirección: *" & Tabla2[[#This Row],[Dirección Entrega]] -> Hola!%0AServicio del día 02-02%0A *Cliente:* COMERCIAL PICHARA SPA */ Cont: * MSNU3058984*/ HR Entrega: *08:30* /Dirección: *Olivo 672, Recoleta | AG14: =IFERROR(HYPERLINK("https://wa.me/"&Tabla2[[#This Row],[CONTACTO]]&"?text="&Tabla2[[#This Row],[Mensaje]],"Enviar mensaje"),"") -> Enviar mensaje | AH14: =CONCATENATE(A14,F14) -> 13MSNU3058984 | AI14: =CONCATENATE("ENT-",A14) -> ENT-13 | AJ14: =IF(Tabla2[[#This Row],[Op]]<>"","ENTREGA","") -> ENTREGA | AK14: =(Tabla2[[#This Row],[FECHA ENTREGA]]&Tabla2[[#This Row],[HORA ENTREGA]]) -> 460550,354166666666667 | AL14: =IFERROR(HYPERLINK("https://wa.me/"&Tabla2[[#This Row],[CONTACTO]]&"?text="&Tabla2[[#This Row],[Mensaje]]),"") -> https://wa.me/56966749395?text=Hola!%0AServicio del día 02-02%0A *Cliente:* COMERCIAL PICHARA SPA */ Cont: * MSNU3058984*/ HR Entrega: *08:30* /Dirección: *Olivo 672, Recoleta
A15: =ROW(A14) -> 14 | B15: =IF(J15=J14,B14+1,1) -> 13 | C15: COMERCIAL PICHARA SPA | D15: IMPO | E15: 141546 | F15: MSBU1457587 | G15: 20 DV | H15: 9000 | I15: 30/01 - 18:04 | J15: 46055 | K15: 0.58333333 | M15: DANIEL GOMEZ | N15: =IFERROR(VLOOKUP(M15,Data!$J$1:$K$58,2,0),"") -> 56993389870 | O15: LPYG-89 | Q15: Olivo 740, Recoleta | R15: MEDLOG SAI | Y15: ENTREGADO | AA15: 0.51736111 | AC15: 46055 | AD15: =IF(Tabla2[[#This Row],[HORA ENTREGA]]="DIRECTO","On time", IF(AA15<>"",IF(Tabla2[[#This Row],[Fecha Real Entrega]]<Tabla2[[#This Row],[FECHA ENTREGA]],"On time",IF(Tabla2[[#This Row],[Hora Real Entrega]]<=Tabla2[[#This Row],[HORA ENTREGA]]+(15/1440),"On time","Off time")),"Sin llegada")) -> On time | AE15: =MID(Tabla2[[#This Row],[TIPO]],1,3) -> 20 | AF15: ="Hola!" & "%0A" & "Servicio del día " &TEXT(Tabla2[[#This Row],[FECHA ENTREGA]],"dd-mm") & "%0A" & " *Cliente:* " &Tabla2[[#This Row],[CLIENTE]] & " */ Cont: * "&Tabla2[[#This Row],[CONTENEDOR]] & "*/ HR Entrega: *" & TEXT(Tabla2[[#This Row],[HORA ENTREGA]],"hh:mm") & "* /Dirección: *" & Tabla2[[#This Row],[Dirección Entrega]] -> Hola!%0AServicio del día 02-02%0A *Cliente:* COMERCIAL PICHARA SPA */ Cont: * MSBU1457587*/ HR Entrega: *14:00* /Dirección: *Olivo 740, Recoleta | AG15: =IFERROR(HYPERLINK("https://wa.me/"&Tabla2[[#This Row],[CONTACTO]]&"?text="&Tabla2[[#This Row],[Mensaje]],"Enviar mensaje"),"") -> Enviar mensaje | AH15: =CONCATENATE(A15,F15) -> 14MSBU1457587 | AI15: =CONCATENATE("ENT-",A15) -> ENT-14 | AJ15: =IF(Tabla2[[#This Row],[Op]]<>"","ENTREGA","") -> ENTREGA | AK15: =(Tabla2[[#This Row],[FECHA ENTREGA]]&Tabla2[[#This Row],[HORA ENTREGA]]) -> 460550,583333333333333 | AL15: =IFERROR(HYPERLINK("https://wa.me/"&Tabla2[[#This Row],[CONTACTO]]&"?text="&Tabla2[[#This Row],[Mensaje]]),"") -> https://wa.me/56993389870?text=Hola!%0AServicio del día 02-02%0A *Cliente:* COMERCIAL PICHARA SPA */ Cont: * MSBU1457587*/ HR Entrega: *14:00* /Dirección: *Olivo 740, Recoleta
A16: =ROW(A15) -> 15 | B16: =IF(J16=J15,B15+1,1) -> 14 | C16: COMERCIAL SANDOVAL E HIJOS LTDA | D16: IMPO | E16: 2006659 | F16: HLBU9864873 | G16: 40 HC | H16: 33000 | I16: FRAGUA | J16: 46055 | K16: 0.33333333 | M16: DANNY CARREÑO | N16: =IFERROR(VLOOKUP(M16,Data!$J$1:$K$58,2,0),"") -> 56990025702 | O16: RRVF-72 | Q16: SANTA ISABEL 370; LAMPA | R16: DYC VALP | Y16: ENTREGADO | AA16: 0.31458333 | AC16: 46055 | AD16: =IF(Tabla2[[#This Row],[HORA ENTREGA]]="DIRECTO","On time", IF(AA16<>"",IF(Tabla2[[#This Row],[Fecha Real Entrega]]<Tabla2[[#This Row],[FECHA ENTREGA]],"On time",IF(Tabla2[[#This Row],[Hora Real Entrega]]<=Tabla2[[#This Row],[HORA ENTREGA]]+(15/1440),"On time","Off time")),"Sin llegada")) -> On time | AE16: =MID(Tabla2[[#This Row],[TIPO]],1,3) -> 40 | AF16: ="Hola!" & "%0A" & "Servicio del día " &TEXT(Tabla2[[#This Row],[FECHA ENTREGA]],"dd-mm") & "%0A" & " *Cliente:* " &Tabla2[[#This Row],[CLIENTE]] & " */ Cont: * "&Tabla2[[#This Row],[CONTENEDOR]] & "*/ HR Entrega: *" & TEXT(Tabla2[[#This Row],[HORA ENTREGA]],"hh:mm") & "* /Dirección: *" & Tabla2[[#This Row],[Dirección Entrega]] -> Hola!%0AServicio del día 02-02%0A *Cliente:* COMERCIAL SANDOVAL E HIJOS LTDA */ Cont: * HLBU9864873*/ HR Entrega: *08:00* /Dirección: *SANTA ISABEL 370; LAMPA | AG16: =IFERROR(HYPERLINK("https://wa.me/"&Tabla2[[#This Row],[CONTACTO]]&"?text="&Tabla2[[#This Row],[Mensaje]],"Enviar mensaje"),"") -> Enviar mensaje | AH16: =CONCATENATE(A16,F16) -> 15HLBU9864873 | AI16: =CONCATENATE("ENT-",A16) -> ENT-15 | AJ16: =IF(Tabla2[[#This Row],[Op]]<>"","ENTREGA","") -> ENTREGA | AK16: =(Tabla2[[#This Row],[FECHA ENTREGA]]&Tabla2[[#This Row],[HORA ENTREGA]]) -> 460550,333333333333333 | AL16: =IFERROR(HYPERLINK("https://wa.me/"&Tabla2[[#This Row],[CONTACTO]]&"?text="&Tabla2[[#This Row],[Mensaje]]),"") -> https://wa.me/56990025702?text=Hola!%0AServicio del día 02-02%0A *Cliente:* COMERCIAL SANDOVAL E HIJOS LTDA */ Cont: * HLBU9864873*/ HR Entrega: *08:00* /Dirección: *SANTA ISABEL 370; LAMPA
A17: =ROW(A16) -> 16 | B17: =IF(J17=J16,B16+1,1) -> 15 | C17: FLEX EQUIPOS DE DESCANSO CHILE | D17: IMPO | E17: 298353 | F17: MRSU7190634 | G17: 40 HC | H17: 20000 | I17: 30/01 - 12:09 | J17: 46055 | K17: 0.35416667 | M17: RUBEN YAÑEZ | N17: =IFERROR(VLOOKUP(M17,Data!$J$1:$K$58,2,0),"") -> 56973887539 | O17: RRVF-71 | Q17: MERSAN (José Joaquín Prieto 9001, Lo Espejo. Bodegas: 7-8-9-10-15-16-17-18) | R17: - | Y17: ENTREGADO | AA17: 0.325 | AC17: 46055 | AD17: =IF(Tabla2[[#This Row],[HORA ENTREGA]]="DIRECTO","On time", IF(AA17<>"",IF(Tabla2[[#This Row],[Fecha Real Entrega]]<Tabla2[[#This Row],[FECHA ENTREGA]],"On time",IF(Tabla2[[#This Row],[Hora Real Entrega]]<=Tabla2[[#This Row],[HORA ENTREGA]]+(15/1440),"On time","Off time")),"Sin llegada")) -> On time | AE17: =MID(Tabla2[[#This Row],[TIPO]],1,3) -> 40 | AF17: ="Hola!" & "%0A" & "Servicio del día " &TEXT(Tabla2[[#This Row],[FECHA ENTREGA]],"dd-mm") & "%0A" & " *Cliente:* " &Tabla2[[#This Row],[CLIENTE]] & " */ Cont: * "&Tabla2[[#This Row],[CONTENEDOR]] & "*/ HR Entrega: *" & TEXT(Tabla2[[#This Row],[HORA ENTREGA]],"hh:mm") & "* /Dirección: *" & Tabla2[[#This Row],[Dirección Entrega]] -> Hola!%0AServicio del día 02-02%0A *Cliente:* FLEX EQUIPOS DE DESCANSO CHILE */ Cont: * MRSU7190634*/ HR Entrega: *08:30* /Dirección: *MERSAN (José Joaquín Prieto 9001, Lo Espejo. Bodegas: 7-8-9-10-15-16-17-18) | AG17: =IFERROR(HYPERLINK("https://wa.me/"&Tabla2[[#This Row],[CONTACTO]]&"?text="&Tabla2[[#This Row],[Mensaje]],"Enviar mensaje"),"") -> Enviar mensaje | AH17: =CONCATENATE(A17,F17) -> 16MRSU7190634 | AI17: =CONCATENATE("ENT-",A17) -> ENT-16 | AJ17: =IF(Tabla2[[#This Row],[Op]]<>"","ENTREGA","") -> ENTREGA | AK17: =(Tabla2[[#This Row],[FECHA ENTREGA]]&Tabla2[[#This Row],[HORA ENTREGA]]) -> 460550,354166666666667 | AL17: =IFERROR(HYPERLINK("https://wa.me/"&Tabla2[[#This Row],[CONTACTO]]&"?text="&Tabla2[[#This Row],[Mensaje]]),"") -> https://wa.me/56973887539?text=Hola!%0AServicio del día 02-02%0A *Cliente:* FLEX EQUIPOS DE DESCANSO CHILE */ Cont: * MRSU7190634*/ HR Entrega: *08:30* /Dirección: *MERSAN (José Joaquín Prieto 9001, Lo Espejo. Bodegas: 7-8-9-10-15-16-17-18)
A18: =ROW(A17) -> 17 | B18: =IF(J18=J17,B17+1,1) -> 16 | C18: GREENEX SPA | D18: EXPO | E18: Booking: SNG0492506 | F18: AMCU9392271 | G18: 40 RF | H18: - | I18: EXPORTACION | J18: 46055 | K18: 0.375 | M18: GABRIEL SALAS | N18: =IFERROR(VLOOKUP(M18,Data!$J$1:$K$58,2,0),"") -> 56999270871 | O18: RFZW-98 | Q18: CONSOLIDADO: PLANTA GREENEX - AV.O'HIGGINS 740, CODEGUA / EMBARQUE: STI | R18: RETIRO VACIO: AGUNSA SAI | AA18: 0.37152778 | AC18: 46055 | AD18: =IF(Tabla2[[#This Row],[HORA ENTREGA]]="DIRECTO","On time", IF(AA18<>"",IF(Tabla2[[#This Row],[Fecha Real Entrega]]<Tabla2[[#This Row],[FECHA ENTREGA]],"On time",IF(Tabla2[[#This Row],[Hora Real Entrega]]<=Tabla2[[#This Row],[HORA ENTREGA]]+(15/1440),"On time","Off time")),"Sin llegada")) -> On time | AE18: =MID(Tabla2[[#This Row],[TIPO]],1,3) -> 40 | AF18: ="Hola!" & "%0A" & "Servicio del día " &TEXT(Tabla2[[#This Row],[FECHA ENTREGA]],"dd-mm") & "%0A" & " *Cliente:* " &Tabla2[[#This Row],[CLIENTE]] & " */ Cont: * "&Tabla2[[#This Row],[CONTENEDOR]] & "*/ HR Entrega: *" & TEXT(Tabla2[[#This Row],[HORA ENTREGA]],"hh:mm") & "* /Dirección: *" & Tabla2[[#This Row],[Dirección Entrega]] -> Hola!%0AServicio del día 02-02%0A *Cliente:* GREENEX SPA */ Cont: * AMCU9392271*/ HR Entrega: *09:00* /Dirección: *CONSOLIDADO: PLANTA GREENEX - AV.O'HIGGINS 740, CODEGUA / EMBARQUE: STI | AG18: =IFERROR(HYPERLINK("https://wa.me/"&Tabla2[[#This Row],[CONTACTO]]&"?text="&Tabla2[[#This Row],[Mensaje]],"Enviar mensaje"),"") -> Enviar mensaje | AH18: =CONCATENATE(A18,F18) -> 17AMCU9392271 | AI18: =CONCATENATE("ENT-",A18) -> ENT-17 | AJ18: =IF(Tabla2[[#This Row],[Op]]<>"","ENTREGA","") -> ENTREGA | AK18: =(Tabla2[[#This Row],[FECHA ENTREGA]]&Tabla2[[#This Row],[HORA ENTREGA]]) -> 460550,375 | AL18: =IFERROR(HYPERLINK("https://wa.me/"&Tabla2[[#This Row],[CONTACTO]]&"?text="&Tabla2[[#This Row],[Mensaje]]),"") -> https://wa.me/56999270871?text=Hola!%0AServicio del día 02-02%0A *Cliente:* GREENEX SPA */ Cont: * AMCU9392271*/ HR Entrega: *09:00* /Dirección: *CONSOLIDADO: PLANTA GREENEX - AV.O'HIGGINS 740, CODEGUA / EMBARQUE: STI
A19: =ROW(A18) -> 18 | B19: =IF(J19=J18,B18+1,1) -> 17 | C19: HORTIFRUT | D19: EXPO | E19: booking: 12089088 | F19: HLBU9428740 | G19: 40 RF | H19: - | I19: EXPORTACION | J19: 46055 | K19: 0.375 | M19: ANTONIO ALCARAZ | N19: =IFERROR(VLOOKUP(M19,Data!$J$1:$K$58,2,0),"") -> 56953801607 | O19: PFVJ-33 | Q19: CONSOLIDADO: VIRQUENCO / EMBARQUE: SAI | R19: RETIRO VACIO: DYC SAI | AA19: 0.96875 | AC19: 46054 | AD19: =IF(Tabla2[[#This Row],[HORA ENTREGA]]="DIRECTO","On time", IF(AA19<>"",IF(Tabla2[[#This Row],[Fecha Real Entrega]]<Tabla2[[#This Row],[FECHA ENTREGA]],"On time",IF(Tabla2[[#This Row],[Hora Real Entrega]]<=Tabla2[[#This Row],[HORA ENTREGA]]+(15/1440),"On time","Off time")),"Sin llegada")) -> On time | AE19: =MID(Tabla2[[#This Row],[TIPO]],1,3) -> 40 | AF19: ="Hola!" & "%0A" & "Servicio del día " &TEXT(Tabla2[[#This Row],[FECHA ENTREGA]],"dd-mm") & "%0A" & " *Cliente:* " &Tabla2[[#This Row],[CLIENTE]] & " */ Cont: * "&Tabla2[[#This Row],[CONTENEDOR]] & "*/ HR Entrega: *" & TEXT(Tabla2[[#This Row],[HORA ENTREGA]],"hh:mm") & "* /Dirección: *" & Tabla2[[#This Row],[Dirección Entrega]] -> Hola!%0AServicio del día 02-02%0A *Cliente:* HORTIFRUT */ Cont: * HLBU9428740*/ HR Entrega: *09:00* /Dirección: *CONSOLIDADO: VIRQUENCO / EMBARQUE: SAI | AG19: =IFERROR(HYPERLINK("https://wa.me/"&Tabla2[[#This Row],[CONTACTO]]&"?text="&Tabla2[[#This Row],[Mensaje]],"Enviar mensaje"),"") -> Enviar mensaje | AH19: =CONCATENATE(A19,F19) -> 18HLBU9428740 | AI19: =CONCATENATE("ENT-",A19) -> ENT-18 | AJ19: =IF(Tabla2[[#This Row],[Op]]<>"","ENTREGA","") -> ENTREGA | AK19: =(Tabla2[[#This Row],[FECHA ENTREGA]]&Tabla2[[#This Row],[HORA ENTREGA]]) -> 460550,375 | AL19: =IFERROR(HYPERLINK("https://wa.me/"&Tabla2[[#This Row],[CONTACTO]]&"?text="&Tabla2[[#This Row],[Mensaje]]),"") -> https://wa.me/56953801607?text=Hola!%0AServicio del día 02-02%0A *Cliente:* HORTIFRUT */ Cont: * HLBU9428740*/ HR Entrega: *09:00* /Dirección: *CONSOLIDADO: VIRQUENCO / EMBARQUE: SAI
A20: =ROW(A19) -> 19 | B20: =IF(J20=J19,B19+1,1) -> 18 | C20: HORTIFRUT | D20: EXPO | E20: booking: SRC260001015 | F20: FDDU2543588 | G20: 40 RF | H20: - | I20: EXPORTACION | J20: 46055 | K20: 0.41666667 | M20: JUAN ESPINOZA | N20: =IFERROR(VLOOKUP(M20,Data!$J$1:$K$58,2,0),"") -> 56965312953 | O20: LGGR-15 | Q20: CONSOLIDADO: CARRERA 695, GORBEA - PLANTA HORTIFRUT GORBEA / EMBARQUE: VALP | R20: RETIRO VACIO: AGUNSA VALP | AA20: 0.010416667 | AC20: 46055 | AD20: =IF(Tabla2[[#This Row],[HORA ENTREGA]]="DIRECTO","On time", IF(AA20<>"",IF(Tabla2[[#This Row],[Fecha Real Entrega]]<Tabla2[[#This Row],[FECHA ENTREGA]],"On time",IF(Tabla2[[#This Row],[Hora Real Entrega]]<=Tabla2[[#This Row],[HORA ENTREGA]]+(15/1440),"On time","Off time")),"Sin llegada")) -> On time | AE20: =MID(Tabla2[[#This Row],[TIPO]],1,3) -> 40 | AF20: ="Hola!" & "%0A" & "Servicio del día " &TEXT(Tabla2[[#This Row],[FECHA ENTREGA]],"dd-mm") & "%0A" & " *Cliente:* " &Tabla2[[#This Row],[CLIENTE]] & " */ Cont: * "&Tabla2[[#This Row],[CONTENEDOR]] & "*/ HR Entrega: *" & TEXT(Tabla2[[#This Row],[HORA ENTREGA]],"hh:mm") & "* /Dirección: *" & Tabla2[[#This Row],[Dirección Entrega]] -> Hola!%0AServicio del día 02-02%0A *Cliente:* HORTIFRUT */ Cont: * FDDU2543588*/ HR Entrega: *10:00* /Dirección: *CONSOLIDADO: CARRERA 695, GORBEA - PLANTA HORTIFRUT GORBEA / EMBARQUE: VALP | AG20: =IFERROR(HYPERLINK("https://wa.me/"&Tabla2[[#This Row],[CONTACTO]]&"?text="&Tabla2[[#This Row],[Mensaje]],"Enviar mensaje"),"") -> Enviar mensaje | AH20: =CONCATENATE(A20,F20) -> 19FDDU2543588 | AI20: =CONCATENATE("ENT-",A20) -> ENT-19 | AJ20: =IF(Tabla2[[#This Row],[Op]]<>"","ENTREGA","") -> ENTREGA | AK20: =(Tabla2[[#This Row],[FECHA ENTREGA]]&Tabla2[[#This Row],[HORA ENTREGA]]) -> 460550,416666666666667 | AL20: =IFERROR(HYPERLINK("https://wa.me/"&Tabla2[[#This Row],[CONTACTO]]&"?text="&Tabla2[[#This Row],[Mensaje]]),"") -> https://wa.me/56965312953?text=Hola!%0AServicio del día 02-02%0A *Cliente:* HORTIFRUT */ Cont: * FDDU2543588*/ HR Entrega: *10:00* /Dirección: *CONSOLIDADO: CARRERA 695, GORBEA - PLANTA HORTIFRUT GORBEA / EMBARQUE: VALP
A21: =ROW(A20) -> 20 | B21: =IF(J21=J20,B20+1,1) -> 19 | C21: HORTIFRUT | D21: EXPO | E21: booking: 12089088 | F21: HLBU9181199 | G21: 40 RF | H21: - | I21: EXPORTACION | J21: 46055 | K21: 0.4375 | M21: JOSE ROJAS | N21: =IFERROR(VLOOKUP(M21,Data!$J$1:$K$58,2,0),"") -> 56940144795 | O21: TSYB-23 | Q21: CONSOLIDADO: VIRQUENCO / EMBARQUE: SAI | R21: RETIRO VACIO: DYC SAI | AA21: 0.97222222 | AC21: 46054 | AD21: =IF(Tabla2[[#This Row],[HORA ENTREGA]]="DIRECTO","On time", IF(AA21<>"",IF(Tabla2[[#This Row],[Fecha Real Entrega]]<Tabla2[[#This Row],[FECHA ENTREGA]],"On time",IF(Tabla2[[#This Row],[Hora Real Entrega]]<=Tabla2[[#This Row],[HORA ENTREGA]]+(15/1440),"On time","Off time")),"Sin llegada")) -> On time | AE21: =MID(Tabla2[[#This Row],[TIPO]],1,3) -> 40 | AF21: ="Hola!" & "%0A" & "Servicio del día " &TEXT(Tabla2[[#This Row],[FECHA ENTREGA]],"dd-mm") & "%0A" & " *Cliente:* " &Tabla2[[#This Row],[CLIENTE]] & " */ Cont: * "&Tabla2[[#This Row],[CONTENEDOR]] & "*/ HR Entrega: *" & TEXT(Tabla2[[#This Row],[HORA ENTREGA]],"hh:mm") & "* /Dirección: *" & Tabla2[[#This Row],[Dirección Entrega]] -> Hola!%0AServicio del día 02-02%0A *Cliente:* HORTIFRUT */ Cont: * HLBU9181199*/ HR Entrega: *10:30* /Dirección: *CONSOLIDADO: VIRQUENCO / EMBARQUE: SAI | AG21: =IFERROR(HYPERLINK("https://wa.me/"&Tabla2[[#This Row],[CONTACTO]]&"?text="&Tabla2[[#This Row],[Mensaje]],"Enviar mensaje"),"") -> Enviar mensaje | AH21: =CONCATENATE(A21,F21) -> 20HLBU9181199 | AI21: =CONCATENATE("ENT-",A21) -> ENT-20 | AJ21: =IF(Tabla2[[#This Row],[Op]]<>"","ENTREGA","") -> ENTREGA | AK21: =(Tabla2[[#This Row],[FECHA ENTREGA]]&Tabla2[[#This Row],[HORA ENTREGA]]) -> 460550,4375 | AL21: =IFERROR(HYPERLINK("https://wa.me/"&Tabla2[[#This Row],[CONTACTO]]&"?text="&Tabla2[[#This Row],[Mensaje]]),"") -> https://wa.me/56940144795?text=Hola!%0AServicio del día 02-02%0A *Cliente:* HORTIFRUT */ Cont: * HLBU9181199*/ HR Entrega: *10:30* /Dirección: *CONSOLIDADO: VIRQUENCO / EMBARQUE: SAI
A22: =ROW(A21) -> 21 | B22: =IF(J22=J21,B21+1,1) -> 20 | C22: HORTIFRUT | D22: EXPO | E22: booking: 12089088 | F22: HLBU9265140 | G22: 40 RF | H22: - | I22: EXPORTACION | J22: 46055 | K22: 0.5 | M22: JULIO CATALAN | N22: =IFERROR(VLOOKUP(M22,Data!$J$1:$K$58,2,0),"") -> 56935532735 | O22: TSYB-22 | Q22: CONSOLIDADO: VIRQUENCO / EMBARQUE: SAI | R22: RETIRO VACIO: DYC SAI | AA22: 0.97222222 | AC22: 46054 | AD22: =IF(Tabla2[[#This Row],[HORA ENTREGA]]="DIRECTO","On time", IF(AA22<>"",IF(Tabla2[[#This Row],[Fecha Real Entrega]]<Tabla2[[#This Row],[FECHA ENTREGA]],"On time",IF(Tabla2[[#This Row],[Hora Real Entrega]]<=Tabla2[[#This Row],[HORA ENTREGA]]+(15/1440),"On time","Off time")),"Sin llegada")) -> On time | AE22: =MID(Tabla2[[#This Row],[TIPO]],1,3) -> 40 | AF22: ="Hola!" & "%0A" & "Servicio del día " &TEXT(Tabla2[[#This Row],[FECHA ENTREGA]],"dd-mm") & "%0A" & " *Cliente:* " &Tabla2[[#This Row],[CLIENTE]] & " */ Cont: * "&Tabla2[[#This Row],[CONTENEDOR]] & "*/ HR Entrega: *" & TEXT(Tabla2[[#This Row],[HORA ENTREGA]],"hh:mm") & "* /Dirección: *" & Tabla2[[#This Row],[Dirección Entrega]] -> Hola!%0AServicio del día 02-02%0A *Cliente:* HORTIFRUT */ Cont: * HLBU9265140*/ HR Entrega: *12:00* /Dirección: *CONSOLIDADO: VIRQUENCO / EMBARQUE: SAI | AG22: =IFERROR(HYPERLINK("https://wa.me/"&Tabla2[[#This Row],[CONTACTO]]&"?text="&Tabla2[[#This Row],[Mensaje]],"Enviar mensaje"),"") -> Enviar mensaje | AH22: =CONCATENATE(A22,F22) -> 21HLBU9265140 | AI22: =CONCATENATE("ENT-",A22) -> ENT-21 | AJ22: =IF(Tabla2[[#This Row],[Op]]<>"","ENTREGA","") -> ENTREGA | AK22: =(Tabla2[[#This Row],[FECHA ENTREGA]]&Tabla2[[#This Row],[HORA ENTREGA]]) -> 460550,5 | AL22: =IFERROR(HYPERLINK("https://wa.me/"&Tabla2[[#This Row],[CONTACTO]]&"?text="&Tabla2[[#This Row],[Mensaje]]),"") -> https://wa.me/56935532735?text=Hola!%0AServicio del día 02-02%0A *Cliente:* HORTIFRUT */ Cont: * HLBU9265140*/ HR Entrega: *12:00* /Dirección: *CONSOLIDADO: VIRQUENCO / EMBARQUE: SAI
A23: =ROW(A22) -> 22 | B23: =IF(J23=J22,B22+1,1) -> 21 | C23: IMPORTADORA MIDEA CARRIER CHILE LTDA | D23: IMPO | E23: 2590530 | F23: TIIU6476679 | G23: 40 HC | H23: 10000 | I23: FRAGUA | J23: 46055 | K23: 0.375 | M23: JOSE SALAZAR | N23: =IFERROR(VLOOKUP(M23,Data!$J$1:$K$58,2,0),"") -> 56973887427 | O23: TRKJ-65 | Q23: BOD. MIEA AGURTO - PUERTO MADERO 9710, BOD. E13; PUDAHUEL | R23: CIS | Y23: ENTREGADO | AA23: 0.36111111 | AC23: 46055 | AD23: =IF(Tabla2[[#This Row],[HORA ENTREGA]]="DIRECTO","On time", IF(AA23<>"",IF(Tabla2[[#This Row],[Fecha Real Entrega]]<Tabla2[[#This Row],[FECHA ENTREGA]],"On time",IF(Tabla2[[#This Row],[Hora Real Entrega]]<=Tabla2[[#This Row],[HORA ENTREGA]]+(15/1440),"On time","Off time")),"Sin llegada")) -> On time | AE23: =MID(Tabla2[[#This Row],[TIPO]],1,3) -> 40 | AF23: ="Hola!" & "%0A" & "Servicio del día " &TEXT(Tabla2[[#This Row],[FECHA ENTREGA]],"dd-mm") & "%0A" & " *Cliente:* " &Tabla2[[#This Row],[CLIENTE]] & " */ Cont: * "&Tabla2[[#This Row],[CONTENEDOR]] & "*/ HR Entrega: *" & TEXT(Tabla2[[#This Row],[HORA ENTREGA]],"hh:mm") & "* /Dirección: *" & Tabla2[[#This Row],[Dirección Entrega]] -> Hola!%0AServicio del día 02-02%0A *Cliente:* IMPORTADORA MIDEA CARRIER CHILE LTDA */ Cont: * TIIU6476679*/ HR Entrega: *09:00* /Dirección: *BOD. MIEA AGURTO - PUERTO MADERO 9710, BOD. E13; PUDAHUEL | AG23: =IFERROR(HYPERLINK("https://wa.me/"&Tabla2[[#This Row],[CONTACTO]]&"?text="&Tabla2[[#This Row],[Mensaje]],"Enviar mensaje"),"") -> Enviar mensaje | AH23: =CONCATENATE(A23,F23) -> 22TIIU6476679 | AI23: =CONCATENATE("ENT-",A23) -> ENT-22 | AJ23: =IF(Tabla2[[#This Row],[Op]]<>"","ENTREGA","") -> ENTREGA | AK23: =(Tabla2[[#This Row],[FECHA ENTREGA]]&Tabla2[[#This Row],[HORA ENTREGA]]) -> 460550,375 | AL23: =IFERROR(HYPERLINK("https://wa.me/"&Tabla2[[#This Row],[CONTACTO]]&"?text="&Tabla2[[#This Row],[Mensaje]]),"") -> https://wa.me/56973887427?text=Hola!%0AServicio del día 02-02%0A *Cliente:* IMPORTADORA MIDEA CARRIER CHILE LTDA */ Cont: * TIIU6476679*/ HR Entrega: *09:00* /Dirección: *BOD. MIEA AGURTO - PUERTO MADERO 9710, BOD. E13; PUDAHUEL
A24: =ROW(A23) -> 23 | B24: =IF(J24=J23,B23+1,1) -> 22 | C24: IMPORTADORA MIDEA CARRIER CHILE LTDA | D24: IMPO | E24: 2593555 | F24: TCLU1522380 | G24: 40 HC | H24: 10000 | I24: FRAGUA | J24: 46055 | K24: 0.41666667 | M24: GERLINDHER BERNUY | N24: =IFERROR(VLOOKUP(M24,Data!$J$1:$K$58,2,0),"") -> 56926181825 | O24: RLGL-23 | Q24: BOD. MIEA AGURTO - PUERTO MADERO 9710, BOD. E13; PUDAHUEL | R24: CIS | Y24: ENTREGADO | AA24: 0.38958333 | AC24: 46055 | AD24: =IF(Tabla2[[#This Row],[HORA ENTREGA]]="DIRECTO","On time", IF(AA24<>"",IF(Tabla2[[#This Row],[Fecha Real Entrega]]<Tabla2[[#This Row],[FECHA ENTREGA]],"On time",IF(Tabla2[[#This Row],[Hora Real Entrega]]<=Tabla2[[#This Row],[HORA ENTREGA]]+(15/1440),"On time","Off time")),"Sin llegada")) -> On time | AE24: =MID(Tabla2[[#This Row],[TIPO]],1,3) -> 40 | AF24: ="Hola!" & "%0A" & "Servicio del día " &TEXT(Tabla2[[#This Row],[FECHA ENTREGA]],"dd-mm") & "%0A" & " *Cliente:* " &Tabla2[[#This Row],[CLIENTE]] & " */ Cont: * "&Tabla2[[#This Row],[CONTENEDOR]] & "*/ HR Entrega: *" & TEXT(Tabla2[[#This Row],[HORA ENTREGA]],"hh:mm") & "* /Dirección: *" & Tabla2[[#This Row],[Dirección Entrega]] -> Hola!%0AServicio del día 02-02%0A *Cliente:* IMPORTADORA MIDEA CARRIER CHILE LTDA */ Cont: * TCLU1522380*/ HR Entrega: *10:00* /Dirección: *BOD. MIEA AGURTO - PUERTO MADERO 9710, BOD. E13; PUDAHUEL | AG24: =IFERROR(HYPERLINK("https://wa.me/"&Tabla2[[#This Row],[CONTACTO]]&"?text="&Tabla2[[#This Row],[Mensaje]],"Enviar mensaje"),"") -> Enviar mensaje | AH24: =CONCATENATE(A24,F24) -> 23TCLU1522380 | AI24: =CONCATENATE("ENT-",A24) -> ENT-23 | AJ24: =IF(Tabla2[[#This Row],[Op]]<>"","ENTREGA","") -> ENTREGA | AK24: =(Tabla2[[#This Row],[FECHA ENTREGA]]&Tabla2[[#This Row],[HORA ENTREGA]]) -> 460550,416666666666667 | AL24: =IFERROR(HYPERLINK("https://wa.me/"&Tabla2[[#This Row],[CONTACTO]]&"?text="&Tabla2[[#This Row],[Mensaje]]),"") -> https://wa.me/56926181825?text=Hola!%0AServicio del día 02-02%0A *Cliente:* IMPORTADORA MIDEA CARRIER CHILE LTDA */ Cont: * TCLU1522380*/ HR Entrega: *10:00* /Dirección: *BOD. MIEA AGURTO - PUERTO MADERO 9710, BOD. E13; PUDAHUEL
A25: =ROW(A24) -> 24 | B25: =IF(J25=J24,B24+1,1) -> 23 | C25: IMPORTADORA MIDEA CARRIER CHILE LTDA | D25: IMPO | E25: 2593555 | F25: GAOU6814495 | G25: 40 HC | H25: 10000 | I25: FRAGUA | J25: 46055 | K25: 0.41666667 | M25: SEBASTIAN CUETO | N25: =IFERROR(VLOOKUP(M25,Data!$J$1:$K$58,2,0),"") -> 56931745801 | O25: THYG-62 | Q25: BOD. MIEA AGURTO - PUERTO MADERO 9710, BOD. E13; PUDAHUEL | R25: CIS | Y25: ENTREGADO | AA25: 0.33333333 | AC25: 46055 | AD25: =IF(Tabla2[[#This Row],[HORA ENTREGA]]="DIRECTO","On time", IF(AA25<>"",IF(Tabla2[[#This Row],[Fecha Real Entrega]]<Tabla2[[#This Row],[FECHA ENTREGA]],"On time",IF(Tabla2[[#This Row],[Hora Real Entrega]]<=Tabla2[[#This Row],[HORA ENTREGA]]+(15/1440),"On time","Off time")),"Sin llegada")) -> On time | AE25: =MID(Tabla2[[#This Row],[TIPO]],1,3) -> 40 | AF25: ="Hola!" & "%0A" & "Servicio del día " &TEXT(Tabla2[[#This Row],[FECHA ENTREGA]],"dd-mm") & "%0A" & " *Cliente:* " &Tabla2[[#This Row],[CLIENTE]] & " */ Cont: * "&Tabla2[[#This Row],[CONTENEDOR]] & "*/ HR Entrega: *" & TEXT(Tabla2[[#This Row],[HORA ENTREGA]],"hh:mm") & "* /Dirección: *" & Tabla2[[#This Row],[Dirección Entrega]] -> Hola!%0AServicio del día 02-02%0A *Cliente:* IMPORTADORA MIDEA CARRIER CHILE LTDA */ Cont: * GAOU6814495*/ HR Entrega: *10:00* /Dirección: *BOD. MIEA AGURTO - PUERTO MADERO 9710, BOD. E13; PUDAHUEL | AG25: =IFERROR(HYPERLINK("https://wa.me/"&Tabla2[[#This Row],[CONTACTO]]&"?text="&Tabla2[[#This Row],[Mensaje]],"Enviar mensaje"),"") -> Enviar mensaje | AH25: =CONCATENATE(A25,F25) -> 24GAOU6814495 | AI25: =CONCATENATE("ENT-",A25) -> ENT-24 | AJ25: =IF(Tabla2[[#This Row],[Op]]<>"","ENTREGA","") -> ENTREGA | AK25: =(Tabla2[[#This Row],[FECHA ENTREGA]]&Tabla2[[#This Row],[HORA ENTREGA]]) -> 460550,416666666666667 | AL25: =IFERROR(HYPERLINK("https://wa.me/"&Tabla2[[#This Row],[CONTACTO]]&"?text="&Tabla2[[#This Row],[Mensaje]]),"") -> https://wa.me/56931745801?text=Hola!%0AServicio del día 02-02%0A *Cliente:* IMPORTADORA MIDEA CARRIER CHILE LTDA */ Cont: * GAOU6814495*/ HR Entrega: *10:00* /Dirección: *BOD. MIEA AGURTO - PUERTO MADERO 9710, BOD. E13; PUDAHUEL
A26: =ROW(A25) -> 25 | B26: =IF(J26=J25,B25+1,1) -> 24 | C26: IMPORTADORA MIDEA CARRIER CHILE LTDA | D26: IMPO | E26: 2593555 | F26: TLLU4316890 | G26: 40 HC | H26: 10000 | I26: FRAGUA | J26: 46055 | K26: 0.41666667 | M26: CHARLES DIAZ | N26: =IFERROR(VLOOKUP(M26,Data!$J$1:$K$58,2,0),"") -> 56966749408 | O26: RVFP-35 | Q26: BOD. MIEA AGURTO - PUERTO MADERO 9710, BOD. E13; PUDAHUEL | R26: CIS | Y26: ENTREGADO | AA26: 0.62916667 | AC26: 46055 | AD26: =IF(Tabla2[[#This Row],[HORA ENTREGA]]="DIRECTO","On time", IF(AA26<>"",IF(Tabla2[[#This Row],[Fecha Real Entrega]]<Tabla2[[#This Row],[FECHA ENTREGA]],"On time",IF(Tabla2[[#This Row],[Hora Real Entrega]]<=Tabla2[[#This Row],[HORA ENTREGA]]+(15/1440),"On time","Off time")),"Sin llegada")) -> Off time | AE26: =MID(Tabla2[[#This Row],[TIPO]],1,3) -> 40 | AF26: ="Hola!" & "%0A" & "Servicio del día " &TEXT(Tabla2[[#This Row],[FECHA ENTREGA]],"dd-mm") & "%0A" & " *Cliente:* " &Tabla2[[#This Row],[CLIENTE]] & " */ Cont: * "&Tabla2[[#This Row],[CONTENEDOR]] & "*/ HR Entrega: *" & TEXT(Tabla2[[#This Row],[HORA ENTREGA]],"hh:mm") & "* /Dirección: *" & Tabla2[[#This Row],[Dirección Entrega]] -> Hola!%0AServicio del día 02-02%0A *Cliente:* IMPORTADORA MIDEA CARRIER CHILE LTDA */ Cont: * TLLU4316890*/ HR Entrega: *10:00* /Dirección: *BOD. MIEA AGURTO - PUERTO MADERO 9710, BOD. E13; PUDAHUEL | AG26: =IFERROR(HYPERLINK("https://wa.me/"&Tabla2[[#This Row],[CONTACTO]]&"?text="&Tabla2[[#This Row],[Mensaje]],"Enviar mensaje"),"") -> Enviar mensaje | AH26: =CONCATENATE(A26,F26) -> 25TLLU4316890 | AI26: =CONCATENATE("ENT-",A26) -> ENT-25 | AJ26: =IF(Tabla2[[#This Row],[Op]]<>"","ENTREGA","") -> ENTREGA | AK26: =(Tabla2[[#This Row],[FECHA ENTREGA]]&Tabla2[[#This Row],[HORA ENTREGA]]) -> 460550,416666666666667 | AL26: =IFERROR(HYPERLINK("https://wa.me/"&Tabla2[[#This Row],[CONTACTO]]&"?text="&Tabla2[[#This Row],[Mensaje]]),"") -> https://wa.me/56966749408?text=Hola!%0AServicio del día 02-02%0A *Cliente:* IMPORTADORA MIDEA CARRIER CHILE LTDA */ Cont: * TLLU4316890*/ HR Entrega: *10:00* /Dirección: *BOD. MIEA AGURTO - PUERTO MADERO 9710, BOD. E13; PUDAHUEL
A27: =ROW(A26) -> 26 | B27: =IF(J27=J26,B26+1,1) -> 25 | C27: IMPORTADORA MIDEA CARRIER CHILE LTDA | D27: IMPO | E27: 2593555 | F27: TRHU7873593 | G27: 40 HC | H27: 10000 | I27: FRAGUA | J27: 46055 | K27: 0.41666667 | M27: JUAN SANHUEZA | N27: =IFERROR(VLOOKUP(M27,Data!$J$1:$K$58,2,0),"") -> 56967398822 | O27: LGGR-16 | Q27: BOD. MIEA AGURTO - PUERTO MADERO 9710, BOD. E13; PUDAHUEL | R27: CIS | Y27: ENTREGADO | AA27: 0.54513889 | AC27: 46055 | AD27: =IF(Tabla2[[#This Row],[HORA ENTREGA]]="DIRECTO","On time", IF(AA27<>"",IF(Tabla2[[#This Row],[Fecha Real Entrega]]<Tabla2[[#This Row],[FECHA ENTREGA]],"On time",IF(Tabla2[[#This Row],[Hora Real Entrega]]<=Tabla2[[#This Row],[HORA ENTREGA]]+(15/1440),"On time","Off time")),"Sin llegada")) -> Off time | AE27: =MID(Tabla2[[#This Row],[TIPO]],1,3) -> 40 | AF27: ="Hola!" & "%0A" & "Servicio del día " &TEXT(Tabla2[[#This Row],[FECHA ENTREGA]],"dd-mm") & "%0A" & " *Cliente:* " &Tabla2[[#This Row],[CLIENTE]] & " */ Cont: * "&Tabla2[[#This Row],[CONTENEDOR]] & "*/ HR Entrega: *" & TEXT(Tabla2[[#This Row],[HORA ENTREGA]],"hh:mm") & "* /Dirección: *" & Tabla2[[#This Row],[Dirección Entrega]] -> Hola!%0AServicio del día 02-02%0A *Cliente:* IMPORTADORA MIDEA CARRIER CHILE LTDA */ Cont: * TRHU7873593*/ HR Entrega: *10:00* /Dirección: *BOD. MIEA AGURTO - PUERTO MADERO 9710, BOD. E13; PUDAHUEL | AG27: =IFERROR(HYPERLINK("https://wa.me/"&Tabla2[[#This Row],[CONTACTO]]&"?text="&Tabla2[[#This Row],[Mensaje]],"Enviar mensaje"),"") -> Enviar mensaje | AH27: =CONCATENATE(A27,F27) -> 26TRHU7873593 | AI27: =CONCATENATE("ENT-",A27) -> ENT-26 | AJ27: =IF(Tabla2[[#This Row],[Op]]<>"","ENTREGA","") -> ENTREGA | AK27: =(Tabla2[[#This Row],[FECHA ENTREGA]]&Tabla2[[#This Row],[HORA ENTREGA]]) -> 460550,416666666666667 | AL27: =IFERROR(HYPERLINK("https://wa.me/"&Tabla2[[#This Row],[CONTACTO]]&"?text="&Tabla2[[#This Row],[Mensaje]]),"") -> https://wa.me/56967398822?text=Hola!%0AServicio del día 02-02%0A *Cliente:* IMPORTADORA MIDEA CARRIER CHILE LTDA */ Cont: * TRHU7873593*/ HR Entrega: *10:00* /Dirección: *BOD. MIEA AGURTO - PUERTO MADERO 9710, BOD. E13; PUDAHUEL
A28: =ROW(A27) -> 27 | B28: =IF(J28=J27,B27+1,1) -> 26 | C28: IMPORTADORA Y COMERCIALIZADORA BZ SPA | D28: IMPO | E28: 871363 | F28: MSMU5843771 | G28: 40 HC | H28: 16000 | I28: FRAGUA | J28: 46055 | K28: 0.45833333 | M28: JORGE CARDENAS | N28: =IFERROR(VLOOKUP(M28,Data!$J$1:$K$58,2,0),"") -> 56944540732 | O28: KBKZ-28 | Q28: PuertoMadero 9710, Bodega X36. Pudahuel | R28: MEDLOG STGO | Y28: ENTREGADO | AA28: 0.51388889 | AC28: 46055 | AD28: =IF(Tabla2[[#This Row],[HORA ENTREGA]]="DIRECTO","On time", IF(AA28<>"",IF(Tabla2[[#This Row],[Fecha Real Entrega]]<Tabla2[[#This Row],[FECHA ENTREGA]],"On time",IF(Tabla2[[#This Row],[Hora Real Entrega]]<=Tabla2[[#This Row],[HORA ENTREGA]]+(15/1440),"On time","Off time")),"Sin llegada")) -> Off time | AE28: =MID(Tabla2[[#This Row],[TIPO]],1,3) -> 40 | AF28: ="Hola!" & "%0A" & "Servicio del día " &TEXT(Tabla2[[#This Row],[FECHA ENTREGA]],"dd-mm") & "%0A" & " *Cliente:* " &Tabla2[[#This Row],[CLIENTE]] & " */ Cont: * "&Tabla2[[#This Row],[CONTENEDOR]] & "*/ HR Entrega: *" & TEXT(Tabla2[[#This Row],[HORA ENTREGA]],"hh:mm") & "* /Dirección: *" & Tabla2[[#This Row],[Dirección Entrega]] -> Hola!%0AServicio del día 02-02%0A *Cliente:* IMPORTADORA Y COMERCIALIZADORA BZ SPA */ Cont: * MSMU5843771*/ HR Entrega: *11:00* /Dirección: *PuertoMadero 9710, Bodega X36. Pudahuel | AG28: =IFERROR(HYPERLINK("https://wa.me/"&Tabla2[[#This Row],[CONTACTO]]&"?text="&Tabla2[[#This Row],[Mensaje]],"Enviar mensaje"),"") -> Enviar mensaje | AH28: =CONCATENATE(A28,F28) -> 27MSMU5843771 | AI28: =CONCATENATE("ENT-",A28) -> ENT-27 | AJ28: =IF(Tabla2[[#This Row],[Op]]<>"","ENTREGA","") -> ENTREGA | AK28: =(Tabla2[[#This Row],[FECHA ENTREGA]]&Tabla2[[#This Row],[HORA ENTREGA]]) -> 460550,458333333333333 | AL28: =IFERROR(HYPERLINK("https://wa.me/"&Tabla2[[#This Row],[CONTACTO]]&"?text="&Tabla2[[#This Row],[Mensaje]]),"") -> https://wa.me/56944540732?text=Hola!%0AServicio del día 02-02%0A *Cliente:* IMPORTADORA Y COMERCIALIZADORA BZ SPA */ Cont: * MSMU5843771*/ HR Entrega: *11:00* /Dirección: *PuertoMadero 9710, Bodega X36. Pudahuel
A29: =ROW(A28) -> 28 | B29: =IF(J29=J28,B28+1,1) -> 27 | C29: IMPORTADORA Y COMERCIALIZADORA BZ SPA | D29: IMPO | E29: 871367 | F29: MEDU7395250 | G29: 40 HC | H29: 14000 | I29: MAIPU | J29: 46055 | K29: 0.5 | M29: JESUS GUTIERREZ | N29: =IFERROR(VLOOKUP(M29,Data!$J$1:$K$58,2,0),"") -> 56985215946 | O29: KPBC-56 | Q29: PuertoMadero 9710, Bodega X36. Pudahuel | R29: MEDLOG STGO | Y29: ENTREGADO | AA29: 0.52083333 | AC29: 46055 | AD29: =IF(Tabla2[[#This Row],[HORA ENTREGA]]="DIRECTO","On time", IF(AA29<>"",IF(Tabla2[[#This Row],[Fecha Real Entrega]]<Tabla2[[#This Row],[FECHA ENTREGA]],"On time",IF(Tabla2[[#This Row],[Hora Real Entrega]]<=Tabla2[[#This Row],[HORA ENTREGA]]+(15/1440),"On time","Off time")),"Sin llegada")) -> Off time | AE29: =MID(Tabla2[[#This Row],[TIPO]],1,3) -> 40 | AF29: ="Hola!" & "%0A" & "Servicio del día " &TEXT(Tabla2[[#This Row],[FECHA ENTREGA]],"dd-mm") & "%0A" & " *Cliente:* " &Tabla2[[#This Row],[CLIENTE]] & " */ Cont: * "&Tabla2[[#This Row],[CONTENEDOR]] & "*/ HR Entrega: *" & TEXT(Tabla2[[#This Row],[HORA ENTREGA]],"hh:mm") & "* /Dirección: *" & Tabla2[[#This Row],[Dirección Entrega]] -> Hola!%0AServicio del día 02-02%0A *Cliente:* IMPORTADORA Y COMERCIALIZADORA BZ SPA */ Cont: * MEDU7395250*/ HR Entrega: *12:00* /Dirección: *PuertoMadero 9710, Bodega X36. Pudahuel | AG29: =IFERROR(HYPERLINK("https://wa.me/"&Tabla2[[#This Row],[CONTACTO]]&"?text="&Tabla2[[#This Row],[Mensaje]],"Enviar mensaje"),"") -> Enviar mensaje | AH29: =CONCATENATE(A29,F29) -> 28MEDU7395250 | AI29: =CONCATENATE("ENT-",A29) -> ENT-28 | AJ29: =IF(Tabla2[[#This Row],[Op]]<>"","ENTREGA","") -> ENTREGA | AK29: =(Tabla2[[#This Row],[FECHA ENTREGA]]&Tabla2[[#This Row],[HORA ENTREGA]]) -> 460550,5 | AL29: =IFERROR(HYPERLINK("https://wa.me/"&Tabla2[[#This Row],[CONTACTO]]&"?text="&Tabla2[[#This Row],[Mensaje]]),"") -> https://wa.me/56985215946?text=Hola!%0AServicio del día 02-02%0A *Cliente:* IMPORTADORA Y COMERCIALIZADORA BZ SPA */ Cont: * MEDU7395250*/ HR Entrega: *12:00* /Dirección: *PuertoMadero 9710, Bodega X36. Pudahuel
A30: =ROW(A29) -> 29 | B30: =IF(J30=J29,B29+1,1) -> 28 | C30: IMPORTADORA Y COMERCIALIZADORA BZ SPA | D30: IMPO | E30: 871361 | F30: CAIU4870171 | G30: 40 FR | H30: 10000 | I30: FRAGUA | J30: 46055 | K30: 0.54166667 | M30: IVAN VASQUEZ URBINA | N30: =IFERROR(VLOOKUP(M30,Data!$J$1:$K$58,2,0),"") -> 56968463649 | O30: LGGR-12 | Q30: PuertoMadero 9710, Bodega X36. Pudahuel | R30: MEDLOG STGO | Y30: ENTREGADO | AA30: 0.67152778 | AC30: 46055 | AD30: =IF(Tabla2[[#This Row],[HORA ENTREGA]]="DIRECTO","On time", IF(AA30<>"",IF(Tabla2[[#This Row],[Fecha Real Entrega]]<Tabla2[[#This Row],[FECHA ENTREGA]],"On time",IF(Tabla2[[#This Row],[Hora Real Entrega]]<=Tabla2[[#This Row],[HORA ENTREGA]]+(15/1440),"On time","Off time")),"Sin llegada")) -> Off time | AE30: =MID(Tabla2[[#This Row],[TIPO]],1,3) -> 40 | AF30: ="Hola!" & "%0A" & "Servicio del día " &TEXT(Tabla2[[#This Row],[FECHA ENTREGA]],"dd-mm") & "%0A" & " *Cliente:* " &Tabla2[[#This Row],[CLIENTE]] & " */ Cont: * "&Tabla2[[#This Row],[CONTENEDOR]] & "*/ HR Entrega: *" & TEXT(Tabla2[[#This Row],[HORA ENTREGA]],"hh:mm") & "* /Dirección: *" & Tabla2[[#This Row],[Dirección Entrega]] -> Hola!%0AServicio del día 02-02%0A *Cliente:* IMPORTADORA Y COMERCIALIZADORA BZ SPA */ Cont: * CAIU4870171*/ HR Entrega: *13:00* /Dirección: *PuertoMadero 9710, Bodega X36. Pudahuel | AG30: =IFERROR(HYPERLINK("https://wa.me/"&Tabla2[[#This Row],[CONTACTO]]&"?text="&Tabla2[[#This Row],[Mensaje]],"Enviar mensaje"),"") -> Enviar mensaje | AH30: =CONCATENATE(A30,F30) -> 29CAIU4870171 | AI30: =CONCATENATE("ENT-",A30) -> ENT-29 | AJ30: =IF(Tabla2[[#This Row],[Op]]<>"","ENTREGA","") -> ENTREGA | AK30: =(Tabla2[[#This Row],[FECHA ENTREGA]]&Tabla2[[#This Row],[HORA ENTREGA]]) -> 460550,541666666666667 | AL30: =IFERROR(HYPERLINK("https://wa.me/"&Tabla2[[#This Row],[CONTACTO]]&"?text="&Tabla2[[#This Row],[Mensaje]]),"") -> https://wa.me/56968463649?text=Hola!%0AServicio del día 02-02%0A *Cliente:* IMPORTADORA Y COMERCIALIZADORA BZ SPA */ Cont: * CAIU4870171*/ HR Entrega: *13:00* /Dirección: *PuertoMadero 9710, Bodega X36. Pudahuel
A31: =ROW(A30) -> 30 | B31: =IF(J31=J30,B30+1,1) -> 29 | C31: INVERSIERRA S A | D31: IMPO | E31: 872409 | F31: OTPU6351111 | G31: 40 HC | H31: 23000 | I31: FRAGUA | J31: 46055 | K31: 0.33333333 | M31: PEDRO FERREIRA | N31: =IFERROR(VLOOKUP(M31,Data!$J$1:$K$58,2,0),"") -> 56956063271 | O31: KXTW-11 | Q31: HUECHURABA | R31: SITRANS SAI | Y31: ENTREGADO | AA31: 0.30694444 | AC31: 46055 | AD31: =IF(Tabla2[[#This Row],[HORA ENTREGA]]="DIRECTO","On time", IF(AA31<>"",IF(Tabla2[[#This Row],[Fecha Real Entrega]]<Tabla2[[#This Row],[FECHA ENTREGA]],"On time",IF(Tabla2[[#This Row],[Hora Real Entrega]]<=Tabla2[[#This Row],[HORA ENTREGA]]+(15/1440),"On time","Off time")),"Sin llegada")) -> On time | AE31: =MID(Tabla2[[#This Row],[TIPO]],1,3) -> 40 | AF31: ="Hola!" & "%0A" & "Servicio del día " &TEXT(Tabla2[[#This Row],[FECHA ENTREGA]],"dd-mm") & "%0A" & " *Cliente:* " &Tabla2[[#This Row],[CLIENTE]] & " */ Cont: * "&Tabla2[[#This Row],[CONTENEDOR]] & "*/ HR Entrega: *" & TEXT(Tabla2[[#This Row],[HORA ENTREGA]],"hh:mm") & "* /Dirección: *" & Tabla2[[#This Row],[Dirección Entrega]] -> Hola!%0AServicio del día 02-02%0A *Cliente:* INVERSIERRA S A */ Cont: * OTPU6351111*/ HR Entrega: *08:00* /Dirección: *HUECHURABA | AG31: =IFERROR(HYPERLINK("https://wa.me/"&Tabla2[[#This Row],[CONTACTO]]&"?text="&Tabla2[[#This Row],[Mensaje]],"Enviar mensaje"),"") -> Enviar mensaje | AH31: =CONCATENATE(A31,F31) -> 30OTPU6351111 | AI31: =CONCATENATE("ENT-",A31) -> ENT-30 | AJ31: =IF(Tabla2[[#This Row],[Op]]<>"","ENTREGA","") -> ENTREGA | AK31: =(Tabla2[[#This Row],[FECHA ENTREGA]]&Tabla2[[#This Row],[HORA ENTREGA]]) -> 460550,333333333333333 | AL31: =IFERROR(HYPERLINK("https://wa.me/"&Tabla2[[#This Row],[CONTACTO]]&"?text="&Tabla2[[#This Row],[Mensaje]]),"") -> https://wa.me/56956063271?text=Hola!%0AServicio del día 02-02%0A *Cliente:* INVERSIERRA S A */ Cont: * OTPU6351111*/ HR Entrega: *08:00* /Dirección: *HUECHURABA
A32: =ROW(A31) -> 31 | B32: =IF(J32=J31,B31+1,1) -> 30 | C32: INVERSIERRA S A | D32: IMPO | E32: 871174 | F32: MSNU5209930 | G32: 40 HC | H32: 7000 | I32: ALCATRANS | J32: 46055 | K32: 0.5 | N32: =IFERROR(VLOOKUP(M32,Data!$J$1:$K$58,2,0),"") | Q32: HUECHURABA | R32: - | Y32: PENDIENTE | Z32: FUERA DE HORARIO / REPROGRAMADO | AD32: =IF(Tabla2[[#This Row],[HORA ENTREGA]]="DIRECTO","On time", IF(AA32<>"",IF(Tabla2[[#This Row],[Fecha Real Entrega]]<Tabla2[[#This Row],[FECHA ENTREGA]],"On time",IF(Tabla2[[#This Row],[Hora Real Entrega]]<=Tabla2[[#This Row],[HORA ENTREGA]]+(15/1440),"On time","Off time")),"Sin llegada")) -> Sin llegada | AE32: =MID(Tabla2[[#This Row],[TIPO]],1,3) -> 40 | AF32: ="Hola!" & "%0A" & "Servicio del día " &TEXT(Tabla2[[#This Row],[FECHA ENTREGA]],"dd-mm") & "%0A" & " *Cliente:* " &Tabla2[[#This Row],[CLIENTE]] & " */ Cont: * "&Tabla2[[#This Row],[CONTENEDOR]] & "*/ HR Entrega: *" & TEXT(Tabla2[[#This Row],[HORA ENTREGA]],"hh:mm") & "* /Dirección: *" & Tabla2[[#This Row],[Dirección Entrega]] -> Hola!%0AServicio del día 02-02%0A *Cliente:* INVERSIERRA S A */ Cont: * MSNU5209930*/ HR Entrega: *12:00* /Dirección: *HUECHURABA | AG32: =IFERROR(HYPERLINK("https://wa.me/"&Tabla2[[#This Row],[CONTACTO]]&"?text="&Tabla2[[#This Row],[Mensaje]],"Enviar mensaje"),"") -> Enviar mensaje | AH32: =CONCATENATE(A32,F32) -> 31MSNU5209930 | AI32: =CONCATENATE("ENT-",A32) -> ENT-31 | AJ32: =IF(Tabla2[[#This Row],[Op]]<>"","ENTREGA","") -> ENTREGA | AK32: =(Tabla2[[#This Row],[FECHA ENTREGA]]&Tabla2[[#This Row],[HORA ENTREGA]]) -> 460550,5 | AL32: =IFERROR(HYPERLINK("https://wa.me/"&Tabla2[[#This Row],[CONTACTO]]&"?text="&Tabla2[[#This Row],[Mensaje]]),"") -> https://wa.me/?text=Hola!%0AServicio del día 02-02%0A *Cliente:* INVERSIERRA S A */ Cont: * MSNU5209930*/ HR Entrega: *12:00* /Dirección: *HUECHURABA
A33: =ROW(A32) -> 32 | B33: =IF(J33=J32,B32+1,1) -> 31 | C33: LAMAIGNERE CHILE S.A. | D33: IMPO | E33: 187931 | F33: CMAU5538713 | G33: 40 HC | H33: 30000 | I33: FRAGUA | J33: 46055 | K33: 0.5 | M33: SEBASTIAN CUETO | N33: =IFERROR(VLOOKUP(M33,Data!$J$1:$K$58,2,0),"") -> 56931745801 | O33: THYG-62 | Q33: AV. MARTA OSSA RUIZ 601 (CAMINO CASAS VIEJAS); MAIPU | R33: CIS | Y33: ENTREGADO | AA33: 0.56597222 | AC33: 46055 | AD33: =IF(Tabla2[[#This Row],[HORA ENTREGA]]="DIRECTO","On time", IF(AA33<>"",IF(Tabla2[[#This Row],[Fecha Real Entrega]]<Tabla2[[#This Row],[FECHA ENTREGA]],"On time",IF(Tabla2[[#This Row],[Hora Real Entrega]]<=Tabla2[[#This Row],[HORA ENTREGA]]+(15/1440),"On time","Off time")),"Sin llegada")) -> Off time | AE33: =MID(Tabla2[[#This Row],[TIPO]],1,3) -> 40 | AF33: ="Hola!" & "%0A" & "Servicio del día " &TEXT(Tabla2[[#This Row],[FECHA ENTREGA]],"dd-mm") & "%0A" & " *Cliente:* " &Tabla2[[#This Row],[CLIENTE]] & " */ Cont: * "&Tabla2[[#This Row],[CONTENEDOR]] & "*/ HR Entrega: *" & TEXT(Tabla2[[#This Row],[HORA ENTREGA]],"hh:mm") & "* /Dirección: *" & Tabla2[[#This Row],[Dirección Entrega]] -> Hola!%0AServicio del día 02-02%0A *Cliente:* LAMAIGNERE CHILE S.A. */ Cont: * CMAU5538713*/ HR Entrega: *12:00* /Dirección: *AV. MARTA OSSA RUIZ 601 (CAMINO CASAS VIEJAS); MAIPU | AG33: =IFERROR(HYPERLINK("https://wa.me/"&Tabla2[[#This Row],[CONTACTO]]&"?text="&Tabla2[[#This Row],[Mensaje]],"Enviar mensaje"),"") -> Enviar mensaje | AH33: =CONCATENATE(A33,F33) -> 32CMAU5538713 | AI33: =CONCATENATE("ENT-",A33) -> ENT-32 | AJ33: =IF(Tabla2[[#This Row],[Op]]<>"","ENTREGA","") -> ENTREGA | AK33: =(Tabla2[[#This Row],[FECHA ENTREGA]]&Tabla2[[#This Row],[HORA ENTREGA]]) -> 460550,5 | AL33: =IFERROR(HYPERLINK("https://wa.me/"&Tabla2[[#This Row],[CONTACTO]]&"?text="&Tabla2[[#This Row],[Mensaje]]),"") -> https://wa.me/56931745801?text=Hola!%0AServicio del día 02-02%0A *Cliente:* LAMAIGNERE CHILE S.A. */ Cont: * CMAU5538713*/ HR Entrega: *12:00* /Dirección: *AV. MARTA OSSA RUIZ 601 (CAMINO CASAS VIEJAS); MAIPU
A34: =ROW(A33) -> 33 | B34: =IF(J34=J33,B33+1,1) -> 32 | C34: LAMAIGNERE CHILE S.A. | D34: IMPO | E34: 187931 | F34: CAAU6267586 | G34: 40 HC | H34: 30000 | I34: FRAGUA | J34: 46055 | K34: 0.5 | M34: JUAN SAAVEDRA | N34: =IFERROR(VLOOKUP(M34,Data!$J$1:$K$58,2,0),"") -> 56967396661 | O34: KXTW-11 | Q34: AV. MARTA OSSA RUIZ 601 (CAMINO CASAS VIEJAS); MAIPU | R34: CIS | Y34: ENTREGADO | AA34: 0.57291667 | AC34: 46055 | AD34: =IF(Tabla2[[#This Row],[HORA ENTREGA]]="DIRECTO","On time", IF(AA34<>"",IF(Tabla2[[#This Row],[Fecha Real Entrega]]<Tabla2[[#This Row],[FECHA ENTREGA]],"On time",IF(Tabla2[[#This Row],[Hora Real Entrega]]<=Tabla2[[#This Row],[HORA ENTREGA]]+(15/1440),"On time","Off time")),"Sin llegada")) -> Off time | AE34: =MID(Tabla2[[#This Row],[TIPO]],1,3) -> 40 | AF34: ="Hola!" & "%0A" & "Servicio del día " &TEXT(Tabla2[[#This Row],[FECHA ENTREGA]],"dd-mm") & "%0A" & " *Cliente:* " &Tabla2[[#This Row],[CLIENTE]] & " */ Cont: * "&Tabla2[[#This Row],[CONTENEDOR]] & "*/ HR Entrega: *" & TEXT(Tabla2[[#This Row],[HORA ENTREGA]],"hh:mm") & "* /Dirección: *" & Tabla2[[#This Row],[Dirección Entrega]] -> Hola!%0AServicio del día 02-02%0A *Cliente:* LAMAIGNERE CHILE S.A. */ Cont: * CAAU6267586*/ HR Entrega: *12:00* /Dirección: *AV. MARTA OSSA RUIZ 601 (CAMINO CASAS VIEJAS); MAIPU | AG34: =IFERROR(HYPERLINK("https://wa.me/"&Tabla2[[#This Row],[CONTACTO]]&"?text="&Tabla2[[#This Row],[Mensaje]],"Enviar mensaje"),"") -> Enviar mensaje | AH34: =CONCATENATE(A34,F34) -> 33CAAU6267586 | AI34: =CONCATENATE("ENT-",A34) -> ENT-33 | AJ34: =IF(Tabla2[[#This Row],[Op]]<>"","ENTREGA","") -> ENTREGA | AK34: =(Tabla2[[#This Row],[FECHA ENTREGA]]&Tabla2[[#This Row],[HORA ENTREGA]]) -> 460550,5 | AL34: =IFERROR(HYPERLINK("https://wa.me/"&Tabla2[[#This Row],[CONTACTO]]&"?text="&Tabla2[[#This Row],[Mensaje]]),"") -> https://wa.me/56967396661?text=Hola!%0AServicio del día 02-02%0A *Cliente:* LAMAIGNERE CHILE S.A. */ Cont: * CAAU6267586*/ HR Entrega: *12:00* /Dirección: *AV. MARTA OSSA RUIZ 601 (CAMINO CASAS VIEJAS); MAIPU
A35: =ROW(A34) -> 34 | B35: =IF(J35=J34,B34+1,1) -> 33 | C35: LAMAIGNERE CHILE S.A. | D35: IMPO | E35: 187906 | F35: ECMU5095006 | G35: 40 HC | H35: 30000 | I35: FRAGUA | J35: 46055 | K35: 0.58333333 | N35: =IFERROR(VLOOKUP(M35,Data!$J$1:$K$58,2,0),"") | Q35: AV. MARTA OSSA RUIZ 601 (CAMINO CASAS VIEJAS); MAIPU | R35: CIS | Y35: PENDIENTE | Z35: FUERA DE HORARIO / REPROGRAMADO | AD35: =IF(Tabla2[[#This Row],[HORA ENTREGA]]="DIRECTO","On time", IF(AA35<>"",IF(Tabla2[[#This Row],[Fecha Real Entrega]]<Tabla2[[#This Row],[FECHA ENTREGA]],"On time",IF(Tabla2[[#This Row],[Hora Real Entrega]]<=Tabla2[[#This Row],[HORA ENTREGA]]+(15/1440),"On time","Off time")),"Sin llegada")) -> Sin llegada | AE35: =MID(Tabla2[[#This Row],[TIPO]],1,3) -> 40 | AF35: ="Hola!" & "%0A" & "Servicio del día " &TEXT(Tabla2[[#This Row],[FECHA ENTREGA]],"dd-mm") & "%0A" & " *Cliente:* " &Tabla2[[#This Row],[CLIENTE]] & " */ Cont: * "&Tabla2[[#This Row],[CONTENEDOR]] & "*/ HR Entrega: *" & TEXT(Tabla2[[#This Row],[HORA ENTREGA]],"hh:mm") & "* /Dirección: *" & Tabla2[[#This Row],[Dirección Entrega]] -> Hola!%0AServicio del día 02-02%0A *Cliente:* LAMAIGNERE CHILE S.A. */ Cont: * ECMU5095006*/ HR Entrega: *14:00* /Dirección: *AV. MARTA OSSA RUIZ 601 (CAMINO CASAS VIEJAS); MAIPU | AG35: =IFERROR(HYPERLINK("https://wa.me/"&Tabla2[[#This Row],[CONTACTO]]&"?text="&Tabla2[[#This Row],[Mensaje]],"Enviar mensaje"),"") -> Enviar mensaje | AH35: =CONCATENATE(A35,F35) -> 34ECMU5095006 | AI35: =CONCATENATE("ENT-",A35) -> ENT-34 | AJ35: =IF(Tabla2[[#This Row],[Op]]<>"","ENTREGA","") -> ENTREGA | AK35: =(Tabla2[[#This Row],[FECHA ENTREGA]]&Tabla2[[#This Row],[HORA ENTREGA]]) -> 460550,583333333333333 | AL35: =IFERROR(HYPERLINK("https://wa.me/"&Tabla2[[#This Row],[CONTACTO]]&"?text="&Tabla2[[#This Row],[Mensaje]]),"") -> https://wa.me/?text=Hola!%0AServicio del día 02-02%0A *Cliente:* LAMAIGNERE CHILE S.A. */ Cont: * ECMU5095006*/ HR Entrega: *14:00* /Dirección: *AV. MARTA OSSA RUIZ 601 (CAMINO CASAS VIEJAS); MAIPU
A36: =ROW(A35) -> 35 | B36: =IF(J36=J35,B35+1,1) -> 34 | C36: LAMAIGNERE CHILE S.A. | D36: IMPO | E36: 187967 | F36: FFAU3979718 | G36: 40 HC | H36: 30000 | I36: FRAGUA | J36: 46055 | K36: 0.58333333 | N36: =IFERROR(VLOOKUP(M36,Data!$J$1:$K$58,2,0),"") | Q36: AV. MARTA OSSA RUIZ 601 (CAMINO CASAS VIEJAS); MAIPU | R36: MEDLOG VALP | Y36: PENDIENTE | Z36: FUERA DE HORARIO / REPROGRAMADO | AD36: =IF(Tabla2[[#This Row],[HORA ENTREGA]]="DIRECTO","On time", IF(AA36<>"",IF(Tabla2[[#This Row],[Fecha Real Entrega]]<Tabla2[[#This Row],[FECHA ENTREGA]],"On time",IF(Tabla2[[#This Row],[Hora Real Entrega]]<=Tabla2[[#This Row],[HORA ENTREGA]]+(15/1440),"On time","Off time")),"Sin llegada")) -> Sin llegada | AE36: =MID(Tabla2[[#This Row],[TIPO]],1,3) -> 40 | AF36: ="Hola!" & "%0A" & "Servicio del día " &TEXT(Tabla2[[#This Row],[FECHA ENTREGA]],"dd-mm") & "%0A" & " *Cliente:* " &Tabla2[[#This Row],[CLIENTE]] & " */ Cont: * "&Tabla2[[#This Row],[CONTENEDOR]] & "*/ HR Entrega: *" & TEXT(Tabla2[[#This Row],[HORA ENTREGA]],"hh:mm") & "* /Dirección: *" & Tabla2[[#This Row],[Dirección Entrega]] -> Hola!%0AServicio del día 02-02%0A *Cliente:* LAMAIGNERE CHILE S.A. */ Cont: * FFAU3979718*/ HR Entrega: *14:00* /Dirección: *AV. MARTA OSSA RUIZ 601 (CAMINO CASAS VIEJAS); MAIPU | AG36: =IFERROR(HYPERLINK("https://wa.me/"&Tabla2[[#This Row],[CONTACTO]]&"?text="&Tabla2[[#This Row],[Mensaje]],"Enviar mensaje"),"") -> Enviar mensaje | AH36: =CONCATENATE(A36,F36) -> 35FFAU3979718 | AI36: =CONCATENATE("ENT-",A36) -> ENT-35 | AJ36: =IF(Tabla2[[#This Row],[Op]]<>"","ENTREGA","") -> ENTREGA | AK36: =(Tabla2[[#This Row],[FECHA ENTREGA]]&Tabla2[[#This Row],[HORA ENTREGA]]) -> 460550,583333333333333 | AL36: =IFERROR(HYPERLINK("https://wa.me/"&Tabla2[[#This Row],[CONTACTO]]&"?text="&Tabla2[[#This Row],[Mensaje]]),"") -> https://wa.me/?text=Hola!%0AServicio del día 02-02%0A *Cliente:* LAMAIGNERE CHILE S.A. */ Cont: * FFAU3979718*/ HR Entrega: *14:00* /Dirección: *AV. MARTA OSSA RUIZ 601 (CAMINO CASAS VIEJAS); MAIPU
A37: =ROW(A36) -> 36 | B37: =IF(J37=J36,B36+1,1) -> 35 | C37: LANCO & HARRIS SURAMERICA SPA | D37: IMPO | E37: 295542 | F37: TCLU4706185 | G37: 40 HC | H37: 17000 | I37: 30/01 - 10:50 | J37: 46055 | K37: 0.33333333 | M37: OSCAR GALAZ MORALES | N37: =IFERROR(VLOOKUP(M37,Data!$J$1:$K$58,2,0),"") -> 56975315726 | O37: KBKZ-27 | Q37: CALLE CHORRILLOS 1 PARC.19B, LAMPA | R37: SITRANS SAI | Y37: ENTREGADO | AA37: 0.38541667 | AC37: 46055 | AD37: =IF(Tabla2[[#This Row],[HORA ENTREGA]]="DIRECTO","On time", IF(AA37<>"",IF(Tabla2[[#This Row],[Fecha Real Entrega]]<Tabla2[[#This Row],[FECHA ENTREGA]],"On time",IF(Tabla2[[#This Row],[Hora Real Entrega]]<=Tabla2[[#This Row],[HORA ENTREGA]]+(15/1440),"On time","Off time")),"Sin llegada")) -> Off time | AE37: =MID(Tabla2[[#This Row],[TIPO]],1,3) -> 40 | AF37: ="Hola!" & "%0A" & "Servicio del día " &TEXT(Tabla2[[#This Row],[FECHA ENTREGA]],"dd-mm") & "%0A" & " *Cliente:* " &Tabla2[[#This Row],[CLIENTE]] & " */ Cont: * "&Tabla2[[#This Row],[CONTENEDOR]] & "*/ HR Entrega: *" & TEXT(Tabla2[[#This Row],[HORA ENTREGA]],"hh:mm") & "* /Dirección: *" & Tabla2[[#This Row],[Dirección Entrega]] -> Hola!%0AServicio del día 02-02%0A *Cliente:* LANCO & HARRIS SURAMERICA SPA */ Cont: * TCLU4706185*/ HR Entrega: *08:00* /Dirección: *CALLE CHORRILLOS 1 PARC.19B, LAMPA | AG37: =IFERROR(HYPERLINK("https://wa.me/"&Tabla2[[#This Row],[CONTACTO]]&"?text="&Tabla2[[#This Row],[Mensaje]],"Enviar mensaje"),"") -> Enviar mensaje | AH37: =CONCATENATE(A37,F37) -> 36TCLU4706185 | AI37: =CONCATENATE("ENT-",A37) -> ENT-36 | AJ37: =IF(Tabla2[[#This Row],[Op]]<>"","ENTREGA","") -> ENTREGA | AK37: =(Tabla2[[#This Row],[FECHA ENTREGA]]&Tabla2[[#This Row],[HORA ENTREGA]]) -> 460550,333333333333333 | AL37: =IFERROR(HYPERLINK("https://wa.me/"&Tabla2[[#This Row],[CONTACTO]]&"?text="&Tabla2[[#This Row],[Mensaje]]),"") -> https://wa.me/56975315726?text=Hola!%0AServicio del día 02-02%0A *Cliente:* LANCO & HARRIS SURAMERICA SPA */ Cont: * TCLU4706185*/ HR Entrega: *08:00* /Dirección: *CALLE CHORRILLOS 1 PARC.19B, LAMPA
A38: =ROW(A37) -> 37 | B38: =IF(J38=J37,B37+1,1) -> 36 | C38: LANCO & HARRIS SURAMERICA SPA | D38: IMPO | E38: 298447 | F38: ONEU2730874 | G38: 20 DV | H38: 23000 | I38: MAIPU | J38: 46055 | K38: 0.58333333 | M38: SAMUEL SALAS | N38: =IFERROR(VLOOKUP(M38,Data!$J$1:$K$58,2,0),"") -> 56950981572 | O38: KPBC-57 | Q38: CALLE CHORRILLOS 1 PARC.19B, LAMPA | R38: SITRANS SAI | Y38: ENTREGADO | AA38: 0.55555556 | AC38: 46055 | AD38: =IF(Tabla2[[#This Row],[HORA ENTREGA]]="DIRECTO","On time", IF(AA38<>"",IF(Tabla2[[#This Row],[Fecha Real Entrega]]<Tabla2[[#This Row],[FECHA ENTREGA]],"On time",IF(Tabla2[[#This Row],[Hora Real Entrega]]<=Tabla2[[#This Row],[HORA ENTREGA]]+(15/1440),"On time","Off time")),"Sin llegada")) -> On time | AE38: =MID(Tabla2[[#This Row],[TIPO]],1,3) -> 20 | AF38: ="Hola!" & "%0A" & "Servicio del día " &TEXT(Tabla2[[#This Row],[FECHA ENTREGA]],"dd-mm") & "%0A" & " *Cliente:* " &Tabla2[[#This Row],[CLIENTE]] & " */ Cont: * "&Tabla2[[#This Row],[CONTENEDOR]] & "*/ HR Entrega: *" & TEXT(Tabla2[[#This Row],[HORA ENTREGA]],"hh:mm") & "* /Dirección: *" & Tabla2[[#This Row],[Dirección Entrega]] -> Hola!%0AServicio del día 02-02%0A *Cliente:* LANCO & HARRIS SURAMERICA SPA */ Cont: * ONEU2730874*/ HR Entrega: *14:00* /Dirección: *CALLE CHORRILLOS 1 PARC.19B, LAMPA | AG38: =IFERROR(HYPERLINK("https://wa.me/"&Tabla2[[#This Row],[CONTACTO]]&"?text="&Tabla2[[#This Row],[Mensaje]],"Enviar mensaje"),"") -> Enviar mensaje | AH38: =CONCATENATE(A38,F38) -> 37ONEU2730874 | AI38: =CONCATENATE("ENT-",A38) -> ENT-37 | AJ38: =IF(Tabla2[[#This Row],[Op]]<>"","ENTREGA","") -> ENTREGA | AK38: =(Tabla2[[#This Row],[FECHA ENTREGA]]&Tabla2[[#This Row],[HORA ENTREGA]]) -> 460550,583333333333333 | AL38: =IFERROR(HYPERLINK("https://wa.me/"&Tabla2[[#This Row],[CONTACTO]]&"?text="&Tabla2[[#This Row],[Mensaje]]),"") -> https://wa.me/56950981572?text=Hola!%0AServicio del día 02-02%0A *Cliente:* LANCO & HARRIS SURAMERICA SPA */ Cont: * ONEU2730874*/ HR Entrega: *14:00* /Dirección: *CALLE CHORRILLOS 1 PARC.19B, LAMPA
A39: =ROW(A38) -> 38 | B39: =IF(J39=J38,B38+1,1) -> 37 | C39: OXIQUIM S A | D39: IMPO | E39: 482774 | F39: ZCSU7489526 | G39: 40 HC | H39: 16000 | I39: 30/01 - 16:00 | J39: 46055 | K39: 0.35416667 | M39: JUAN BARRAZA | N39: =IFERROR(VLOOKUP(M39,Data!$J$1:$K$58,2,0),"") -> 56944277110 | O39: LFHK-35 | Q39: CAÑAVERAL 901; QUILICURA | R39: AGUNSA ALCATRANS | Y39: ENTREGADO | AA39: 0.30694444 | AC39: 46055 | AD39: =IF(Tabla2[[#This Row],[HORA ENTREGA]]="DIRECTO","On time", IF(AA39<>"",IF(Tabla2[[#This Row],[Fecha Real Entrega]]<Tabla2[[#This Row],[FECHA ENTREGA]],"On time",IF(Tabla2[[#This Row],[Hora Real Entrega]]<=Tabla2[[#This Row],[HORA ENTREGA]]+(15/1440),"On time","Off time")),"Sin llegada")) -> On time | AE39: =MID(Tabla2[[#This Row],[TIPO]],1,3) -> 40 | AF39: ="Hola!" & "%0A" & "Servicio del día " &TEXT(Tabla2[[#This Row],[FECHA ENTREGA]],"dd-mm") & "%0A" & " *Cliente:* " &Tabla2[[#This Row],[CLIENTE]] & " */ Cont: * "&Tabla2[[#This Row],[CONTENEDOR]] & "*/ HR Entrega: *" & TEXT(Tabla2[[#This Row],[HORA ENTREGA]],"hh:mm") & "* /Dirección: *" & Tabla2[[#This Row],[Dirección Entrega]] -> Hola!%0AServicio del día 02-02%0A *Cliente:* OXIQUIM S A */ Cont: * ZCSU7489526*/ HR Entrega: *08:30* /Dirección: *CAÑAVERAL 901; QUILICURA | AG39: =IFERROR(HYPERLINK("https://wa.me/"&Tabla2[[#This Row],[CONTACTO]]&"?text="&Tabla2[[#This Row],[Mensaje]],"Enviar mensaje"),"") -> Enviar mensaje | AH39: =CONCATENATE(A39,F39) -> 38ZCSU7489526 | AI39: =CONCATENATE("ENT-",A39) -> ENT-38 | AJ39: =IF(Tabla2[[#This Row],[Op]]<>"","ENTREGA","") -> ENTREGA | AK39: =(Tabla2[[#This Row],[FECHA ENTREGA]]&Tabla2[[#This Row],[HORA ENTREGA]]) -> 460550,354166666666667 | AL39: =IFERROR(HYPERLINK("https://wa.me/"&Tabla2[[#This Row],[CONTACTO]]&"?text="&Tabla2[[#This Row],[Mensaje]]),"") -> https://wa.me/56944277110?text=Hola!%0AServicio del día 02-02%0A *Cliente:* OXIQUIM S A */ Cont: * ZCSU7489526*/ HR Entrega: *08:30* /Dirección: *CAÑAVERAL 901; QUILICURA
A40: =ROW(A39) -> 39 | B40: =IF(J40=J39,B39+1,1) -> 38 | C40: OXIQUIM S A | D40: IMPO | E40: 1178309 | F40: MSDU6166318 | G40: 40 HC | H40: 22000 | I40: 30/01 - 21:10 | J40: 46055 | K40: 0.35416667 | M40: JOSE AGUILAR | N40: =IFERROR(VLOOKUP(M40,Data!$J$1:$K$58,2,0),"") -> 56961282379 | O40: TSYB-25 | Q40: CAÑAVERAL 901; QUILICURA | R40: - | Y40: ENTREGADO | AA40: 0.34444444 | AC40: 46055 | AD40: =IF(Tabla2[[#This Row],[HORA ENTREGA]]="DIRECTO","On time", IF(AA40<>"",IF(Tabla2[[#This Row],[Fecha Real Entrega]]<Tabla2[[#This Row],[FECHA ENTREGA]],"On time",IF(Tabla2[[#This Row],[Hora Real Entrega]]<=Tabla2[[#This Row],[HORA ENTREGA]]+(15/1440),"On time","Off time")),"Sin llegada")) -> On time | AE40: =MID(Tabla2[[#This Row],[TIPO]],1,3) -> 40 | AF40: ="Hola!" & "%0A" & "Servicio del día " &TEXT(Tabla2[[#This Row],[FECHA ENTREGA]],"dd-mm") & "%0A" & " *Cliente:* " &Tabla2[[#This Row],[CLIENTE]] & " */ Cont: * "&Tabla2[[#This Row],[CONTENEDOR]] & "*/ HR Entrega: *" & TEXT(Tabla2[[#This Row],[HORA ENTREGA]],"hh:mm") & "* /Dirección: *" & Tabla2[[#This Row],[Dirección Entrega]] -> Hola!%0AServicio del día 02-02%0A *Cliente:* OXIQUIM S A */ Cont: * MSDU6166318*/ HR Entrega: *08:30* /Dirección: *CAÑAVERAL 901; QUILICURA | AG40: =IFERROR(HYPERLINK("https://wa.me/"&Tabla2[[#This Row],[CONTACTO]]&"?text="&Tabla2[[#This Row],[Mensaje]],"Enviar mensaje"),"") -> Enviar mensaje | AH40: =CONCATENATE(A40,F40) -> 39MSDU6166318 | AI40: =CONCATENATE("ENT-",A40) -> ENT-39 | AJ40: =IF(Tabla2[[#This Row],[Op]]<>"","ENTREGA","") -> ENTREGA | AK40: =(Tabla2[[#This Row],[FECHA ENTREGA]]&Tabla2[[#This Row],[HORA ENTREGA]]) -> 460550,354166666666667 | AL40: =IFERROR(HYPERLINK("https://wa.me/"&Tabla2[[#This Row],[CONTACTO]]&"?text="&Tabla2[[#This Row],[Mensaje]]),"") -> https://wa.me/56961282379?text=Hola!%0AServicio del día 02-02%0A *Cliente:* OXIQUIM S A */ Cont: * MSDU6166318*/ HR Entrega: *08:30* /Dirección: *CAÑAVERAL 901; QUILICURA
A41: =ROW(A40) -> 40 | B41: =IF(J41=J40,B40+1,1) -> 39 | C41: PTM CHILE LTDA | D41: IMPO | E41: 298168 | F41: UACU5939642 | G41: 40 HC | H41: 5000 | I41: ALCATRANS | J41: 46055 | K41: 0.375 | M41: CARLOS ALBERTO DIAZ | N41: =IFERROR(VLOOKUP(M41,Data!$J$1:$K$58,2,0),"") -> 56978089957 | O41: RVFP-33 | Q41: Issa Pichara 830, Bodega 5D, renca | R41: CONTOPSA SAI | Y41: ENTREGADO | AA41: 0.42361111 | AC41: 46055 | AD41: =IF(Tabla2[[#This Row],[HORA ENTREGA]]="DIRECTO","On time", IF(AA41<>"",IF(Tabla2[[#This Row],[Fecha Real Entrega]]<Tabla2[[#This Row],[FECHA ENTREGA]],"On time",IF(Tabla2[[#This Row],[Hora Real Entrega]]<=Tabla2[[#This Row],[HORA ENTREGA]]+(15/1440),"On time","Off time")),"Sin llegada")) -> Off time | AE41: =MID(Tabla2[[#This Row],[TIPO]],1,3) -> 40 | AF41: ="Hola!" & "%0A" & "Servicio del día " &TEXT(Tabla2[[#This Row],[FECHA ENTREGA]],"dd-mm") & "%0A" & " *Cliente:* " &Tabla2[[#This Row],[CLIENTE]] & " */ Cont: * "&Tabla2[[#This Row],[CONTENEDOR]] & "*/ HR Entrega: *" & TEXT(Tabla2[[#This Row],[HORA ENTREGA]],"hh:mm") & "* /Dirección: *" & Tabla2[[#This Row],[Dirección Entrega]] -> Hola!%0AServicio del día 02-02%0A *Cliente:* PTM CHILE LTDA */ Cont: * UACU5939642*/ HR Entrega: *09:00* /Dirección: *Issa Pichara 830, Bodega 5D, renca | AG41: =IFERROR(HYPERLINK("https://wa.me/"&Tabla2[[#This Row],[CONTACTO]]&"?text="&Tabla2[[#This Row],[Mensaje]],"Enviar mensaje"),"") -> Enviar mensaje | AH41: =CONCATENATE(A41,F41) -> 40UACU5939642 | AI41: =CONCATENATE("ENT-",A41) -> ENT-40 | AJ41: =IF(Tabla2[[#This Row],[Op]]<>"","ENTREGA","") -> ENTREGA | AK41: =(Tabla2[[#This Row],[FECHA ENTREGA]]&Tabla2[[#This Row],[HORA ENTREGA]]) -> 460550,375 | AL41: =IFERROR(HYPERLINK("https://wa.me/"&Tabla2[[#This Row],[CONTACTO]]&"?text="&Tabla2[[#This Row],[Mensaje]]),"") -> https://wa.me/56978089957?text=Hola!%0AServicio del día 02-02%0A *Cliente:* PTM CHILE LTDA */ Cont: * UACU5939642*/ HR Entrega: *09:00* /Dirección: *Issa Pichara 830, Bodega 5D, renca
A42: =ROW(A41) -> 41 | B42: =IF(J42=J41,B41+1,1) -> 40 | C42: RENDIC S.A. | D42: IMPO | E42: 102086 | F42: FANU1104109 | G42: 40 HC | H42: 10000 | I42: FRAGUA | J42: 46055 | K42: 0.29166667 | M42: JOSE VENEGAS | N42: =IFERROR(VLOOKUP(M42,Data!$J$1:$K$58,2,0),"") -> 56965378427 | O42: RRVF-70 | Q42: CAMINO A CORONEL KM. 11 N°6060, MEGACENTRO 2, SAN PEDRO DE LA PAZ | R42: CONTOPSA SAI | Y42: ENTREGADO | AA42: 0.9375 | AC42: 46054 | AD42: =IF(Tabla2[[#This Row],[HORA ENTREGA]]="DIRECTO","On time", IF(AA42<>"",IF(Tabla2[[#This Row],[Fecha Real Entrega]]<Tabla2[[#This Row],[FECHA ENTREGA]],"On time",IF(Tabla2[[#This Row],[Hora Real Entrega]]<=Tabla2[[#This Row],[HORA ENTREGA]]+(15/1440),"On time","Off time")),"Sin llegada")) -> On time | AE42: =MID(Tabla2[[#This Row],[TIPO]],1,3) -> 40 | AF42: ="Hola!" & "%0A" & "Servicio del día " &TEXT(Tabla2[[#This Row],[FECHA ENTREGA]],"dd-mm") & "%0A" & " *Cliente:* " &Tabla2[[#This Row],[CLIENTE]] & " */ Cont: * "&Tabla2[[#This Row],[CONTENEDOR]] & "*/ HR Entrega: *" & TEXT(Tabla2[[#This Row],[HORA ENTREGA]],"hh:mm") & "* /Dirección: *" & Tabla2[[#This Row],[Dirección Entrega]] -> Hola!%0AServicio del día 02-02%0A *Cliente:* RENDIC S.A. */ Cont: * FANU1104109*/ HR Entrega: *07:00* /Dirección: *CAMINO A CORONEL KM. 11 N°6060, MEGACENTRO 2, SAN PEDRO DE LA PAZ | AG42: =IFERROR(HYPERLINK("https://wa.me/"&Tabla2[[#This Row],[CONTACTO]]&"?text="&Tabla2[[#This Row],[Mensaje]],"Enviar mensaje"),"") -> Enviar mensaje | AH42: =CONCATENATE(A42,F42) -> 41FANU1104109 | AI42: =CONCATENATE("ENT-",A42) -> ENT-41 | AJ42: =IF(Tabla2[[#This Row],[Op]]<>"","ENTREGA","") -> ENTREGA | AK42: =(Tabla2[[#This Row],[FECHA ENTREGA]]&Tabla2[[#This Row],[HORA ENTREGA]]) -> 460550,291666666666667 | AL42: =IFERROR(HYPERLINK("https://wa.me/"&Tabla2[[#This Row],[CONTACTO]]&"?text="&Tabla2[[#This Row],[Mensaje]]),"") -> https://wa.me/56965378427?text=Hola!%0AServicio del día 02-02%0A *Cliente:* RENDIC S.A. */ Cont: * FANU1104109*/ HR Entrega: *07:00* /Dirección: *CAMINO A CORONEL KM. 11 N°6060, MEGACENTRO 2, SAN PEDRO DE LA PAZ
A43: =ROW(A42) -> 42 | B43: =IF(J43=J42,B42+1,1) -> 41 | C43: RENDIC S.A. | D43: IMPO | E43: 102355 | F43: MEDU4854757 | G43: 40 HC | H43: 10000 | I43: FRAGUA | J43: 46055 | K43: 0.35416667 | M43: OSCAR SANCHEZ | N43: =IFERROR(VLOOKUP(M43,Data!$J$1:$K$58,2,0),"") -> 56978811158 | O43: PFVJ-36 | Q43: PARCELA 109 A COQUIMBO | R43: MEDLOG VALP | Y43: ENTREGADO | AA43: 0.93055556 | AC43: 46054 | AD43: =IF(Tabla2[[#This Row],[HORA ENTREGA]]="DIRECTO","On time", IF(AA43<>"",IF(Tabla2[[#This Row],[Fecha Real Entrega]]<Tabla2[[#This Row],[FECHA ENTREGA]],"On time",IF(Tabla2[[#This Row],[Hora Real Entrega]]<=Tabla2[[#This Row],[HORA ENTREGA]]+(15/1440),"On time","Off time")),"Sin llegada")) -> On time | AE43: =MID(Tabla2[[#This Row],[TIPO]],1,3) -> 40 | AF43: ="Hola!" & "%0A" & "Servicio del día " &TEXT(Tabla2[[#This Row],[FECHA ENTREGA]],"dd-mm") & "%0A" & " *Cliente:* " &Tabla2[[#This Row],[CLIENTE]] & " */ Cont: * "&Tabla2[[#This Row],[CONTENEDOR]] & "*/ HR Entrega: *" & TEXT(Tabla2[[#This Row],[HORA ENTREGA]],"hh:mm") & "* /Dirección: *" & Tabla2[[#This Row],[Dirección Entrega]] -> Hola!%0AServicio del día 02-02%0A *Cliente:* RENDIC S.A. */ Cont: * MEDU4854757*/ HR Entrega: *08:30* /Dirección: *PARCELA 109 A COQUIMBO | AG43: =IFERROR(HYPERLINK("https://wa.me/"&Tabla2[[#This Row],[CONTACTO]]&"?text="&Tabla2[[#This Row],[Mensaje]],"Enviar mensaje"),"") -> Enviar mensaje | AH43: =CONCATENATE(A43,F43) -> 42MEDU4854757 | AI43: =CONCATENATE("ENT-",A43) -> ENT-42 | AJ43: =IF(Tabla2[[#This Row],[Op]]<>"","ENTREGA","") -> ENTREGA | AK43: =(Tabla2[[#This Row],[FECHA ENTREGA]]&Tabla2[[#This Row],[HORA ENTREGA]]) -> 460550,354166666666667 | AL43: =IFERROR(HYPERLINK("https://wa.me/"&Tabla2[[#This Row],[CONTACTO]]&"?text="&Tabla2[[#This Row],[Mensaje]]),"") -> https://wa.me/56978811158?text=Hola!%0AServicio del día 02-02%0A *Cliente:* RENDIC S.A. */ Cont: * MEDU4854757*/ HR Entrega: *08:30* /Dirección: *PARCELA 109 A COQUIMBO
A44: =ROW(A43) -> 43 | B44: =IF(J44=J43,B43+1,1) -> 42 | C44: RENDIC S.A. | D44: IMPO | E44: 102234 | F44: CMAU6200628 | G44: 40 HC | H44: 21000 | I44: FRAGUA | J44: 46055 | K44: 0.45833333 | M44: JOSE SALAZAR | N44: =IFERROR(VLOOKUP(M44,Data!$J$1:$K$58,2,0),"") -> 56973887427 | O44: TRKJ-65 | Q44: Avenida Miraflores 9700-Bodega 4C, PUDAHUEL | R44: CIS | Y44: ENTREGADO | AA44: 0.52638889 | AC44: 46055 | AD44: =IF(Tabla2[[#This Row],[HORA ENTREGA]]="DIRECTO","On time", IF(AA44<>"",IF(Tabla2[[#This Row],[Fecha Real Entrega]]<Tabla2[[#This Row],[FECHA ENTREGA]],"On time",IF(Tabla2[[#This Row],[Hora Real Entrega]]<=Tabla2[[#This Row],[HORA ENTREGA]]+(15/1440),"On time","Off time")),"Sin llegada")) -> Off time | AE44: =MID(Tabla2[[#This Row],[TIPO]],1,3) -> 40 | AF44: ="Hola!" & "%0A" & "Servicio del día " &TEXT(Tabla2[[#This Row],[FECHA ENTREGA]],"dd-mm") & "%0A" & " *Cliente:* " &Tabla2[[#This Row],[CLIENTE]] & " */ Cont: * "&Tabla2[[#This Row],[CONTENEDOR]] & "*/ HR Entrega: *" & TEXT(Tabla2[[#This Row],[HORA ENTREGA]],"hh:mm") & "* /Dirección: *" & Tabla2[[#This Row],[Dirección Entrega]] -> Hola!%0AServicio del día 02-02%0A *Cliente:* RENDIC S.A. */ Cont: * CMAU6200628*/ HR Entrega: *11:00* /Dirección: *Avenida Miraflores 9700-Bodega 4C, PUDAHUEL | AG44: =IFERROR(HYPERLINK("https://wa.me/"&Tabla2[[#This Row],[CONTACTO]]&"?text="&Tabla2[[#This Row],[Mensaje]],"Enviar mensaje"),"") -> Enviar mensaje | AH44: =CONCATENATE(A44,F44) -> 43CMAU6200628 | AI44: =CONCATENATE("ENT-",A44) -> ENT-43 | AJ44: =IF(Tabla2[[#This Row],[Op]]<>"","ENTREGA","") -> ENTREGA | AK44: =(Tabla2[[#This Row],[FECHA ENTREGA]]&Tabla2[[#This Row],[HORA ENTREGA]]) -> 460550,458333333333333 | AL44: =IFERROR(HYPERLINK("https://wa.me/"&Tabla2[[#This Row],[CONTACTO]]&"?text="&Tabla2[[#This Row],[Mensaje]]),"") -> https://wa.me/56973887427?text=Hola!%0AServicio del día 02-02%0A *Cliente:* RENDIC S.A. */ Cont: * CMAU6200628*/ HR Entrega: *11:00* /Dirección: *Avenida Miraflores 9700-Bodega 4C, PUDAHUEL
A45: =ROW(A44) -> 44 | B45: =IF(J45=J44,B44+1,1) -> 43 | C45: SISTEMAS HIDRAULICOS E INDUSTRIALES BALFLEX CHILE | D45: IMPO | E45: 141627 | F45: MRKU0784694 | G45: 40 HC | H45: 6000 | I45: 30/01 - 14:00 | J45: 46055 | K45: 0.39583333 | M45: GUSTAVO VEGA ARAYA | N45: =IFERROR(VLOOKUP(M45,Data!$J$1:$K$58,2,0),"") -> 56998494086 | O45: KKWG-93 | Q45: SANTA ADELA 10120 MAIPU | R45: CONTOPSA SAI | Y45: ENTREGADO | AA45: 0.38333333 | AC45: 46055 | AD45: =IF(Tabla2[[#This Row],[HORA ENTREGA]]="DIRECTO","On time", IF(AA45<>"",IF(Tabla2[[#This Row],[Fecha Real Entrega]]<Tabla2[[#This Row],[FECHA ENTREGA]],"On time",IF(Tabla2[[#This Row],[Hora Real Entrega]]<=Tabla2[[#This Row],[HORA ENTREGA]]+(15/1440),"On time","Off time")),"Sin llegada")) -> On time | AE45: =MID(Tabla2[[#This Row],[TIPO]],1,3) -> 40 | AF45: ="Hola!" & "%0A" & "Servicio del día " &TEXT(Tabla2[[#This Row],[FECHA ENTREGA]],"dd-mm") & "%0A" & " *Cliente:* " &Tabla2[[#This Row],[CLIENTE]] & " */ Cont: * "&Tabla2[[#This Row],[CONTENEDOR]] & "*/ HR Entrega: *" & TEXT(Tabla2[[#This Row],[HORA ENTREGA]],"hh:mm") & "* /Dirección: *" & Tabla2[[#This Row],[Dirección Entrega]] -> Hola!%0AServicio del día 02-02%0A *Cliente:* SISTEMAS HIDRAULICOS E INDUSTRIALES BALFLEX CHILE */ Cont: * MRKU0784694*/ HR Entrega: *09:30* /Dirección: *SANTA ADELA 10120 MAIPU | AG45: =IFERROR(HYPERLINK("https://wa.me/"&Tabla2[[#This Row],[CONTACTO]]&"?text="&Tabla2[[#This Row],[Mensaje]],"Enviar mensaje"),"") -> Enviar mensaje | AH45: =CONCATENATE(A45,F45) -> 44MRKU0784694 | AI45: =CONCATENATE("ENT-",A45) -> ENT-44 | AJ45: =IF(Tabla2[[#This Row],[Op]]<>"","ENTREGA","") -> ENTREGA | AK45: =(Tabla2[[#This Row],[FECHA ENTREGA]]&Tabla2[[#This Row],[HORA ENTREGA]]) -> 460550,395833333333333 | AL45: =IFERROR(HYPERLINK("https://wa.me/"&Tabla2[[#This Row],[CONTACTO]]&"?text="&Tabla2[[#This Row],[Mensaje]]),"") -> https://wa.me/56998494086?text=Hola!%0AServicio del día 02-02%0A *Cliente:* SISTEMAS HIDRAULICOS E INDUSTRIALES BALFLEX CHILE */ Cont: * MRKU0784694*/ HR Entrega: *09:30* /Dirección: *SANTA ADELA 10120 MAIPU
A46: =ROW(A45) -> 45 | B46: =IF(J46=J45,B45+1,1) -> 44 | C46: SOCIEDAD COMERCIAL MARBEN PETS LTDA | D46: IMPO | E46: 504946 | F46: SEGU2135046 | G46: 20 DV | H46: 30000 | I46: FRAGUA | J46: 46055 | K46: 0.41666667 | M46: JESUS GUTIERREZ | N46: =IFERROR(VLOOKUP(M46,Data!$J$1:$K$58,2,0),"") -> 56985215946 | O46: KPBC-56 | Q46: CARRETERA GENERAL SAN MARTIN 8250 BODEGA A 21 QUILICURA | R46: CIS | Y46: ENTREGADO | AA46: 0.37847222 | AC46: 46055 | AD46: =IF(Tabla2[[#This Row],[HORA ENTREGA]]="DIRECTO","On time", IF(AA46<>"",IF(Tabla2[[#This Row],[Fecha Real Entrega]]<Tabla2[[#This Row],[FECHA ENTREGA]],"On time",IF(Tabla2[[#This Row],[Hora Real Entrega]]<=Tabla2[[#This Row],[HORA ENTREGA]]+(15/1440),"On time","Off time")),"Sin llegada")) -> On time | AE46: =MID(Tabla2[[#This Row],[TIPO]],1,3) -> 20 | AF46: ="Hola!" & "%0A" & "Servicio del día " &TEXT(Tabla2[[#This Row],[FECHA ENTREGA]],"dd-mm") & "%0A" & " *Cliente:* " &Tabla2[[#This Row],[CLIENTE]] & " */ Cont: * "&Tabla2[[#This Row],[CONTENEDOR]] & "*/ HR Entrega: *" & TEXT(Tabla2[[#This Row],[HORA ENTREGA]],"hh:mm") & "* /Dirección: *" & Tabla2[[#This Row],[Dirección Entrega]] -> Hola!%0AServicio del día 02-02%0A *Cliente:* SOCIEDAD COMERCIAL MARBEN PETS LTDA */ Cont: * SEGU2135046*/ HR Entrega: *10:00* /Dirección: *CARRETERA GENERAL SAN MARTIN 8250 BODEGA A 21 QUILICURA | AG46: =IFERROR(HYPERLINK("https://wa.me/"&Tabla2[[#This Row],[CONTACTO]]&"?text="&Tabla2[[#This Row],[Mensaje]],"Enviar mensaje"),"") -> Enviar mensaje | AH46: =CONCATENATE(A46,F46) -> 45SEGU2135046 | AI46: =CONCATENATE("ENT-",A46) -> ENT-45 | AJ46: =IF(Tabla2[[#This Row],[Op]]<>"","ENTREGA","") -> ENTREGA | AK46: =(Tabla2[[#This Row],[FECHA ENTREGA]]&Tabla2[[#This Row],[HORA ENTREGA]]) -> 460550,416666666666667 | AL46: =IFERROR(HYPERLINK("https://wa.me/"&Tabla2[[#This Row],[CONTACTO]]&"?text="&Tabla2[[#This Row],[Mensaje]]),"") -> https://wa.me/56985215946?text=Hola!%0AServicio del día 02-02%0A *Cliente:* SOCIEDAD COMERCIAL MARBEN PETS LTDA */ Cont: * SEGU2135046*/ HR Entrega: *10:00* /Dirección: *CARRETERA GENERAL SAN MARTIN 8250 BODEGA A 21 QUILICURA
A47: =ROW(A46) -> 46 | B47: =IF(J47=J46,B46+1,1) -> 45 | C47: SUPERMERCADO DEL NEUMATICO LTDA | D47: IMPO | E47: 298211 | F47: HASU4281221 | G47: 40 HC | H47: 15000 | I47: FRAGUA | J47: 46055 | K47: 0.33333333 | M47: PEDRO JOSE CARRILLO | N47: =IFERROR(VLOOKUP(M47,Data!$J$1:$K$58,2,0),"") -> 56984880436 | O47: HLGX-83 | Q47: VELASQUEZ | R47: CONTOPSA SAI | Y47: ENTREGADO | AA47: 0.32638889 | AC47: 46055 | AD47: =IF(Tabla2[[#This Row],[HORA ENTREGA]]="DIRECTO","On time", IF(AA47<>"",IF(Tabla2[[#This Row],[Fecha Real Entrega]]<Tabla2[[#This Row],[FECHA ENTREGA]],"On time",IF(Tabla2[[#This Row],[Hora Real Entrega]]<=Tabla2[[#This Row],[HORA ENTREGA]]+(15/1440),"On time","Off time")),"Sin llegada")) -> On time | AE47: =MID(Tabla2[[#This Row],[TIPO]],1,3) -> 40 | AF47: ="Hola!" & "%0A" & "Servicio del día " &TEXT(Tabla2[[#This Row],[FECHA ENTREGA]],"dd-mm") & "%0A" & " *Cliente:* " &Tabla2[[#This Row],[CLIENTE]] & " */ Cont: * "&Tabla2[[#This Row],[CONTENEDOR]] & "*/ HR Entrega: *" & TEXT(Tabla2[[#This Row],[HORA ENTREGA]],"hh:mm") & "* /Dirección: *" & Tabla2[[#This Row],[Dirección Entrega]] -> Hola!%0AServicio del día 02-02%0A *Cliente:* SUPERMERCADO DEL NEUMATICO LTDA */ Cont: * HASU4281221*/ HR Entrega: *08:00* /Dirección: *VELASQUEZ | AG47: =IFERROR(HYPERLINK("https://wa.me/"&Tabla2[[#This Row],[CONTACTO]]&"?text="&Tabla2[[#This Row],[Mensaje]],"Enviar mensaje"),"") -> Enviar mensaje | AH47: =CONCATENATE(A47,F47) -> 46HASU4281221 | AI47: =CONCATENATE("ENT-",A47) -> ENT-46 | AJ47: =IF(Tabla2[[#This Row],[Op]]<>"","ENTREGA","") -> ENTREGA | AK47: =(Tabla2[[#This Row],[FECHA ENTREGA]]&Tabla2[[#This Row],[HORA ENTREGA]]) -> 460550,333333333333333 | AL47: =IFERROR(HYPERLINK("https://wa.me/"&Tabla2[[#This Row],[CONTACTO]]&"?text="&Tabla2[[#This Row],[Mensaje]]),"") -> https://wa.me/56984880436?text=Hola!%0AServicio del día 02-02%0A *Cliente:* SUPERMERCADO DEL NEUMATICO LTDA */ Cont: * HASU4281221*/ HR Entrega: *08:00* /Dirección: *VELASQUEZ
A48: =ROW(A47) -> 47 | B48: =IF(J48=J47,B47+1,1) -> 46 | C48: VILLAR HERMANOS S.A. | D48: IMPO | E48: 527896 | F48: TCLU3844430 | G48: 20 DV | H48: 23000 | I48: 31/01 - 14:51 | J48: 46055 | K48: 0.375 | M48: IVAN VASQUEZ FERNANDEZ | N48: =IFERROR(VLOOKUP(M48,Data!$J$1:$K$58,2,0),"") -> 56953157599 | O48: RKLF-60 | Q48: SALAR DE ATACAMA 1330, PUDAHUEL | R48: AGUNSA VALP | Y48: ENTREGADO | AA48: 0.35763889 | AC48: 46055 | AD48: =IF(Tabla2[[#This Row],[HORA ENTREGA]]="DIRECTO","On time", IF(AA48<>"",IF(Tabla2[[#This Row],[Fecha Real Entrega]]<Tabla2[[#This Row],[FECHA ENTREGA]],"On time",IF(Tabla2[[#This Row],[Hora Real Entrega]]<=Tabla2[[#This Row],[HORA ENTREGA]]+(15/1440),"On time","Off time")),"Sin llegada")) -> On time | AE48: =MID(Tabla2[[#This Row],[TIPO]],1,3) -> 20 | AF48: ="Hola!" & "%0A" & "Servicio del día " &TEXT(Tabla2[[#This Row],[FECHA ENTREGA]],"dd-mm") & "%0A" & " *Cliente:* " &Tabla2[[#This Row],[CLIENTE]] & " */ Cont: * "&Tabla2[[#This Row],[CONTENEDOR]] & "*/ HR Entrega: *" & TEXT(Tabla2[[#This Row],[HORA ENTREGA]],"hh:mm") & "* /Dirección: *" & Tabla2[[#This Row],[Dirección Entrega]] -> Hola!%0AServicio del día 02-02%0A *Cliente:* VILLAR HERMANOS S.A. */ Cont: * TCLU3844430*/ HR Entrega: *09:00* /Dirección: *SALAR DE ATACAMA 1330, PUDAHUEL | AG48: =IFERROR(HYPERLINK("https://wa.me/"&Tabla2[[#This Row],[CONTACTO]]&"?text="&Tabla2[[#This Row],[Mensaje]],"Enviar mensaje"),"") -> Enviar mensaje | AH48: =CONCATENATE(A48,F48) -> 47TCLU3844430 | AI48: =CONCATENATE("ENT-",A48) -> ENT-47 | AJ48: =IF(Tabla2[[#This Row],[Op]]<>"","ENTREGA","") -> ENTREGA | AK48: =(Tabla2[[#This Row],[FECHA ENTREGA]]&Tabla2[[#This Row],[HORA ENTREGA]]) -> 460550,375 | AL48: =IFERROR(HYPERLINK("https://wa.me/"&Tabla2[[#This Row],[CONTACTO]]&"?text="&Tabla2[[#This Row],[Mensaje]]),"") -> https://wa.me/56953157599?text=Hola!%0AServicio del día 02-02%0A *Cliente:* VILLAR HERMANOS S.A. */ Cont: * TCLU3844430*/ HR Entrega: *09:00* /Dirección: *SALAR DE ATACAMA 1330, PUDAHUEL
A49: =ROW(A48) -> 48 | B49: =IF(J49=J48,B48+1,1) -> 47 | C49: VILLAR HERMANOS S.A. | D49: IMPO | E49: 527965 | F49: TIIU2925771 | G49: 40 HC | H49: 4000 | I49: 30/01 - 14:18 | J49: 46055 | K49: 0.625 | M49: JORGE PACHECO PLAZA | N49: =IFERROR(VLOOKUP(M49,Data!$J$1:$K$58,2,0),"") -> 56966749395 | O49: RVFP-31 | Q49: SALAR DE ATACAMA 1330, PUDAHUEL | R49: CIS | Y49: ENTREGADO | AA49: 0.66180556 | AC49: 46055 | AD49: =IF(Tabla2[[#This Row],[HORA ENTREGA]]="DIRECTO","On time", IF(AA49<>"",IF(Tabla2[[#This Row],[Fecha Real Entrega]]<Tabla2[[#This Row],[FECHA ENTREGA]],"On time",IF(Tabla2[[#This Row],[Hora Real Entrega]]<=Tabla2[[#This Row],[HORA ENTREGA]]+(15/1440),"On time","Off time")),"Sin llegada")) -> Off time | AE49: =MID(Tabla2[[#This Row],[TIPO]],1,3) -> 40 | AF49: ="Hola!" & "%0A" & "Servicio del día " &TEXT(Tabla2[[#This Row],[FECHA ENTREGA]],"dd-mm") & "%0A" & " *Cliente:* " &Tabla2[[#This Row],[CLIENTE]] & " */ Cont: * "&Tabla2[[#This Row],[CONTENEDOR]] & "*/ HR Entrega: *" & TEXT(Tabla2[[#This Row],[HORA ENTREGA]],"hh:mm") & "* /Dirección: *" & Tabla2[[#This Row],[Dirección Entrega]] -> Hola!%0AServicio del día 02-02%0A *Cliente:* VILLAR HERMANOS S.A. */ Cont: * TIIU2925771*/ HR Entrega: *15:00* /Dirección: *SALAR DE ATACAMA 1330, PUDAHUEL | AG49: =IFERROR(HYPERLINK("https://wa.me/"&Tabla2[[#This Row],[CONTACTO]]&"?text="&Tabla2[[#This Row],[Mensaje]],"Enviar mensaje"),"") -> Enviar mensaje | AH49: =CONCATENATE(A49,F49) -> 48TIIU2925771 | AI49: =CONCATENATE("ENT-",A49) -> ENT-48 | AJ49: =IF(Tabla2[[#This Row],[Op]]<>"","ENTREGA","") -> ENTREGA | AK49: =(Tabla2[[#This Row],[FECHA ENTREGA]]&Tabla2[[#This Row],[HORA ENTREGA]]) -> 460550,625 | AL49: =IFERROR(HYPERLINK("https://wa.me/"&Tabla2[[#This Row],[CONTACTO]]&"?text="&Tabla2[[#This Row],[Mensaje]]),"") -> https://wa.me/56966749395?text=Hola!%0AServicio del día 02-02%0A *Cliente:* VILLAR HERMANOS S.A. */ Cont: * TIIU2925771*/ HR Entrega: *15:00* /Dirección: *SALAR DE ATACAMA 1330, PUDAHUEL
A50: =ROW(A49) -> 49 | B50: =IF(J50=J49,B49+1,1) -> 1 | C50: A R G TRAILERS SPA | D50: IMPO | E50: 70085 | F50: TCNU3850894 | G50: 40 HC | H50: 23000 | I50: 03/02 - 10:04 | J50: 46056 | K50: 0.625 | M50: PEDRO JOSE CARRILLO | N50: =IFERROR(VLOOKUP(M50,Data!$J$1:$K$58,2,0),"") -> 56984880436 | O50: HLGX-83 | Q50: GOREN - LA PRIMAVERA 361; LAMPA | R50: CIS | Y50: PENDIENTE | Z50: FUERA DE HORARIO / REPROGRAMADO | AD50: =IF(Tabla2[[#This Row],[HORA ENTREGA]]="DIRECTO","On time", IF(AA50<>"",IF(Tabla2[[#This Row],[Fecha Real Entrega]]<Tabla2[[#This Row],[FECHA ENTREGA]],"On time",IF(Tabla2[[#This Row],[Hora Real Entrega]]<=Tabla2[[#This Row],[HORA ENTREGA]]+(15/1440),"On time","Off time")),"Sin llegada")) -> Sin llegada | AE50: =MID(Tabla2[[#This Row],[TIPO]],1,3) -> 40 | AF50: ="Hola!" & "%0A" & "Servicio del día " &TEXT(Tabla2[[#This Row],[FECHA ENTREGA]],"dd-mm") & "%0A" & " *Cliente:* " &Tabla2[[#This Row],[CLIENTE]] & " */ Cont: * "&Tabla2[[#This Row],[CONTENEDOR]] & "*/ HR Entrega: *" & TEXT(Tabla2[[#This Row],[HORA ENTREGA]],"hh:mm") & "* /Dirección: *" & Tabla2[[#This Row],[Dirección Entrega]] -> Hola!%0AServicio del día 03-02%0A *Cliente:* A R G TRAILERS SPA */ Cont: * TCNU3850894*/ HR Entrega: *15:00* /Dirección: *GOREN - LA PRIMAVERA 361; LAMPA | AG50: =IFERROR(HYPERLINK("https://wa.me/"&Tabla2[[#This Row],[CONTACTO]]&"?text="&Tabla2[[#This Row],[Mensaje]],"Enviar mensaje"),"") -> Enviar mensaje | AH50: =CONCATENATE(A50,F50) -> 49TCNU3850894 | AI50: =CONCATENATE("ENT-",A50) -> ENT-49 | AJ50: =IF(Tabla2[[#This Row],[Op]]<>"","ENTREGA","") -> ENTREGA | AK50: =(Tabla2[[#This Row],[FECHA ENTREGA]]&Tabla2[[#This Row],[HORA ENTREGA]]) -> 460560,625 | AL50: =IFERROR(HYPERLINK("https://wa.me/"&Tabla2[[#This Row],[CONTACTO]]&"?text="&Tabla2[[#This Row],[Mensaje]]),"") -> https://wa.me/56984880436?text=Hola!%0AServicio del día 03-02%0A *Cliente:* A R G TRAILERS SPA */ Cont: * TCNU3850894*/ HR Entrega: *15:00* /Dirección: *GOREN - LA PRIMAVERA 361; LAMPA
A51: =ROW(A50) -> 50 | B51: =IF(J51=J50,B50+1,1) -> 2 | C51: ALMAKILA SPA | D51: IMPO | E51: 298206 | F51: MNBU0123436 | G51: 40 RF | H51: 27000 | I51: FRAGUA | J51: 46056 | K51: 0.375 | M51: GABRIEL SALAS | N51: =IFERROR(VLOOKUP(M51,Data!$J$1:$K$58,2,0),"") -> 56999270871 | O51: RFZW-98 | Q51: ANTILLANCA SUR 586 PUDAHUEL | R51: CONTOPSA SAI | Y51: ENTREGADO | AA51: 0.37152778 | AC51: 46056 | AD51: =IF(Tabla2[[#This Row],[HORA ENTREGA]]="DIRECTO","On time", IF(AA51<>"",IF(Tabla2[[#This Row],[Fecha Real Entrega]]<Tabla2[[#This Row],[FECHA ENTREGA]],"On time",IF(Tabla2[[#This Row],[Hora Real Entrega]]<=Tabla2[[#This Row],[HORA ENTREGA]]+(15/1440),"On time","Off time")),"Sin llegada")) -> On time | AE51: =MID(Tabla2[[#This Row],[TIPO]],1,3) -> 40 | AF51: ="Hola!" & "%0A" & "Servicio del día " &TEXT(Tabla2[[#This Row],[FECHA ENTREGA]],"dd-mm") & "%0A" & " *Cliente:* " &Tabla2[[#This Row],[CLIENTE]] & " */ Cont: * "&Tabla2[[#This Row],[CONTENEDOR]] & "*/ HR Entrega: *" & TEXT(Tabla2[[#This Row],[HORA ENTREGA]],"hh:mm") & "* /Dirección: *" & Tabla2[[#This Row],[Dirección Entrega]] -> Hola!%0AServicio del día 03-02%0A *Cliente:* ALMAKILA SPA */ Cont: * MNBU0123436*/ HR Entrega: *09:00* /Dirección: *ANTILLANCA SUR 586 PUDAHUEL | AG51: =IFERROR(HYPERLINK("https://wa.me/"&Tabla2[[#This Row],[CONTACTO]]&"?text="&Tabla2[[#This Row],[Mensaje]],"Enviar mensaje"),"") -> Enviar mensaje | AH51: =CONCATENATE(A51,F51) -> 50MNBU0123436 | AI51: =CONCATENATE("ENT-",A51) -> ENT-50 | AJ51: =IF(Tabla2[[#This Row],[Op]]<>"","ENTREGA","") -> ENTREGA | AK51: =(Tabla2[[#This Row],[FECHA ENTREGA]]&Tabla2[[#This Row],[HORA ENTREGA]]) -> 460560,375 | AL51: =IFERROR(HYPERLINK("https://wa.me/"&Tabla2[[#This Row],[CONTACTO]]&"?text="&Tabla2[[#This Row],[Mensaje]]),"") -> https://wa.me/56999270871?text=Hola!%0AServicio del día 03-02%0A *Cliente:* ALMAKILA SPA */ Cont: * MNBU0123436*/ HR Entrega: *09:00* /Dirección: *ANTILLANCA SUR 586 PUDAHUEL
A52: =ROW(A51) -> 51 | B52: =IF(J52=J51,B51+1,1) -> 3 | C52: ALMAKILA SPA | D52: IMPO | E52: 298205 | F52: MNBU3780326 | G52: 40 RF | H52: 28000 | I52: FRAGUA | J52: 46056 | K52: 0.5 | M52: JUAN ESPINOZA | N52: =IFERROR(VLOOKUP(M52,Data!$J$1:$K$58,2,0),"") -> 56965312953 | O52: LGGR-15 | Q52: ANTILLANCA SUR 586 PUDAHUEL | R52: CONTOPSA SAI | Y52: ENTREGADO | AA52: 0.625 | AC52: 46056 | AD52: =IF(Tabla2[[#This Row],[HORA ENTREGA]]="DIRECTO","On time", IF(AA52<>"",IF(Tabla2[[#This Row],[Fecha Real Entrega]]<Tabla2[[#This Row],[FECHA ENTREGA]],"On time",IF(Tabla2[[#This Row],[Hora Real Entrega]]<=Tabla2[[#This Row],[HORA ENTREGA]]+(15/1440),"On time","Off time")),"Sin llegada")) -> Off time | AE52: =MID(Tabla2[[#This Row],[TIPO]],1,3) -> 40 | AF52: ="Hola!" & "%0A" & "Servicio del día " &TEXT(Tabla2[[#This Row],[FECHA ENTREGA]],"dd-mm") & "%0A" & " *Cliente:* " &Tabla2[[#This Row],[CLIENTE]] & " */ Cont: * "&Tabla2[[#This Row],[CONTENEDOR]] & "*/ HR Entrega: *" & TEXT(Tabla2[[#This Row],[HORA ENTREGA]],"hh:mm") & "* /Dirección: *" & Tabla2[[#This Row],[Dirección Entrega]] -> Hola!%0AServicio del día 03-02%0A *Cliente:* ALMAKILA SPA */ Cont: * MNBU3780326*/ HR Entrega: *12:00* /Dirección: *ANTILLANCA SUR 586 PUDAHUEL | AG52: =IFERROR(HYPERLINK("https://wa.me/"&Tabla2[[#This Row],[CONTACTO]]&"?text="&Tabla2[[#This Row],[Mensaje]],"Enviar mensaje"),"") -> Enviar mensaje | AH52: =CONCATENATE(A52,F52) -> 51MNBU3780326 | AI52: =CONCATENATE("ENT-",A52) -> ENT-51 | AJ52: =IF(Tabla2[[#This Row],[Op]]<>"","ENTREGA","") -> ENTREGA | AK52: =(Tabla2[[#This Row],[FECHA ENTREGA]]&Tabla2[[#This Row],[HORA ENTREGA]]) -> 460560,5 | AL52: =IFERROR(HYPERLINK("https://wa.me/"&Tabla2[[#This Row],[CONTACTO]]&"?text="&Tabla2[[#This Row],[Mensaje]]),"") -> https://wa.me/56965312953?text=Hola!%0AServicio del día 03-02%0A *Cliente:* ALMAKILA SPA */ Cont: * MNBU3780326*/ HR Entrega: *12:00* /Dirección: *ANTILLANCA SUR 586 PUDAHUEL
A53: =ROW(A52) -> 52 | B53: =IF(J53=J52,B52+1,1) -> 4 | C53: BARCEL CHILE S.A. | D53: IMPO | E53: 1280129 | F53: HAMU3709801 | G53: 40 HC | H53: 25000 | I53: FRAGUA | J53: 46056 | K53: 0.35416667 | M53: OSCAR SANCHEZ | N53: =IFERROR(VLOOKUP(M53,Data!$J$1:$K$58,2,0),"") -> 56978811158 | O53: KBKZ-27 | Q53: AGUNSA - La montaña 1550, Quilicura (Ingreso por portería A) | R53: SAAM RENCA | Y53: ENTREGADO | AA53: 0.30208333 | AC53: 46056 | AD53: =IF(Tabla2[[#This Row],[HORA ENTREGA]]="DIRECTO","On time", IF(AA53<>"",IF(Tabla2[[#This Row],[Fecha Real Entrega]]<Tabla2[[#This Row],[FECHA ENTREGA]],"On time",IF(Tabla2[[#This Row],[Hora Real Entrega]]<=Tabla2[[#This Row],[HORA ENTREGA]]+(15/1440),"On time","Off time")),"Sin llegada")) -> On time | AE53: =MID(Tabla2[[#This Row],[TIPO]],1,3) -> 40 | AF53: ="Hola!" & "%0A" & "Servicio del día " &TEXT(Tabla2[[#This Row],[FECHA ENTREGA]],"dd-mm") & "%0A" & " *Cliente:* " &Tabla2[[#This Row],[CLIENTE]] & " */ Cont: * "&Tabla2[[#This Row],[CONTENEDOR]] & "*/ HR Entrega: *" & TEXT(Tabla2[[#This Row],[HORA ENTREGA]],"hh:mm") & "* /Dirección: *" & Tabla2[[#This Row],[Dirección Entrega]] -> Hola!%0AServicio del día 03-02%0A *Cliente:* BARCEL CHILE S.A. */ Cont: * HAMU3709801*/ HR Entrega: *08:30* /Dirección: *AGUNSA - La montaña 1550, Quilicura (Ingreso por portería A) | AG53: =IFERROR(HYPERLINK("https://wa.me/"&Tabla2[[#This Row],[CONTACTO]]&"?text="&Tabla2[[#This Row],[Mensaje]],"Enviar mensaje"),"") -> Enviar mensaje | AH53: =CONCATENATE(A53,F53) -> 52HAMU3709801 | AI53: =CONCATENATE("ENT-",A53) -> ENT-52 | AJ53: =IF(Tabla2[[#This Row],[Op]]<>"","ENTREGA","") -> ENTREGA | AK53: =(Tabla2[[#This Row],[FECHA ENTREGA]]&Tabla2[[#This Row],[HORA ENTREGA]]) -> 460560,354166666666667 | AL53: =IFERROR(HYPERLINK("https://wa.me/"&Tabla2[[#This Row],[CONTACTO]]&"?text="&Tabla2[[#This Row],[Mensaje]]),"") -> https://wa.me/56978811158?text=Hola!%0AServicio del día 03-02%0A *Cliente:* BARCEL CHILE S.A. */ Cont: * HAMU3709801*/ HR Entrega: *08:30* /Dirección: *AGUNSA - La montaña 1550, Quilicura (Ingreso por portería A)
A54: =ROW(A53) -> 53 | B54: =IF(J54=J53,B53+1,1) -> 5 | C54: BARCEL CHILE S.A. | D54: IMPO | E54: 1280129 | F54: HAMU3983730 | G54: 40 HC | H54: 25000 | I54: FRAGUA | J54: 46056 | K54: 0.39583333 | M54: JESUS GUTIERREZ | N54: =IFERROR(VLOOKUP(M54,Data!$J$1:$K$58,2,0),"") -> 56985215946 | O54: KPBC-56 | Q54: AGUNSA - La montaña 1550, Quilicura (Ingreso por portería A) | R54: SAAM RENCA | Y54: ENTREGADO | AA54: 0.36458333 | AC54: 46056 | AD54: =IF(Tabla2[[#This Row],[HORA ENTREGA]]="DIRECTO","On time", IF(AA54<>"",IF(Tabla2[[#This Row],[Fecha Real Entrega]]<Tabla2[[#This Row],[FECHA ENTREGA]],"On time",IF(Tabla2[[#This Row],[Hora Real Entrega]]<=Tabla2[[#This Row],[HORA ENTREGA]]+(15/1440),"On time","Off time")),"Sin llegada")) -> On time | AE54: =MID(Tabla2[[#This Row],[TIPO]],1,3) -> 40 | AF54: ="Hola!" & "%0A" & "Servicio del día " &TEXT(Tabla2[[#This Row],[FECHA ENTREGA]],"dd-mm") & "%0A" & " *Cliente:* " &Tabla2[[#This Row],[CLIENTE]] & " */ Cont: * "&Tabla2[[#This Row],[CONTENEDOR]] & "*/ HR Entrega: *" & TEXT(Tabla2[[#This Row],[HORA ENTREGA]],"hh:mm") & "* /Dirección: *" & Tabla2[[#This Row],[Dirección Entrega]] -> Hola!%0AServicio del día 03-02%0A *Cliente:* BARCEL CHILE S.A. */ Cont: * HAMU3983730*/ HR Entrega: *09:30* /Dirección: *AGUNSA - La montaña 1550, Quilicura (Ingreso por portería A) | AG54: =IFERROR(HYPERLINK("https://wa.me/"&Tabla2[[#This Row],[CONTACTO]]&"?text="&Tabla2[[#This Row],[Mensaje]],"Enviar mensaje"),"") -> Enviar mensaje | AH54: =CONCATENATE(A54,F54) -> 53HAMU3983730 | AI54: =CONCATENATE("ENT-",A54) -> ENT-53 | AJ54: =IF(Tabla2[[#This Row],[Op]]<>"","ENTREGA","") -> ENTREGA | AK54: =(Tabla2[[#This Row],[FECHA ENTREGA]]&Tabla2[[#This Row],[HORA ENTREGA]]) -> 460560,395833333333333 | AL54: =IFERROR(HYPERLINK("https://wa.me/"&Tabla2[[#This Row],[CONTACTO]]&"?text="&Tabla2[[#This Row],[Mensaje]]),"") -> https://wa.me/56985215946?text=Hola!%0AServicio del día 03-02%0A *Cliente:* BARCEL CHILE S.A. */ Cont: * HAMU3983730*/ HR Entrega: *09:30* /Dirección: *AGUNSA - La montaña 1550, Quilicura (Ingreso por portería A)
A55: =ROW(A54) -> 54 | B55: =IF(J55=J54,B54+1,1) -> 6 | C55: BARCEL CHILE S.A. | D55: IMPO | E55: 1280129 | F55: HAMU2034072 | G55: 40 HC | H55: 25000 | I55: FRAGUA | J55: 46056 | K55: 0.4375 | M55: JAVIER LOPEZ | N55: =IFERROR(VLOOKUP(M55,Data!$J$1:$K$58,2,0),"") -> 56987557136 | O55: TRKJ-63 | Q55: AGUNSA - La montaña 1550, Quilicura (Ingreso por portería A) | R55: SAAM RENCA | Y55: ENTREGADO | AA55: 0.43055556 | AC55: 46056 | AD55: =IF(Tabla2[[#This Row],[HORA ENTREGA]]="DIRECTO","On time", IF(AA55<>"",IF(Tabla2[[#This Row],[Fecha Real Entrega]]<Tabla2[[#This Row],[FECHA ENTREGA]],"On time",IF(Tabla2[[#This Row],[Hora Real Entrega]]<=Tabla2[[#This Row],[HORA ENTREGA]]+(15/1440),"On time","Off time")),"Sin llegada")) -> On time | AE55: =MID(Tabla2[[#This Row],[TIPO]],1,3) -> 40 | AF55: ="Hola!" & "%0A" & "Servicio del día " &TEXT(Tabla2[[#This Row],[FECHA ENTREGA]],"dd-mm") & "%0A" & " *Cliente:* " &Tabla2[[#This Row],[CLIENTE]] & " */ Cont: * "&Tabla2[[#This Row],[CONTENEDOR]] & "*/ HR Entrega: *" & TEXT(Tabla2[[#This Row],[HORA ENTREGA]],"hh:mm") & "* /Dirección: *" & Tabla2[[#This Row],[Dirección Entrega]] -> Hola!%0AServicio del día 03-02%0A *Cliente:* BARCEL CHILE S.A. */ Cont: * HAMU2034072*/ HR Entrega: *10:30* /Dirección: *AGUNSA - La montaña 1550, Quilicura (Ingreso por portería A) | AG55: =IFERROR(HYPERLINK("https://wa.me/"&Tabla2[[#This Row],[CONTACTO]]&"?text="&Tabla2[[#This Row],[Mensaje]],"Enviar mensaje"),"") -> Enviar mensaje | AH55: =CONCATENATE(A55,F55) -> 54HAMU2034072 | AI55: =CONCATENATE("ENT-",A55) -> ENT-54 | AJ55: =IF(Tabla2[[#This Row],[Op]]<>"","ENTREGA","") -> ENTREGA | AK55: =(Tabla2[[#This Row],[FECHA ENTREGA]]&Tabla2[[#This Row],[HORA ENTREGA]]) -> 460560,4375 | AL55: =IFERROR(HYPERLINK("https://wa.me/"&Tabla2[[#This Row],[CONTACTO]]&"?text="&Tabla2[[#This Row],[Mensaje]]),"") -> https://wa.me/56987557136?text=Hola!%0AServicio del día 03-02%0A *Cliente:* BARCEL CHILE S.A. */ Cont: * HAMU2034072*/ HR Entrega: *10:30* /Dirección: *AGUNSA - La montaña 1550, Quilicura (Ingreso por portería A)
A56: =ROW(A55) -> 55 | B56: =IF(J56=J55,B55+1,1) -> 7 | C56: BAYONA SPA | D56: IMPO | E56: 297511/297512 | F56: MSDU8296917 | G56: 40 HC | H56: 13000 | I56: FRAGUA | J56: 46056 | K56: 0.33333333 | M56: GUSTAVO VEGA ARAYA | N56: =IFERROR(VLOOKUP(M56,Data!$J$1:$K$58,2,0),"") -> 56998494086 | O56: KKWG-93 | Q56: BOULEVAR 1313 BODENOR FLEX CENTER ENEA, PUDAHUEL | R56: MEDLOG VALP | X56: 4 DESCARGADORES | Y56: ENTREGADO | AA56: 0.32291667 | AC56: 46056 | AD56: =IF(Tabla2[[#This Row],[HORA ENTREGA]]="DIRECTO","On time", IF(AA56<>"",IF(Tabla2[[#This Row],[Fecha Real Entrega]]<Tabla2[[#This Row],[FECHA ENTREGA]],"On time",IF(Tabla2[[#This Row],[Hora Real Entrega]]<=Tabla2[[#This Row],[HORA ENTREGA]]+(15/1440),"On time","Off time")),"Sin llegada")) -> On time | AE56: =MID(Tabla2[[#This Row],[TIPO]],1,3) -> 40 | AF56: ="Hola!" & "%0A" & "Servicio del día " &TEXT(Tabla2[[#This Row],[FECHA ENTREGA]],"dd-mm") & "%0A" & " *Cliente:* " &Tabla2[[#This Row],[CLIENTE]] & " */ Cont: * "&Tabla2[[#This Row],[CONTENEDOR]] & "*/ HR Entrega: *" & TEXT(Tabla2[[#This Row],[HORA ENTREGA]],"hh:mm") & "* /Dirección: *" & Tabla2[[#This Row],[Dirección Entrega]] -> Hola!%0AServicio del día 03-02%0A *Cliente:* BAYONA SPA */ Cont: * MSDU8296917*/ HR Entrega: *08:00* /Dirección: * BOULEVAR 1313 BODENOR FLEX CENTER ENEA, PUDAHUEL | AG56: =IFERROR(HYPERLINK("https://wa.me/"&Tabla2[[#This Row],[CONTACTO]]&"?text="&Tabla2[[#This Row],[Mensaje]],"Enviar mensaje"),"") -> Enviar mensaje | AH56: =CONCATENATE(A56,F56) -> 55MSDU8296917 | AI56: =CONCATENATE("ENT-",A56) -> ENT-55 | AJ56: =IF(Tabla2[[#This Row],[Op]]<>"","ENTREGA","") -> ENTREGA | AK56: =(Tabla2[[#This Row],[FECHA ENTREGA]]&Tabla2[[#This Row],[HORA ENTREGA]]) -> 460560,333333333333333 | AL56: =IFERROR(HYPERLINK("https://wa.me/"&Tabla2[[#This Row],[CONTACTO]]&"?text="&Tabla2[[#This Row],[Mensaje]]),"") -> https://wa.me/56998494086?text=Hola!%0AServicio del día 03-02%0A *Cliente:* BAYONA SPA */ Cont: * MSDU8296917*/ HR Entrega: *08:00* /Dirección: * BOULEVAR 1313 BODENOR FLEX CENTER ENEA, PUDAHUEL
A57: =ROW(A56) -> 56 | B57: =IF(J57=J56,B56+1,1) -> 8 | C57: BAYONA SPA | D57: IMPO | E57: 297776 | F57: CMAU4472099 | G57: 40 HC | H57: 8000 | I57: FRAGUA | J57: 46056 | K57: 0.45833333 | M57: GERARDO GALAZ | N57: =IFERROR(VLOOKUP(M57,Data!$J$1:$K$58,2,0),"") -> 56950103942 | O57: LFHK-36 | Q57: BOULEVAR 1313 BODENOR FLEX CENTER ENEA, PUDAHUEL | R57: CIS | X57: 4 DESCARGADORES | Y57: ENTREGADO | AA57: 0.54513889 | AC57: 46056 | AD57: =IF(Tabla2[[#This Row],[HORA ENTREGA]]="DIRECTO","On time", IF(AA57<>"",IF(Tabla2[[#This Row],[Fecha Real Entrega]]<Tabla2[[#This Row],[FECHA ENTREGA]],"On time",IF(Tabla2[[#This Row],[Hora Real Entrega]]<=Tabla2[[#This Row],[HORA ENTREGA]]+(15/1440),"On time","Off time")),"Sin llegada")) -> Off time | AE57: =MID(Tabla2[[#This Row],[TIPO]],1,3) -> 40 | AF57: ="Hola!" & "%0A" & "Servicio del día " &TEXT(Tabla2[[#This Row],[FECHA ENTREGA]],"dd-mm") & "%0A" & " *Cliente:* " &Tabla2[[#This Row],[CLIENTE]] & " */ Cont: * "&Tabla2[[#This Row],[CONTENEDOR]] & "*/ HR Entrega: *" & TEXT(Tabla2[[#This Row],[HORA ENTREGA]],"hh:mm") & "* /Dirección: *" & Tabla2[[#This Row],[Dirección Entrega]] -> Hola!%0AServicio del día 03-02%0A *Cliente:* BAYONA SPA */ Cont: * CMAU4472099*/ HR Entrega: *11:00* /Dirección: * BOULEVAR 1313 BODENOR FLEX CENTER ENEA, PUDAHUEL | AG57: =IFERROR(HYPERLINK("https://wa.me/"&Tabla2[[#This Row],[CONTACTO]]&"?text="&Tabla2[[#This Row],[Mensaje]],"Enviar mensaje"),"") -> Enviar mensaje | AH57: =CONCATENATE(A57,F57) -> 56CMAU4472099 | AI57: =CONCATENATE("ENT-",A57) -> ENT-56 | AJ57: =IF(Tabla2[[#This Row],[Op]]<>"","ENTREGA","") -> ENTREGA | AK57: =(Tabla2[[#This Row],[FECHA ENTREGA]]&Tabla2[[#This Row],[HORA ENTREGA]]) -> 460560,458333333333333 | AL57: =IFERROR(HYPERLINK("https://wa.me/"&Tabla2[[#This Row],[CONTACTO]]&"?text="&Tabla2[[#This Row],[Mensaje]]),"") -> https://wa.me/56950103942?text=Hola!%0AServicio del día 03-02%0A *Cliente:* BAYONA SPA */ Cont: * CMAU4472099*/ HR Entrega: *11:00* /Dirección: * BOULEVAR 1313 BODENOR FLEX CENTER ENEA, PUDAHUEL
A58: =ROW(A57) -> 57 | B58: =IF(J58=J57,B57+1,1) -> 9 | C58: COMERCIAL CANADA SPA | D58: IMPO | E58: 297821 | F58: AXIU6111306 | G58: 40 HC | H58: 30000 | I58: 02/02 - 21:17 | J58: 46056 | K58: 0.33333333 | M58: JAIME PINTO YAÑEZ | N58: =IFERROR(VLOOKUP(M58,Data!$J$1:$K$58,2,0),"") -> 56956654384 | O58: LPYG-88 | Q58: BERNARDO O"HIGGINS 158 COLINA | R58: CIS | Y58: ENTREGADO | AA58: 0.3375 | AC58: 46056 | AD58: =IF(Tabla2[[#This Row],[HORA ENTREGA]]="DIRECTO","On time", IF(AA58<>"",IF(Tabla2[[#This Row],[Fecha Real Entrega]]<Tabla2[[#This Row],[FECHA ENTREGA]],"On time",IF(Tabla2[[#This Row],[Hora Real Entrega]]<=Tabla2[[#This Row],[HORA ENTREGA]]+(15/1440),"On time","Off time")),"Sin llegada")) -> On time | AE58: =MID(Tabla2[[#This Row],[TIPO]],1,3) -> 40 | AF58: ="Hola!" & "%0A" & "Servicio del día " &TEXT(Tabla2[[#This Row],[FECHA ENTREGA]],"dd-mm") & "%0A" & " *Cliente:* " &Tabla2[[#This Row],[CLIENTE]] & " */ Cont: * "&Tabla2[[#This Row],[CONTENEDOR]] & "*/ HR Entrega: *" & TEXT(Tabla2[[#This Row],[HORA ENTREGA]],"hh:mm") & "* /Dirección: *" & Tabla2[[#This Row],[Dirección Entrega]] -> Hola!%0AServicio del día 03-02%0A *Cliente:* COMERCIAL CANADA SPA */ Cont: * AXIU6111306*/ HR Entrega: *08:00* /Dirección: *BERNARDO O"HIGGINS 158 COLINA | AG58: =IFERROR(HYPERLINK("https://wa.me/"&Tabla2[[#This Row],[CONTACTO]]&"?text="&Tabla2[[#This Row],[Mensaje]],"Enviar mensaje"),"") -> Enviar mensaje | AH58: =CONCATENATE(A58,F58) -> 57AXIU6111306 | AI58: =CONCATENATE("ENT-",A58) -> ENT-57 | AJ58: =IF(Tabla2[[#This Row],[Op]]<>"","ENTREGA","") -> ENTREGA | AK58: =(Tabla2[[#This Row],[FECHA ENTREGA]]&Tabla2[[#This Row],[HORA ENTREGA]]) -> 460560,333333333333333 | AL58: =IFERROR(HYPERLINK("https://wa.me/"&Tabla2[[#This Row],[CONTACTO]]&"?text="&Tabla2[[#This Row],[Mensaje]]),"") -> https://wa.me/56956654384?text=Hola!%0AServicio del día 03-02%0A *Cliente:* COMERCIAL CANADA SPA */ Cont: * AXIU6111306*/ HR Entrega: *08:00* /Dirección: *BERNARDO O"HIGGINS 158 COLINA
A59: =ROW(A58) -> 58 | B59: =IF(J59=J58,B58+1,1) -> 10 | C59: COMERCIAL CANADA SPA | D59: IMPO | E59: 297821 | F59: CGMU5130289 | G59: 40 HC | H59: 30000 | I59: 02/02 - 21:14 | J59: 46056 | K59: 0.41666667 | M59: CHARLES DIAZ | N59: =IFERROR(VLOOKUP(M59,Data!$J$1:$K$58,2,0),"") -> 56966749408 | O59: RVFP-35 | Q59: BERNARDO O"HIGGINS 158 COLINA | R59: AGUNSA SAI | Y59: ENTREGADO | AA59: 0.36666667 | AC59: 46056 | AD59: =IF(Tabla2[[#This Row],[HORA ENTREGA]]="DIRECTO","On time", IF(AA59<>"",IF(Tabla2[[#This Row],[Fecha Real Entrega]]<Tabla2[[#This Row],[FECHA ENTREGA]],"On time",IF(Tabla2[[#This Row],[Hora Real Entrega]]<=Tabla2[[#This Row],[HORA ENTREGA]]+(15/1440),"On time","Off time")),"Sin llegada")) -> On time | AE59: =MID(Tabla2[[#This Row],[TIPO]],1,3) -> 40 | AF59: ="Hola!" & "%0A" & "Servicio del día " &TEXT(Tabla2[[#This Row],[FECHA ENTREGA]],"dd-mm") & "%0A" & " *Cliente:* " &Tabla2[[#This Row],[CLIENTE]] & " */ Cont: * "&Tabla2[[#This Row],[CONTENEDOR]] & "*/ HR Entrega: *" & TEXT(Tabla2[[#This Row],[HORA ENTREGA]],"hh:mm") & "* /Dirección: *" & Tabla2[[#This Row],[Dirección Entrega]] -> Hola!%0AServicio del día 03-02%0A *Cliente:* COMERCIAL CANADA SPA */ Cont: * CGMU5130289*/ HR Entrega: *10:00* /Dirección: *BERNARDO O"HIGGINS 158 COLINA | AG59: =IFERROR(HYPERLINK("https://wa.me/"&Tabla2[[#This Row],[CONTACTO]]&"?text="&Tabla2[[#This Row],[Mensaje]],"Enviar mensaje"),"") -> Enviar mensaje | AH59: =CONCATENATE(A59,F59) -> 58CGMU5130289 | AI59: =CONCATENATE("ENT-",A59) -> ENT-58 | AJ59: =IF(Tabla2[[#This Row],[Op]]<>"","ENTREGA","") -> ENTREGA | AK59: =(Tabla2[[#This Row],[FECHA ENTREGA]]&Tabla2[[#This Row],[HORA ENTREGA]]) -> 460560,416666666666667 | AL59: =IFERROR(HYPERLINK("https://wa.me/"&Tabla2[[#This Row],[CONTACTO]]&"?text="&Tabla2[[#This Row],[Mensaje]]),"") -> https://wa.me/56966749408?text=Hola!%0AServicio del día 03-02%0A *Cliente:* COMERCIAL CANADA SPA */ Cont: * CGMU5130289*/ HR Entrega: *10:00* /Dirección: *BERNARDO O"HIGGINS 158 COLINA
A60: =ROW(A59) -> 59 | B60: =IF(J60=J59,B59+1,1) -> 11 | C60: COMERCIAL CANADA SPA | D60: IMPO | E60: 297821 | F60: TTNU8055369 | G60: 40 HC | H60: 30000 | I60: 02/02 - 21:20 | J60: 46056 | K60: 0.5 | M60: SAMUEL SALAS | N60: =IFERROR(VLOOKUP(M60,Data!$J$1:$K$58,2,0),"") -> 56950981572 | O60: THYG-63 | Q60: BERNARDO O"HIGGINS 158 COLINA | R60: AGUNSA SAI | Y60: ENTREGADO | AA60: 0.55138889 | AC60: 46056 | AD60: =IF(Tabla2[[#This Row],[HORA ENTREGA]]="DIRECTO","On time", IF(AA60<>"",IF(Tabla2[[#This Row],[Fecha Real Entrega]]<Tabla2[[#This Row],[FECHA ENTREGA]],"On time",IF(Tabla2[[#This Row],[Hora Real Entrega]]<=Tabla2[[#This Row],[HORA ENTREGA]]+(15/1440),"On time","Off time")),"Sin llegada")) -> Off time | AE60: =MID(Tabla2[[#This Row],[TIPO]],1,3) -> 40 | AF60: ="Hola!" & "%0A" & "Servicio del día " &TEXT(Tabla2[[#This Row],[FECHA ENTREGA]],"dd-mm") & "%0A" & " *Cliente:* " &Tabla2[[#This Row],[CLIENTE]] & " */ Cont: * "&Tabla2[[#This Row],[CONTENEDOR]] & "*/ HR Entrega: *" & TEXT(Tabla2[[#This Row],[HORA ENTREGA]],"hh:mm") & "* /Dirección: *" & Tabla2[[#This Row],[Dirección Entrega]] -> Hola!%0AServicio del día 03-02%0A *Cliente:* COMERCIAL CANADA SPA */ Cont: * TTNU8055369*/ HR Entrega: *12:00* /Dirección: *BERNARDO O"HIGGINS 158 COLINA | AG60: =IFERROR(HYPERLINK("https://wa.me/"&Tabla2[[#This Row],[CONTACTO]]&"?text="&Tabla2[[#This Row],[Mensaje]],"Enviar mensaje"),"") -> Enviar mensaje | AH60: =CONCATENATE(A60,F60) -> 59TTNU8055369 | AI60: =CONCATENATE("ENT-",A60) -> ENT-59 | AJ60: =IF(Tabla2[[#This Row],[Op]]<>"","ENTREGA","") -> ENTREGA | AK60: =(Tabla2[[#This Row],[FECHA ENTREGA]]&Tabla2[[#This Row],[HORA ENTREGA]]) -> 460560,5 | AL60: =IFERROR(HYPERLINK("https://wa.me/"&Tabla2[[#This Row],[CONTACTO]]&"?text="&Tabla2[[#This Row],[Mensaje]]),"") -> https://wa.me/56950981572?text=Hola!%0AServicio del día 03-02%0A *Cliente:* COMERCIAL CANADA SPA */ Cont: * TTNU8055369*/ HR Entrega: *12:00* /Dirección: *BERNARDO O"HIGGINS 158 COLINA
A61: =ROW(A60) -> 60 | B61: =IF(J61=J60,B60+1,1) -> 12 | C61: COMERCIAL ESCOCIA LTDA | D61: IMPO | E61: 298383 | F61: temu4221290 | G61: 20 DV | H61: 26000 | I61: FRAGUA | J61: 46056 | K61: 0.41666667 | M61: FELIPE CATALAN | N61: =IFERROR(VLOOKUP(M61,Data!$J$1:$K$58,2,0),"") -> 56957438415 | O61: RRVF-73 | Q61: LO ERRAZURIZ 926 CERRILLOS | R61: SITRANS SAI | X61: 4 DESCARGADORES | Y61: ENTREGADO | AA61: 0.58888889 | AC61: 46056 | AD61: =IF(Tabla2[[#This Row],[HORA ENTREGA]]="DIRECTO","On time", IF(AA61<>"",IF(Tabla2[[#This Row],[Fecha Real Entrega]]<Tabla2[[#This Row],[FECHA ENTREGA]],"On time",IF(Tabla2[[#This Row],[Hora Real Entrega]]<=Tabla2[[#This Row],[HORA ENTREGA]]+(15/1440),"On time","Off time")),"Sin llegada")) -> Off time | AE61: =MID(Tabla2[[#This Row],[TIPO]],1,3) -> 20 | AF61: ="Hola!" & "%0A" & "Servicio del día " &TEXT(Tabla2[[#This Row],[FECHA ENTREGA]],"dd-mm") & "%0A" & " *Cliente:* " &Tabla2[[#This Row],[CLIENTE]] & " */ Cont: * "&Tabla2[[#This Row],[CONTENEDOR]] & "*/ HR Entrega: *" & TEXT(Tabla2[[#This Row],[HORA ENTREGA]],"hh:mm") & "* /Dirección: *" & Tabla2[[#This Row],[Dirección Entrega]] -> Hola!%0AServicio del día 03-02%0A *Cliente:* COMERCIAL ESCOCIA LTDA */ Cont: * temu4221290*/ HR Entrega: *10:00* /Dirección: *LO ERRAZURIZ 926 CERRILLOS | AG61: =IFERROR(HYPERLINK("https://wa.me/"&Tabla2[[#This Row],[CONTACTO]]&"?text="&Tabla2[[#This Row],[Mensaje]],"Enviar mensaje"),"") -> Enviar mensaje | AH61: =CONCATENATE(A61,F61) -> 60temu4221290 | AI61: =CONCATENATE("ENT-",A61) -> ENT-60 | AJ61: =IF(Tabla2[[#This Row],[Op]]<>"","ENTREGA","") -> ENTREGA | AK61: =(Tabla2[[#This Row],[FECHA ENTREGA]]&Tabla2[[#This Row],[HORA ENTREGA]]) -> 460560,416666666666667 | AL61: =IFERROR(HYPERLINK("https://wa.me/"&Tabla2[[#This Row],[CONTACTO]]&"?text="&Tabla2[[#This Row],[Mensaje]]),"") -> https://wa.me/56957438415?text=Hola!%0AServicio del día 03-02%0A *Cliente:* COMERCIAL ESCOCIA LTDA */ Cont: * temu4221290*/ HR Entrega: *10:00* /Dirección: *LO ERRAZURIZ 926 CERRILLOS
A62: =ROW(A61) -> 61 | B62: =IF(J62=J61,B61+1,1) -> 13 | C62: COMERCIAL ESCOCIA LTDA | D62: IMPO | E62: 298383 | F62: oneu3189980 | G62: 20 DV | H62: 26000 | I62: FRAGUA | J62: 46056 | K62: 0.52083333 | M62: SEBASTIAN CUETO | N62: =IFERROR(VLOOKUP(M62,Data!$J$1:$K$58,2,0),"") -> 56931745801 | O62: THYG-62 | Q62: LO ERRAZURIZ 926 CERRILLOS | R62: SITRANS SAI | X62: 4 DESCARGADORES | Y62: ENTREGADO | AA62: 0.56597222 | AC62: 46056 | AD62: =IF(Tabla2[[#This Row],[HORA ENTREGA]]="DIRECTO","On time", IF(AA62<>"",IF(Tabla2[[#This Row],[Fecha Real Entrega]]<Tabla2[[#This Row],[FECHA ENTREGA]],"On time",IF(Tabla2[[#This Row],[Hora Real Entrega]]<=Tabla2[[#This Row],[HORA ENTREGA]]+(15/1440),"On time","Off time")),"Sin llegada")) -> Off time | AE62: =MID(Tabla2[[#This Row],[TIPO]],1,3) -> 20 | AF62: ="Hola!" & "%0A" & "Servicio del día " &TEXT(Tabla2[[#This Row],[FECHA ENTREGA]],"dd-mm") & "%0A" & " *Cliente:* " &Tabla2[[#This Row],[CLIENTE]] & " */ Cont: * "&Tabla2[[#This Row],[CONTENEDOR]] & "*/ HR Entrega: *" & TEXT(Tabla2[[#This Row],[HORA ENTREGA]],"hh:mm") & "* /Dirección: *" & Tabla2[[#This Row],[Dirección Entrega]] -> Hola!%0AServicio del día 03-02%0A *Cliente:* COMERCIAL ESCOCIA LTDA */ Cont: * oneu3189980*/ HR Entrega: *12:30* /Dirección: *LO ERRAZURIZ 926 CERRILLOS | AG62: =IFERROR(HYPERLINK("https://wa.me/"&Tabla2[[#This Row],[CONTACTO]]&"?text="&Tabla2[[#This Row],[Mensaje]],"Enviar mensaje"),"") -> Enviar mensaje | AH62: =CONCATENATE(A62,F62) -> 61oneu3189980 | AI62: =CONCATENATE("ENT-",A62) -> ENT-61 | AJ62: =IF(Tabla2[[#This Row],[Op]]<>"","ENTREGA","") -> ENTREGA | AK62: =(Tabla2[[#This Row],[FECHA ENTREGA]]&Tabla2[[#This Row],[HORA ENTREGA]]) -> 460560,520833333333333 | AL62: =IFERROR(HYPERLINK("https://wa.me/"&Tabla2[[#This Row],[CONTACTO]]&"?text="&Tabla2[[#This Row],[Mensaje]]),"") -> https://wa.me/56931745801?text=Hola!%0AServicio del día 03-02%0A *Cliente:* COMERCIAL ESCOCIA LTDA */ Cont: * oneu3189980*/ HR Entrega: *12:30* /Dirección: *LO ERRAZURIZ 926 CERRILLOS
A63: =ROW(A62) -> 62 | B63: =IF(J63=J62,B62+1,1) -> 14 | C63: COMERCIAL SEA GARDEN SPA | D63: IMPO | E63: 102406 | F63: OTPU6652178 | G63: 40 RF | H63: 27000 | I63: 0.375 | J63: 46056 | K63: DIRECTO | M63: IVAN VASQUEZ URBINA | N63: =IFERROR(VLOOKUP(M63,Data!$J$1:$K$58,2,0),"") -> 56968463649 | O63: LGGR-12 | Q63: LOS MAITENES PONIENTE 1332; PUDAHUEL | R63: - | Y63: ENTREGADO | AA63: 0.54166667 | AC63: 46056 | AD63: =IF(Tabla2[[#This Row],[HORA ENTREGA]]="DIRECTO","On time", IF(AA63<>"",IF(Tabla2[[#This Row],[Fecha Real Entrega]]<Tabla2[[#This Row],[FECHA ENTREGA]],"On time",IF(Tabla2[[#This Row],[Hora Real Entrega]]<=Tabla2[[#This Row],[HORA ENTREGA]]+(15/1440),"On time","Off time")),"Sin llegada")) -> On time | AE63: =MID(Tabla2[[#This Row],[TIPO]],1,3) -> 40 | AF63: ="Hola!" & "%0A" & "Servicio del día " &TEXT(Tabla2[[#This Row],[FECHA ENTREGA]],"dd-mm") & "%0A" & " *Cliente:* " &Tabla2[[#This Row],[CLIENTE]] & " */ Cont: * "&Tabla2[[#This Row],[CONTENEDOR]] & "*/ HR Entrega: *" & TEXT(Tabla2[[#This Row],[HORA ENTREGA]],"hh:mm") & "* /Dirección: *" & Tabla2[[#This Row],[Dirección Entrega]] -> Hola!%0AServicio del día 03-02%0A *Cliente:* COMERCIAL SEA GARDEN SPA */ Cont: * OTPU6652178*/ HR Entrega: *DIRECTO* /Dirección: *LOS MAITENES PONIENTE 1332; PUDAHUEL | AG63: =IFERROR(HYPERLINK("https://wa.me/"&Tabla2[[#This Row],[CONTACTO]]&"?text="&Tabla2[[#This Row],[Mensaje]],"Enviar mensaje"),"") -> Enviar mensaje | AH63: =CONCATENATE(A63,F63) -> 62OTPU6652178 | AI63: =CONCATENATE("ENT-",A63) -> ENT-62 | AJ63: =IF(Tabla2[[#This Row],[Op]]<>"","ENTREGA","") -> ENTREGA | AK63: =(Tabla2[[#This Row],[FECHA ENTREGA]]&Tabla2[[#This Row],[HORA ENTREGA]]) -> 46056DIRECTO | AL63: =IFERROR(HYPERLINK("https://wa.me/"&Tabla2[[#This Row],[CONTACTO]]&"?text="&Tabla2[[#This Row],[Mensaje]]),"") -> https://wa.me/56968463649?text=Hola!%0AServicio del día 03-02%0A *Cliente:* COMERCIAL SEA GARDEN SPA */ Cont: * OTPU6652178*/ HR Entrega: *DIRECTO* /Dirección: *LOS MAITENES PONIENTE 1332; PUDAHUEL
A64: =ROW(A63) -> 63 | B64: =IF(J64=J63,B63+1,1) -> 15 | C64: FASSI CHILE S.A. | D64: IMPO | E64: 298095 | F64: HLBU8328747 | G64: 40 OT | H64: 20000 | I64: 02/01 - 13:26 | J64: 46056 | K64: 0.33333333 | M64: CARLOS AGUILAR | N64: =IFERROR(VLOOKUP(M64,Data!$J$1:$K$58,2,0),"") -> 56984994337 | O64: TRKJ-66 | Q64: BARRON VIEYRA 10-A COLINA | R64: DYC SAI | Y64: ENTREGADO | AA64: 0.32361111 | AC64: 46056 | AD64: =IF(Tabla2[[#This Row],[HORA ENTREGA]]="DIRECTO","On time", IF(AA64<>"",IF(Tabla2[[#This Row],[Fecha Real Entrega]]<Tabla2[[#This Row],[FECHA ENTREGA]],"On time",IF(Tabla2[[#This Row],[Hora Real Entrega]]<=Tabla2[[#This Row],[HORA ENTREGA]]+(15/1440),"On time","Off time")),"Sin llegada")) -> On time | AE64: =MID(Tabla2[[#This Row],[TIPO]],1,3) -> 40 | AF64: ="Hola!" & "%0A" & "Servicio del día " &TEXT(Tabla2[[#This Row],[FECHA ENTREGA]],"dd-mm") & "%0A" & " *Cliente:* " &Tabla2[[#This Row],[CLIENTE]] & " */ Cont: * "&Tabla2[[#This Row],[CONTENEDOR]] & "*/ HR Entrega: *" & TEXT(Tabla2[[#This Row],[HORA ENTREGA]],"hh:mm") & "* /Dirección: *" & Tabla2[[#This Row],[Dirección Entrega]] -> Hola!%0AServicio del día 03-02%0A *Cliente:* FASSI CHILE S.A. */ Cont: * HLBU8328747*/ HR Entrega: *08:00* /Dirección: *BARRON VIEYRA 10-A COLINA | AG64: =IFERROR(HYPERLINK("https://wa.me/"&Tabla2[[#This Row],[CONTACTO]]&"?text="&Tabla2[[#This Row],[Mensaje]],"Enviar mensaje"),"") -> Enviar mensaje | AH64: =CONCATENATE(A64,F64) -> 63HLBU8328747 | AI64: =CONCATENATE("ENT-",A64) -> ENT-63 | AJ64: =IF(Tabla2[[#This Row],[Op]]<>"","ENTREGA","") -> ENTREGA | AK64: =(Tabla2[[#This Row],[FECHA ENTREGA]]&Tabla2[[#This Row],[HORA ENTREGA]]) -> 460560,333333333333333 | AL64: =IFERROR(HYPERLINK("https://wa.me/"&Tabla2[[#This Row],[CONTACTO]]&"?text="&Tabla2[[#This Row],[Mensaje]]),"") -> https://wa.me/56984994337?text=Hola!%0AServicio del día 03-02%0A *Cliente:* FASSI CHILE S.A. */ Cont: * HLBU8328747*/ HR Entrega: *08:00* /Dirección: *BARRON VIEYRA 10-A COLINA
A65: =ROW(A64) -> 64 | B65: =IF(J65=J64,B64+1,1) -> 16 | C65: FLEX EQUIPOS DE DESCANSO CHILE | D65: IMPO | E65: 298355 | F65: TCKU6627473 | G65: 40 HC | H65: 23000 | I65: FRAGUA | J65: 46056 | K65: 0.35416667 | M65: ANDRES PULGAR | N65: =IFERROR(VLOOKUP(M65,Data!$J$1:$K$58,2,0),"") -> 56989844861 | O65: RHDV-66 | Q65: MERSAN (José Joaquín Prieto 9001, Lo Espejo. Bodegas: 7-8-9-10-15-16-17-18) | R65: CONTOPSA VALP | Y65: ENTREGADO | AA65: 0.32986111 | AC65: 46056 | AD65: =IF(Tabla2[[#This Row],[HORA ENTREGA]]="DIRECTO","On time", IF(AA65<>"",IF(Tabla2[[#This Row],[Fecha Real Entrega]]<Tabla2[[#This Row],[FECHA ENTREGA]],"On time",IF(Tabla2[[#This Row],[Hora Real Entrega]]<=Tabla2[[#This Row],[HORA ENTREGA]]+(15/1440),"On time","Off time")),"Sin llegada")) -> On time | AE65: =MID(Tabla2[[#This Row],[TIPO]],1,3) -> 40 | AF65: ="Hola!" & "%0A" & "Servicio del día " &TEXT(Tabla2[[#This Row],[FECHA ENTREGA]],"dd-mm") & "%0A" & " *Cliente:* " &Tabla2[[#This Row],[CLIENTE]] & " */ Cont: * "&Tabla2[[#This Row],[CONTENEDOR]] & "*/ HR Entrega: *" & TEXT(Tabla2[[#This Row],[HORA ENTREGA]],"hh:mm") & "* /Dirección: *" & Tabla2[[#This Row],[Dirección Entrega]] -> Hola!%0AServicio del día 03-02%0A *Cliente:* FLEX EQUIPOS DE DESCANSO CHILE */ Cont: * TCKU6627473*/ HR Entrega: *08:30* /Dirección: *MERSAN (José Joaquín Prieto 9001, Lo Espejo. Bodegas: 7-8-9-10-15-16-17-18) | AG65: =IFERROR(HYPERLINK("https://wa.me/"&Tabla2[[#This Row],[CONTACTO]]&"?text="&Tabla2[[#This Row],[Mensaje]],"Enviar mensaje"),"") -> Enviar mensaje | AH65: =CONCATENATE(A65,F65) -> 64TCKU6627473 | AI65: =CONCATENATE("ENT-",A65) -> ENT-64 | AJ65: =IF(Tabla2[[#This Row],[Op]]<>"","ENTREGA","") -> ENTREGA | AK65: =(Tabla2[[#This Row],[FECHA ENTREGA]]&Tabla2[[#This Row],[HORA ENTREGA]]) -> 460560,354166666666667 | AL65: =IFERROR(HYPERLINK("https://wa.me/"&Tabla2[[#This Row],[CONTACTO]]&"?text="&Tabla2[[#This Row],[Mensaje]]),"") -> https://wa.me/56989844861?text=Hola!%0AServicio del día 03-02%0A *Cliente:* FLEX EQUIPOS DE DESCANSO CHILE */ Cont: * TCKU6627473*/ HR Entrega: *08:30* /Dirección: *MERSAN (José Joaquín Prieto 9001, Lo Espejo. Bodegas: 7-8-9-10-15-16-17-18)
A66: =ROW(A65) -> 65 | B66: =IF(J66=J65,B65+1,1) -> 17 | C66: GRAYSON GROUP | D66: IMPO | E66: 1191355 | F66: HAMU2826125 | G66: 40 HC | H66: 20000 | I66: FRAGUA | J66: 46056 | K66: 0.375 | M66: RUBEN YAÑEZ | N66: =IFERROR(VLOOKUP(M66,Data!$J$1:$K$58,2,0),"") -> 56973887539 | O66: RRVF-71 | Q66: Avda. Presidente Eduardo Frei Montalva 7050 bodega 5, Quilicura | R66: CONTOPSA SAI | Y66: ENTREGADO | AA66: 0.35277778 | AC66: 46056 | AD66: =IF(Tabla2[[#This Row],[HORA ENTREGA]]="DIRECTO","On time", IF(AA66<>"",IF(Tabla2[[#This Row],[Fecha Real Entrega]]<Tabla2[[#This Row],[FECHA ENTREGA]],"On time",IF(Tabla2[[#This Row],[Hora Real Entrega]]<=Tabla2[[#This Row],[HORA ENTREGA]]+(15/1440),"On time","Off time")),"Sin llegada")) -> On time | AE66: =MID(Tabla2[[#This Row],[TIPO]],1,3) -> 40 | AF66: ="Hola!" & "%0A" & "Servicio del día " &TEXT(Tabla2[[#This Row],[FECHA ENTREGA]],"dd-mm") & "%0A" & " *Cliente:* " &Tabla2[[#This Row],[CLIENTE]] & " */ Cont: * "&Tabla2[[#This Row],[CONTENEDOR]] & "*/ HR Entrega: *" & TEXT(Tabla2[[#This Row],[HORA ENTREGA]],"hh:mm") & "* /Dirección: *" & Tabla2[[#This Row],[Dirección Entrega]] -> Hola!%0AServicio del día 03-02%0A *Cliente:* GRAYSON GROUP */ Cont: * HAMU2826125*/ HR Entrega: *09:00* /Dirección: *Avda. Presidente Eduardo Frei Montalva 7050 bodega 5, Quilicura | AG66: =IFERROR(HYPERLINK("https://wa.me/"&Tabla2[[#This Row],[CONTACTO]]&"?text="&Tabla2[[#This Row],[Mensaje]],"Enviar mensaje"),"") -> Enviar mensaje | AH66: =CONCATENATE(A66,F66) -> 65HAMU2826125 | AI66: =CONCATENATE("ENT-",A66) -> ENT-65 | AJ66: =IF(Tabla2[[#This Row],[Op]]<>"","ENTREGA","") -> ENTREGA | AK66: =(Tabla2[[#This Row],[FECHA ENTREGA]]&Tabla2[[#This Row],[HORA ENTREGA]]) -> 460560,375 | AL66: =IFERROR(HYPERLINK("https://wa.me/"&Tabla2[[#This Row],[CONTACTO]]&"?text="&Tabla2[[#This Row],[Mensaje]]),"") -> https://wa.me/56973887539?text=Hola!%0AServicio del día 03-02%0A *Cliente:* GRAYSON GROUP */ Cont: * HAMU2826125*/ HR Entrega: *09:00* /Dirección: *Avda. Presidente Eduardo Frei Montalva 7050 bodega 5, Quilicura
A67: =ROW(A66) -> 66 | B67: =IF(J67=J66,B66+1,1) -> 18 | C67: GRAYSON GROUP | D67: IMPO | E67: 1191355 | F67: FSCU7107375 | G67: 40 HC | H67: 20000 | I67: 02/02 - 11:10 | J67: 46056 | K67: 0.58333333 | M67: JUAN SALINAS | N67: =IFERROR(VLOOKUP(M67,Data!$J$1:$K$58,2,0),"") -> 56978089148 | O67: HSWP-41 | Q67: Avda. Presidente Eduardo Frei Montalva 7050 bodega 5, Quilicura | R67: - | Y67: ENTREGADO | AA67: 0.60625 | AC67: 46056 | AD67: =IF(Tabla2[[#This Row],[HORA ENTREGA]]="DIRECTO","On time", IF(AA67<>"",IF(Tabla2[[#This Row],[Fecha Real Entrega]]<Tabla2[[#This Row],[FECHA ENTREGA]],"On time",IF(Tabla2[[#This Row],[Hora Real Entrega]]<=Tabla2[[#This Row],[HORA ENTREGA]]+(15/1440),"On time","Off time")),"Sin llegada")) -> Off time | AE67: =MID(Tabla2[[#This Row],[TIPO]],1,3) -> 40 | AF67: ="Hola!" & "%0A" & "Servicio del día " &TEXT(Tabla2[[#This Row],[FECHA ENTREGA]],"dd-mm") & "%0A" & " *Cliente:* " &Tabla2[[#This Row],[CLIENTE]] & " */ Cont: * "&Tabla2[[#This Row],[CONTENEDOR]] & "*/ HR Entrega: *" & TEXT(Tabla2[[#This Row],[HORA ENTREGA]],"hh:mm") & "* /Dirección: *" & Tabla2[[#This Row],[Dirección Entrega]] -> Hola!%0AServicio del día 03-02%0A *Cliente:* GRAYSON GROUP */ Cont: * FSCU7107375*/ HR Entrega: *14:00* /Dirección: *Avda. Presidente Eduardo Frei Montalva 7050 bodega 5, Quilicura | AG67: =IFERROR(HYPERLINK("https://wa.me/"&Tabla2[[#This Row],[CONTACTO]]&"?text="&Tabla2[[#This Row],[Mensaje]],"Enviar mensaje"),"") -> Enviar mensaje | AH67: =CONCATENATE(A67,F67) -> 66FSCU7107375 | AI67: =CONCATENATE("ENT-",A67) -> ENT-66 | AJ67: =IF(Tabla2[[#This Row],[Op]]<>"","ENTREGA","") -> ENTREGA | AK67: =(Tabla2[[#This Row],[FECHA ENTREGA]]&Tabla2[[#This Row],[HORA ENTREGA]]) -> 460560,583333333333333 | AL67: =IFERROR(HYPERLINK("https://wa.me/"&Tabla2[[#This Row],[CONTACTO]]&"?text="&Tabla2[[#This Row],[Mensaje]]),"") -> https://wa.me/56978089148?text=Hola!%0AServicio del día 03-02%0A *Cliente:* GRAYSON GROUP */ Cont: * FSCU7107375*/ HR Entrega: *14:00* /Dirección: *Avda. Presidente Eduardo Frei Montalva 7050 bodega 5, Quilicura
A68: =ROW(A67) -> 67 | B68: =IF(J68=J67,B67+1,1) -> 19 | C68: HORTIFRUT | D68: EXPO | E68: booking: SRC260001015 | F68: FDDU2543931 | G68: 40 RF | H68: - | I68: EXPORTACION | J68: 46056 | K68: 0.375 | M68: FRANCISCO SEPULVEDA | N68: =IFERROR(VLOOKUP(M68,Data!$J$1:$K$58,2,0),"") -> 56966631737 | O68: RFZW-97 | Q68: CONSOLIDADO: CARRERA 695, GORBEA - PLANTA HORTIFRUT GORBEA / EMBARQUE: VALP | R68: RETIRO VACIO: AGUNSA VALP | AA68: 0.89236111 | AC68: 46055 | AD68: =IF(Tabla2[[#This Row],[HORA ENTREGA]]="DIRECTO","On time", IF(AA68<>"",IF(Tabla2[[#This Row],[Fecha Real Entrega]]<Tabla2[[#This Row],[FECHA ENTREGA]],"On time",IF(Tabla2[[#This Row],[Hora Real Entrega]]<=Tabla2[[#This Row],[HORA ENTREGA]]+(15/1440),"On time","Off time")),"Sin llegada")) -> On time | AE68: =MID(Tabla2[[#This Row],[TIPO]],1,3) -> 40 | AF68: ="Hola!" & "%0A" & "Servicio del día " &TEXT(Tabla2[[#This Row],[FECHA ENTREGA]],"dd-mm") & "%0A" & " *Cliente:* " &Tabla2[[#This Row],[CLIENTE]] & " */ Cont: * "&Tabla2[[#This Row],[CONTENEDOR]] & "*/ HR Entrega: *" & TEXT(Tabla2[[#This Row],[HORA ENTREGA]],"hh:mm") & "* /Dirección: *" & Tabla2[[#This Row],[Dirección Entrega]] -> Hola!%0AServicio del día 03-02%0A *Cliente:* HORTIFRUT */ Cont: * FDDU2543931*/ HR Entrega: *09:00* /Dirección: *CONSOLIDADO: CARRERA 695, GORBEA - PLANTA HORTIFRUT GORBEA / EMBARQUE: VALP | AG68: =IFERROR(HYPERLINK("https://wa.me/"&Tabla2[[#This Row],[CONTACTO]]&"?text="&Tabla2[[#This Row],[Mensaje]],"Enviar mensaje"),"") -> Enviar mensaje | AH68: =CONCATENATE(A68,F68) -> 67FDDU2543931 | AI68: =CONCATENATE("ENT-",A68) -> ENT-67 | AJ68: =IF(Tabla2[[#This Row],[Op]]<>"","ENTREGA","") -> ENTREGA | AK68: =(Tabla2[[#This Row],[FECHA ENTREGA]]&Tabla2[[#This Row],[HORA ENTREGA]]) -> 460560,375 | AL68: =IFERROR(HYPERLINK("https://wa.me/"&Tabla2[[#This Row],[CONTACTO]]&"?text="&Tabla2[[#This Row],[Mensaje]]),"") -> https://wa.me/56966631737?text=Hola!%0AServicio del día 03-02%0A *Cliente:* HORTIFRUT */ Cont: * FDDU2543931*/ HR Entrega: *09:00* /Dirección: *CONSOLIDADO: CARRERA 695, GORBEA - PLANTA HORTIFRUT GORBEA / EMBARQUE: VALP
A69: =ROW(A68) -> 68 | B69: =IF(J69=J68,B68+1,1) -> 20 | C69: IMPORTADORA MIDEA CARRIER CHILE LTDA | D69: IMPO | E69: 2593543 | F69: CMAU5895259 | G69: 40 HC | H69: 11000 | I69: FRAGUA | J69: 46056 | K69: 0.33333333 | M69: GERARDO GALAZ | N69: =IFERROR(VLOOKUP(M69,Data!$J$1:$K$58,2,0),"") -> 56950103942 | O69: LFHK-36 | Q69: BOD. MIEA AGURTO - PUERTO MADERO 9710, BOD. E13; PUDAHUEL | R69: SITRANS SAI | X69: m5893843 | Y69: ENTREGADO | AA69: 0.28958333 | AC69: 46056 | AD69: =IF(Tabla2[[#This Row],[HORA ENTREGA]]="DIRECTO","On time", IF(AA69<>"",IF(Tabla2[[#This Row],[Fecha Real Entrega]]<Tabla2[[#This Row],[FECHA ENTREGA]],"On time",IF(Tabla2[[#This Row],[Hora Real Entrega]]<=Tabla2[[#This Row],[HORA ENTREGA]]+(15/1440),"On time","Off time")),"Sin llegada")) -> On time | AE69: =MID(Tabla2[[#This Row],[TIPO]],1,3) -> 40 | AF69: ="Hola!" & "%0A" & "Servicio del día " &TEXT(Tabla2[[#This Row],[FECHA ENTREGA]],"dd-mm") & "%0A" & " *Cliente:* " &Tabla2[[#This Row],[CLIENTE]] & " */ Cont: * "&Tabla2[[#This Row],[CONTENEDOR]] & "*/ HR Entrega: *" & TEXT(Tabla2[[#This Row],[HORA ENTREGA]],"hh:mm") & "* /Dirección: *" & Tabla2[[#This Row],[Dirección Entrega]] -> Hola!%0AServicio del día 03-02%0A *Cliente:* IMPORTADORA MIDEA CARRIER CHILE LTDA */ Cont: * CMAU5895259*/ HR Entrega: *08:00* /Dirección: *BOD. MIEA AGURTO - PUERTO MADERO 9710, BOD. E13; PUDAHUEL | AG69: =IFERROR(HYPERLINK("https://wa.me/"&Tabla2[[#This Row],[CONTACTO]]&"?text="&Tabla2[[#This Row],[Mensaje]],"Enviar mensaje"),"") -> Enviar mensaje | AH69: =CONCATENATE(A69,F69) -> 68CMAU5895259 | AI69: =CONCATENATE("ENT-",A69) -> ENT-68 | AJ69: =IF(Tabla2[[#This Row],[Op]]<>"","ENTREGA","") -> ENTREGA | AK69: =(Tabla2[[#This Row],[FECHA ENTREGA]]&Tabla2[[#This Row],[HORA ENTREGA]]) -> 460560,333333333333333 | AL69: =IFERROR(HYPERLINK("https://wa.me/"&Tabla2[[#This Row],[CONTACTO]]&"?text="&Tabla2[[#This Row],[Mensaje]]),"") -> https://wa.me/56950103942?text=Hola!%0AServicio del día 03-02%0A *Cliente:* IMPORTADORA MIDEA CARRIER CHILE LTDA */ Cont: * CMAU5895259*/ HR Entrega: *08:00* /Dirección: *BOD. MIEA AGURTO - PUERTO MADERO 9710, BOD. E13; PUDAHUEL
A70: =ROW(A69) -> 69 | B70: =IF(J70=J69,B69+1,1) -> 21 | C70: IMPORTADORA MIDEA CARRIER CHILE LTDA | D70: IMPO | E70: 2593544 | F70: CMAU4273878 | G70: 40 HC | H70: 10000 | I70: FRAGUA | J70: 46056 | K70: 0.375 | M70: MIGUEL CACERES LOYOLA | N70: =IFERROR(VLOOKUP(M70,Data!$J$1:$K$58,2,0),"") -> 56967387744 | O70: LXCB-59 | Q70: BOD. MIEA AGURTO - PUERTO MADERO 9710, BOD. E13; PUDAHUEL | R70: CIS | X70: m7979818 | Y70: ENTREGADO | AA70: 0.31597222 | AC70: 46056 | AD70: =IF(Tabla2[[#This Row],[HORA ENTREGA]]="DIRECTO","On time", IF(AA70<>"",IF(Tabla2[[#This Row],[Fecha Real Entrega]]<Tabla2[[#This Row],[FECHA ENTREGA]],"On time",IF(Tabla2[[#This Row],[Hora Real Entrega]]<=Tabla2[[#This Row],[HORA ENTREGA]]+(15/1440),"On time","Off time")),"Sin llegada")) -> On time | AE70: =MID(Tabla2[[#This Row],[TIPO]],1,3) -> 40 | AF70: ="Hola!" & "%0A" & "Servicio del día " &TEXT(Tabla2[[#This Row],[FECHA ENTREGA]],"dd-mm") & "%0A" & " *Cliente:* " &Tabla2[[#This Row],[CLIENTE]] & " */ Cont: * "&Tabla2[[#This Row],[CONTENEDOR]] & "*/ HR Entrega: *" & TEXT(Tabla2[[#This Row],[HORA ENTREGA]],"hh:mm") & "* /Dirección: *" & Tabla2[[#This Row],[Dirección Entrega]] -> Hola!%0AServicio del día 03-02%0A *Cliente:* IMPORTADORA MIDEA CARRIER CHILE LTDA */ Cont: * CMAU4273878*/ HR Entrega: *09:00* /Dirección: *BOD. MIEA AGURTO - PUERTO MADERO 9710, BOD. E13; PUDAHUEL | AG70: =IFERROR(HYPERLINK("https://wa.me/"&Tabla2[[#This Row],[CONTACTO]]&"?text="&Tabla2[[#This Row],[Mensaje]],"Enviar mensaje"),"") -> Enviar mensaje | AH70: =CONCATENATE(A70,F70) -> 69CMAU4273878 | AI70: =CONCATENATE("ENT-",A70) -> ENT-69 | AJ70: =IF(Tabla2[[#This Row],[Op]]<>"","ENTREGA","") -> ENTREGA | AK70: =(Tabla2[[#This Row],[FECHA ENTREGA]]&Tabla2[[#This Row],[HORA ENTREGA]]) -> 460560,375 | AL70: =IFERROR(HYPERLINK("https://wa.me/"&Tabla2[[#This Row],[CONTACTO]]&"?text="&Tabla2[[#This Row],[Mensaje]]),"") -> https://wa.me/56967387744?text=Hola!%0AServicio del día 03-02%0A *Cliente:* IMPORTADORA MIDEA CARRIER CHILE LTDA */ Cont: * CMAU4273878*/ HR Entrega: *09:00* /Dirección: *BOD. MIEA AGURTO - PUERTO MADERO 9710, BOD. E13; PUDAHUEL
A71: =ROW(A70) -> 70 | B71: =IF(J71=J70,B70+1,1) -> 22 | C71: IMPORTADORA MIDEA CARRIER CHILE LTDA | D71: IMPO | E71: 2598836 | F71: APHU7039171 | G71: 40 HC | H71: 10000 | I71: FRAGUA | J71: 46056 | K71: 0.45833333 | M71: GERLINDHER BERNUY | N71: =IFERROR(VLOOKUP(M71,Data!$J$1:$K$58,2,0),"") -> 56926181825 | O71: RRVF-72 | Q71: BOD. MIEA AGURTO - PUERTO MADERO 9710, BOD. E13; PUDAHUEL | R71: CIS | X71: m7974670 | Y71: ENTREGADO | AA71: 0.57013889 | AC71: 46056 | AD71: =IF(Tabla2[[#This Row],[HORA ENTREGA]]="DIRECTO","On time", IF(AA71<>"",IF(Tabla2[[#This Row],[Fecha Real Entrega]]<Tabla2[[#This Row],[FECHA ENTREGA]],"On time",IF(Tabla2[[#This Row],[Hora Real Entrega]]<=Tabla2[[#This Row],[HORA ENTREGA]]+(15/1440),"On time","Off time")),"Sin llegada")) -> Off time | AE71: =MID(Tabla2[[#This Row],[TIPO]],1,3) -> 40 | AF71: ="Hola!" & "%0A" & "Servicio del día " &TEXT(Tabla2[[#This Row],[FECHA ENTREGA]],"dd-mm") & "%0A" & " *Cliente:* " &Tabla2[[#This Row],[CLIENTE]] & " */ Cont: * "&Tabla2[[#This Row],[CONTENEDOR]] & "*/ HR Entrega: *" & TEXT(Tabla2[[#This Row],[HORA ENTREGA]],"hh:mm") & "* /Dirección: *" & Tabla2[[#This Row],[Dirección Entrega]] -> Hola!%0AServicio del día 03-02%0A *Cliente:* IMPORTADORA MIDEA CARRIER CHILE LTDA */ Cont: * APHU7039171*/ HR Entrega: *11:00* /Dirección: *BOD. MIEA AGURTO - PUERTO MADERO 9710, BOD. E13; PUDAHUEL | AG71: =IFERROR(HYPERLINK("https://wa.me/"&Tabla2[[#This Row],[CONTACTO]]&"?text="&Tabla2[[#This Row],[Mensaje]],"Enviar mensaje"),"") -> Enviar mensaje | AH71: =CONCATENATE(A71,F71) -> 70APHU7039171 | AI71: =CONCATENATE("ENT-",A71) -> ENT-70 | AJ71: =IF(Tabla2[[#This Row],[Op]]<>"","ENTREGA","") -> ENTREGA | AK71: =(Tabla2[[#This Row],[FECHA ENTREGA]]&Tabla2[[#This Row],[HORA ENTREGA]]) -> 460560,458333333333333 | AL71: =IFERROR(HYPERLINK("https://wa.me/"&Tabla2[[#This Row],[CONTACTO]]&"?text="&Tabla2[[#This Row],[Mensaje]]),"") -> https://wa.me/56926181825?text=Hola!%0AServicio del día 03-02%0A *Cliente:* IMPORTADORA MIDEA CARRIER CHILE LTDA */ Cont: * APHU7039171*/ HR Entrega: *11:00* /Dirección: *BOD. MIEA AGURTO - PUERTO MADERO 9710, BOD. E13; PUDAHUEL
A72: =ROW(A71) -> 71 | B72: =IF(J72=J71,B71+1,1) -> 23 | C72: IMPORTADORA MIDEA CARRIER CHILE LTDA | D72: IMPO | E72: 2593658 | F72: TRHU8609672 | G72: 40 HC | H72: 10000 | I72: FRAGUA | J72: 46056 | K72: 0.45833333 | M72: HECTOR GONZALEZ | N72: =IFERROR(VLOOKUP(M72,Data!$J$1:$K$58,2,0),"") -> 56948501048 | O72: RLGL-22 | Q72: BOD. MIEA AGURTO - PUERTO MADERO 9710, BOD. E13; PUDAHUEL | R72: SITRANS SAI | X72: cndk87645ca | Y72: ENTREGADO | AA72: 0.55208333 | AC72: 46056 | AD72: =IF(Tabla2[[#This Row],[HORA ENTREGA]]="DIRECTO","On time", IF(AA72<>"",IF(Tabla2[[#This Row],[Fecha Real Entrega]]<Tabla2[[#This Row],[FECHA ENTREGA]],"On time",IF(Tabla2[[#This Row],[Hora Real Entrega]]<=Tabla2[[#This Row],[HORA ENTREGA]]+(15/1440),"On time","Off time")),"Sin llegada")) -> Off time | AE72: =MID(Tabla2[[#This Row],[TIPO]],1,3) -> 40 | AF72: ="Hola!" & "%0A" & "Servicio del día " &TEXT(Tabla2[[#This Row],[FECHA ENTREGA]],"dd-mm") & "%0A" & " *Cliente:* " &Tabla2[[#This Row],[CLIENTE]] & " */ Cont: * "&Tabla2[[#This Row],[CONTENEDOR]] & "*/ HR Entrega: *" & TEXT(Tabla2[[#This Row],[HORA ENTREGA]],"hh:mm") & "* /Dirección: *" & Tabla2[[#This Row],[Dirección Entrega]] -> Hola!%0AServicio del día 03-02%0A *Cliente:* IMPORTADORA MIDEA CARRIER CHILE LTDA */ Cont: * TRHU8609672*/ HR Entrega: *11:00* /Dirección: *BOD. MIEA AGURTO - PUERTO MADERO 9710, BOD. E13; PUDAHUEL | AG72: =IFERROR(HYPERLINK("https://wa.me/"&Tabla2[[#This Row],[CONTACTO]]&"?text="&Tabla2[[#This Row],[Mensaje]],"Enviar mensaje"),"") -> Enviar mensaje | AH72: =CONCATENATE(A72,F72) -> 71TRHU8609672 | AI72: =CONCATENATE("ENT-",A72) -> ENT-71 | AJ72: =IF(Tabla2[[#This Row],[Op]]<>"","ENTREGA","") -> ENTREGA | AK72: =(Tabla2[[#This Row],[FECHA ENTREGA]]&Tabla2[[#This Row],[HORA ENTREGA]]) -> 460560,458333333333333 | AL72: =IFERROR(HYPERLINK("https://wa.me/"&Tabla2[[#This Row],[CONTACTO]]&"?text="&Tabla2[[#This Row],[Mensaje]]),"") -> https://wa.me/56948501048?text=Hola!%0AServicio del día 03-02%0A *Cliente:* IMPORTADORA MIDEA CARRIER CHILE LTDA */ Cont: * TRHU8609672*/ HR Entrega: *11:00* /Dirección: *BOD. MIEA AGURTO - PUERTO MADERO 9710, BOD. E13; PUDAHUEL
A73: =ROW(A72) -> 72 | B73: =IF(J73=J72,B72+1,1) -> 24 | C73: IMPORTADORA MIDEA CARRIER CHILE LTDA | D73: IMPO | E73: 2593663 | F73: TCNU6554031 | G73: 40 HC | H73: 10000 | I73: FRAGUA | J73: 46056 | K73: 0.45833333 | M73: HELBERTH CASTRO | N73: =IFERROR(VLOOKUP(M73,Data!$J$1:$K$58,2,0),"") -> 56967256951 | O73: RFZW-96 | Q73: BOD. MIEA AGURTO - PUERTO MADERO 9710, BOD. E13; PUDAHUEL | R73: SITRANS SAI | X73: cndk87655ca | Y73: ENTREGADO | AA73: 0.55902778 | AC73: 46056 | AD73: =IF(Tabla2[[#This Row],[HORA ENTREGA]]="DIRECTO","On time", IF(AA73<>"",IF(Tabla2[[#This Row],[Fecha Real Entrega]]<Tabla2[[#This Row],[FECHA ENTREGA]],"On time",IF(Tabla2[[#This Row],[Hora Real Entrega]]<=Tabla2[[#This Row],[HORA ENTREGA]]+(15/1440),"On time","Off time")),"Sin llegada")) -> Off time | AE73: =MID(Tabla2[[#This Row],[TIPO]],1,3) -> 40 | AF73: ="Hola!" & "%0A" & "Servicio del día " &TEXT(Tabla2[[#This Row],[FECHA ENTREGA]],"dd-mm") & "%0A" & " *Cliente:* " &Tabla2[[#This Row],[CLIENTE]] & " */ Cont: * "&Tabla2[[#This Row],[CONTENEDOR]] & "*/ HR Entrega: *" & TEXT(Tabla2[[#This Row],[HORA ENTREGA]],"hh:mm") & "* /Dirección: *" & Tabla2[[#This Row],[Dirección Entrega]] -> Hola!%0AServicio del día 03-02%0A *Cliente:* IMPORTADORA MIDEA CARRIER CHILE LTDA */ Cont: * TCNU6554031*/ HR Entrega: *11:00* /Dirección: *BOD. MIEA AGURTO - PUERTO MADERO 9710, BOD. E13; PUDAHUEL | AG73: =IFERROR(HYPERLINK("https://wa.me/"&Tabla2[[#This Row],[CONTACTO]]&"?text="&Tabla2[[#This Row],[Mensaje]],"Enviar mensaje"),"") -> Enviar mensaje | AH73: =CONCATENATE(A73,F73) -> 72TCNU6554031 | AI73: =CONCATENATE("ENT-",A73) -> ENT-72 | AJ73: =IF(Tabla2[[#This Row],[Op]]<>"","ENTREGA","") -> ENTREGA | AK73: =(Tabla2[[#This Row],[FECHA ENTREGA]]&Tabla2[[#This Row],[HORA ENTREGA]]) -> 460560,458333333333333 | AL73: =IFERROR(HYPERLINK("https://wa.me/"&Tabla2[[#This Row],[CONTACTO]]&"?text="&Tabla2[[#This Row],[Mensaje]]),"") -> https://wa.me/56967256951?text=Hola!%0AServicio del día 03-02%0A *Cliente:* IMPORTADORA MIDEA CARRIER CHILE LTDA */ Cont: * TCNU6554031*/ HR Entrega: *11:00* /Dirección: *BOD. MIEA AGURTO - PUERTO MADERO 9710, BOD. E13; PUDAHUEL
A74: =ROW(A73) -> 73 | B74: =IF(J74=J73,B73+1,1) -> 25 | C74: IMPORTADORA MIDEA CARRIER CHILE LTDA | D74: IMPO | E74: 2598835 | F74: ECMU7645971 | G74: 40 HC | H74: 10000 | I74: FRAGUA | J74: 46056 | K74: 0.5 | M74: JUAN CASTAÑEDA | N74: =IFERROR(VLOOKUP(M74,Data!$J$1:$K$58,2,0),"") -> 56964850744 | O74: RKLF-61 | Q74: BOD. MIEA AGURTO - PUERTO MADERO 9710, BOD. E13; PUDAHUEL | R74: CIS | X74: m7974661 | Y74: ENTREGADO | AA74: 0.55902778 | AC74: 46056 | AD74: =IF(Tabla2[[#This Row],[HORA ENTREGA]]="DIRECTO","On time", IF(AA74<>"",IF(Tabla2[[#This Row],[Fecha Real Entrega]]<Tabla2[[#This Row],[FECHA ENTREGA]],"On time",IF(Tabla2[[#This Row],[Hora Real Entrega]]<=Tabla2[[#This Row],[HORA ENTREGA]]+(15/1440),"On time","Off time")),"Sin llegada")) -> Off time | AE74: =MID(Tabla2[[#This Row],[TIPO]],1,3) -> 40 | AF74: ="Hola!" & "%0A" & "Servicio del día " &TEXT(Tabla2[[#This Row],[FECHA ENTREGA]],"dd-mm") & "%0A" & " *Cliente:* " &Tabla2[[#This Row],[CLIENTE]] & " */ Cont: * "&Tabla2[[#This Row],[CONTENEDOR]] & "*/ HR Entrega: *" & TEXT(Tabla2[[#This Row],[HORA ENTREGA]],"hh:mm") & "* /Dirección: *" & Tabla2[[#This Row],[Dirección Entrega]] -> Hola!%0AServicio del día 03-02%0A *Cliente:* IMPORTADORA MIDEA CARRIER CHILE LTDA */ Cont: * ECMU7645971*/ HR Entrega: *12:00* /Dirección: *BOD. MIEA AGURTO - PUERTO MADERO 9710, BOD. E13; PUDAHUEL | AG74: =IFERROR(HYPERLINK("https://wa.me/"&Tabla2[[#This Row],[CONTACTO]]&"?text="&Tabla2[[#This Row],[Mensaje]],"Enviar mensaje"),"") -> Enviar mensaje | AH74: =CONCATENATE(A74,F74) -> 73ECMU7645971 | AI74: =CONCATENATE("ENT-",A74) -> ENT-73 | AJ74: =IF(Tabla2[[#This Row],[Op]]<>"","ENTREGA","") -> ENTREGA | AK74: =(Tabla2[[#This Row],[FECHA ENTREGA]]&Tabla2[[#This Row],[HORA ENTREGA]]) -> 460560,5 | AL74: =IFERROR(HYPERLINK("https://wa.me/"&Tabla2[[#This Row],[CONTACTO]]&"?text="&Tabla2[[#This Row],[Mensaje]]),"") -> https://wa.me/56964850744?text=Hola!%0AServicio del día 03-02%0A *Cliente:* IMPORTADORA MIDEA CARRIER CHILE LTDA */ Cont: * ECMU7645971*/ HR Entrega: *12:00* /Dirección: *BOD. MIEA AGURTO - PUERTO MADERO 9710, BOD. E13; PUDAHUEL
A75: =ROW(A74) -> 74 | B75: =IF(J75=J74,B74+1,1) -> 26 | C75: IMPORTADORA MIDEA CARRIER CHILE LTDA | D75: IMPO | E75: 2598835 | F75: CMAU5235527 | G75: 40 HC | H75: 10000 | I75: FRAGUA | J75: 46056 | K75: 0.5 | M75: CARLOS AGUILAR | N75: =IFERROR(VLOOKUP(M75,Data!$J$1:$K$58,2,0),"") -> 56984994337 | O75: TRKJ-66 | Q75: BOD. MIEA AGURTO - PUERTO MADERO 9710, BOD. E13; PUDAHUEL | R75: CIS | X75: m7973282 | Y75: ENTREGADO | AA75: 0.55902778 | AC75: 46056 | AD75: =IF(Tabla2[[#This Row],[HORA ENTREGA]]="DIRECTO","On time", IF(AA75<>"",IF(Tabla2[[#This Row],[Fecha Real Entrega]]<Tabla2[[#This Row],[FECHA ENTREGA]],"On time",IF(Tabla2[[#This Row],[Hora Real Entrega]]<=Tabla2[[#This Row],[HORA ENTREGA]]+(15/1440),"On time","Off time")),"Sin llegada")) -> Off time | AE75: =MID(Tabla2[[#This Row],[TIPO]],1,3) -> 40 | AF75: ="Hola!" & "%0A" & "Servicio del día " &TEXT(Tabla2[[#This Row],[FECHA ENTREGA]],"dd-mm") & "%0A" & " *Cliente:* " &Tabla2[[#This Row],[CLIENTE]] & " */ Cont: * "&Tabla2[[#This Row],[CONTENEDOR]] & "*/ HR Entrega: *" & TEXT(Tabla2[[#This Row],[HORA ENTREGA]],"hh:mm") & "* /Dirección: *" & Tabla2[[#This Row],[Dirección Entrega]] -> Hola!%0AServicio del día 03-02%0A *Cliente:* IMPORTADORA MIDEA CARRIER CHILE LTDA */ Cont: * CMAU5235527*/ HR Entrega: *12:00* /Dirección: *BOD. MIEA AGURTO - PUERTO MADERO 9710, BOD. E13; PUDAHUEL | AG75: =IFERROR(HYPERLINK("https://wa.me/"&Tabla2[[#This Row],[CONTACTO]]&"?text="&Tabla2[[#This Row],[Mensaje]],"Enviar mensaje"),"") -> Enviar mensaje | AH75: =CONCATENATE(A75,F75) -> 74CMAU5235527 | AI75: =CONCATENATE("ENT-",A75) -> ENT-74 | AJ75: =IF(Tabla2[[#This Row],[Op]]<>"","ENTREGA","") -> ENTREGA | AK75: =(Tabla2[[#This Row],[FECHA ENTREGA]]&Tabla2[[#This Row],[HORA ENTREGA]]) -> 460560,5 | AL75: =IFERROR(HYPERLINK("https://wa.me/"&Tabla2[[#This Row],[CONTACTO]]&"?text="&Tabla2[[#This Row],[Mensaje]]),"") -> https://wa.me/56984994337?text=Hola!%0AServicio del día 03-02%0A *Cliente:* IMPORTADORA MIDEA CARRIER CHILE LTDA */ Cont: * CMAU5235527*/ HR Entrega: *12:00* /Dirección: *BOD. MIEA AGURTO - PUERTO MADERO 9710, BOD. E13; PUDAHUEL
A76: =ROW(A75) -> 75 | B76: =IF(J76=J75,B75+1,1) -> 27 | C76: IMPORTADORA MIDEA CARRIER CHILE LTDA | D76: IMPO | E76: 2598835 | F76: SEGU4633921 | G76: 40 HC | H76: 10000 | I76: FRAGUA | J76: 46056 | K76: 0.5 | N76: =IFERROR(VLOOKUP(M76,Data!$J$1:$K$58,2,0),"") | Q76: BOD. MIEA AGURTO - PUERTO MADERO 9710, BOD. E13; PUDAHUEL | R76: CIS | X76: m7974562 | Y76: PENDIENTE | Z76: FUERA DE HORARIO / REPROGRAMADO | AD76: =IF(Tabla2[[#This Row],[HORA ENTREGA]]="DIRECTO","On time", IF(AA76<>"",IF(Tabla2[[#This Row],[Fecha Real Entrega]]<Tabla2[[#This Row],[FECHA ENTREGA]],"On time",IF(Tabla2[[#This Row],[Hora Real Entrega]]<=Tabla2[[#This Row],[HORA ENTREGA]]+(15/1440),"On time","Off time")),"Sin llegada")) -> Sin llegada | AE76: =MID(Tabla2[[#This Row],[TIPO]],1,3) -> 40 | AF76: ="Hola!" & "%0A" & "Servicio del día " &TEXT(Tabla2[[#This Row],[FECHA ENTREGA]],"dd-mm") & "%0A" & " *Cliente:* " &Tabla2[[#This Row],[CLIENTE]] & " */ Cont: * "&Tabla2[[#This Row],[CONTENEDOR]] & "*/ HR Entrega: *" & TEXT(Tabla2[[#This Row],[HORA ENTREGA]],"hh:mm") & "* /Dirección: *" & Tabla2[[#This Row],[Dirección Entrega]] -> Hola!%0AServicio del día 03-02%0A *Cliente:* IMPORTADORA MIDEA CARRIER CHILE LTDA */ Cont: * SEGU4633921*/ HR Entrega: *12:00* /Dirección: *BOD. MIEA AGURTO - PUERTO MADERO 9710, BOD. E13; PUDAHUEL | AG76: =IFERROR(HYPERLINK("https://wa.me/"&Tabla2[[#This Row],[CONTACTO]]&"?text="&Tabla2[[#This Row],[Mensaje]],"Enviar mensaje"),"") -> Enviar mensaje | AH76: =CONCATENATE(A76,F76) -> 75SEGU4633921 | AI76: =CONCATENATE("ENT-",A76) -> ENT-75 | AJ76: =IF(Tabla2[[#This Row],[Op]]<>"","ENTREGA","") -> ENTREGA | AK76: =(Tabla2[[#This Row],[FECHA ENTREGA]]&Tabla2[[#This Row],[HORA ENTREGA]]) -> 460560,5 | AL76: =IFERROR(HYPERLINK("https://wa.me/"&Tabla2[[#This Row],[CONTACTO]]&"?text="&Tabla2[[#This Row],[Mensaje]]),"") -> https://wa.me/?text=Hola!%0AServicio del día 03-02%0A *Cliente:* IMPORTADORA MIDEA CARRIER CHILE LTDA */ Cont: * SEGU4633921*/ HR Entrega: *12:00* /Dirección: *BOD. MIEA AGURTO - PUERTO MADERO 9710, BOD. E13; PUDAHUEL
A77: =ROW(A76) -> 76 | B77: =IF(J77=J76,B76+1,1) -> 28 | C77: IMPORTADORA MIDEA CARRIER CHILE LTDA | D77: IMPO | E77: 2593661 | F77: FDCU0600812 | G77: 40 HC | H77: 10000 | I77: FRAGUA | J77: 46056 | K77: 0.54166667 | N77: =IFERROR(VLOOKUP(M77,Data!$J$1:$K$58,2,0),"") | Q77: BOD. MIEA AGURTO - PUERTO MADERO 9710, BOD. E13; PUDAHUEL | R77: SITRANS SAI | X77: cndl30386ca | Y77: PENDIENTE | Z77: FUERA DE HORARIO / REPROGRAMADO | AD77: =IF(Tabla2[[#This Row],[HORA ENTREGA]]="DIRECTO","On time", IF(AA77<>"",IF(Tabla2[[#This Row],[Fecha Real Entrega]]<Tabla2[[#This Row],[FECHA ENTREGA]],"On time",IF(Tabla2[[#This Row],[Hora Real Entrega]]<=Tabla2[[#This Row],[HORA ENTREGA]]+(15/1440),"On time","Off time")),"Sin llegada")) -> Sin llegada | AE77: =MID(Tabla2[[#This Row],[TIPO]],1,3) -> 40 | AF77: ="Hola!" & "%0A" & "Servicio del día " &TEXT(Tabla2[[#This Row],[FECHA ENTREGA]],"dd-mm") & "%0A" & " *Cliente:* " &Tabla2[[#This Row],[CLIENTE]] & " */ Cont: * "&Tabla2[[#This Row],[CONTENEDOR]] & "*/ HR Entrega: *" & TEXT(Tabla2[[#This Row],[HORA ENTREGA]],"hh:mm") & "* /Dirección: *" & Tabla2[[#This Row],[Dirección Entrega]] -> Hola!%0AServicio del día 03-02%0A *Cliente:* IMPORTADORA MIDEA CARRIER CHILE LTDA */ Cont: * FDCU0600812*/ HR Entrega: *13:00* /Dirección: *BOD. MIEA AGURTO - PUERTO MADERO 9710, BOD. E13; PUDAHUEL | AG77: =IFERROR(HYPERLINK("https://wa.me/"&Tabla2[[#This Row],[CONTACTO]]&"?text="&Tabla2[[#This Row],[Mensaje]],"Enviar mensaje"),"") -> Enviar mensaje | AH77: =CONCATENATE(A77,F77) -> 76FDCU0600812 | AI77: =CONCATENATE("ENT-",A77) -> ENT-76 | AJ77: =IF(Tabla2[[#This Row],[Op]]<>"","ENTREGA","") -> ENTREGA | AK77: =(Tabla2[[#This Row],[FECHA ENTREGA]]&Tabla2[[#This Row],[HORA ENTREGA]]) -> 460560,541666666666667 | AL77: =IFERROR(HYPERLINK("https://wa.me/"&Tabla2[[#This Row],[CONTACTO]]&"?text="&Tabla2[[#This Row],[Mensaje]]),"") -> https://wa.me/?text=Hola!%0AServicio del día 03-02%0A *Cliente:* IMPORTADORA MIDEA CARRIER CHILE LTDA */ Cont: * FDCU0600812*/ HR Entrega: *13:00* /Dirección: *BOD. MIEA AGURTO - PUERTO MADERO 9710, BOD. E13; PUDAHUEL
A78: =ROW(A77) -> 77 | B78: =IF(J78=J77,B77+1,1) -> 29 | C78: INVERSIERRA S A | D78: IMPO | E78: 873070 | F78: HLBU2307691 | G78: 20 DV | H78: 25000 | I78: FRAGUA | J78: 46056 | K78: 0.33333333 | M78: JORGE PACHECO PLAZA | N78: =IFERROR(VLOOKUP(M78,Data!$J$1:$K$58,2,0),"") -> 56966749395 | O78: LPYG-89 | Q78: HUECHURABA | R78: CIS | X78: RAMPLA CORTA | Y78: ENTREGADO | AA78: 0.33333333 | AC78: 46056 | AD78: =IF(Tabla2[[#This Row],[HORA ENTREGA]]="DIRECTO","On time", IF(AA78<>"",IF(Tabla2[[#This Row],[Fecha Real Entrega]]<Tabla2[[#This Row],[FECHA ENTREGA]],"On time",IF(Tabla2[[#This Row],[Hora Real Entrega]]<=Tabla2[[#This Row],[HORA ENTREGA]]+(15/1440),"On time","Off time")),"Sin llegada")) -> On time | AE78: =MID(Tabla2[[#This Row],[TIPO]],1,3) -> 20 | AF78: ="Hola!" & "%0A" & "Servicio del día " &TEXT(Tabla2[[#This Row],[FECHA ENTREGA]],"dd-mm") & "%0A" & " *Cliente:* " &Tabla2[[#This Row],[CLIENTE]] & " */ Cont: * "&Tabla2[[#This Row],[CONTENEDOR]] & "*/ HR Entrega: *" & TEXT(Tabla2[[#This Row],[HORA ENTREGA]],"hh:mm") & "* /Dirección: *" & Tabla2[[#This Row],[Dirección Entrega]] -> Hola!%0AServicio del día 03-02%0A *Cliente:* INVERSIERRA S A */ Cont: * HLBU2307691*/ HR Entrega: *08:00* /Dirección: *HUECHURABA | AG78: =IFERROR(HYPERLINK("https://wa.me/"&Tabla2[[#This Row],[CONTACTO]]&"?text="&Tabla2[[#This Row],[Mensaje]],"Enviar mensaje"),"") -> Enviar mensaje | AH78: =CONCATENATE(A78,F78) -> 77HLBU2307691 | AI78: =CONCATENATE("ENT-",A78) -> ENT-77 | AJ78: =IF(Tabla2[[#This Row],[Op]]<>"","ENTREGA","") -> ENTREGA | AK78: =(Tabla2[[#This Row],[FECHA ENTREGA]]&Tabla2[[#This Row],[HORA ENTREGA]]) -> 460560,333333333333333 | AL78: =IFERROR(HYPERLINK("https://wa.me/"&Tabla2[[#This Row],[CONTACTO]]&"?text="&Tabla2[[#This Row],[Mensaje]]),"") -> https://wa.me/56966749395?text=Hola!%0AServicio del día 03-02%0A *Cliente:* INVERSIERRA S A */ Cont: * HLBU2307691*/ HR Entrega: *08:00* /Dirección: *HUECHURABA
A79: =ROW(A78) -> 78 | B79: =IF(J79=J78,B78+1,1) -> 30 | C79: INVERSIERRA S A | D79: IMPO | E79: 871760 | F79: SEGU4764515 | G79: 40 HC | H79: 25000 | I79: FRAGUA | J79: 46056 | K79: 0.33333333 | M79: CARLOS ALBERTO DIAZ | N79: =IFERROR(VLOOKUP(M79,Data!$J$1:$K$58,2,0),"") -> 56978089957 | O79: RVFP-33 | Q79: QUILICURA | R79: - | Y79: ENTREGADO | AA79: 0.34166667 | AC79: 46056 | AD79: =IF(Tabla2[[#This Row],[HORA ENTREGA]]="DIRECTO","On time", IF(AA79<>"",IF(Tabla2[[#This Row],[Fecha Real Entrega]]<Tabla2[[#This Row],[FECHA ENTREGA]],"On time",IF(Tabla2[[#This Row],[Hora Real Entrega]]<=Tabla2[[#This Row],[HORA ENTREGA]]+(15/1440),"On time","Off time")),"Sin llegada")) -> On time | AE79: =MID(Tabla2[[#This Row],[TIPO]],1,3) -> 40 | AF79: ="Hola!" & "%0A" & "Servicio del día " &TEXT(Tabla2[[#This Row],[FECHA ENTREGA]],"dd-mm") & "%0A" & " *Cliente:* " &Tabla2[[#This Row],[CLIENTE]] & " */ Cont: * "&Tabla2[[#This Row],[CONTENEDOR]] & "*/ HR Entrega: *" & TEXT(Tabla2[[#This Row],[HORA ENTREGA]],"hh:mm") & "* /Dirección: *" & Tabla2[[#This Row],[Dirección Entrega]] -> Hola!%0AServicio del día 03-02%0A *Cliente:* INVERSIERRA S A */ Cont: * SEGU4764515*/ HR Entrega: *08:00* /Dirección: *QUILICURA | AG79: =IFERROR(HYPERLINK("https://wa.me/"&Tabla2[[#This Row],[CONTACTO]]&"?text="&Tabla2[[#This Row],[Mensaje]],"Enviar mensaje"),"") -> Enviar mensaje | AH79: =CONCATENATE(A79,F79) -> 78SEGU4764515 | AI79: =CONCATENATE("ENT-",A79) -> ENT-78 | AJ79: =IF(Tabla2[[#This Row],[Op]]<>"","ENTREGA","") -> ENTREGA | AK79: =(Tabla2[[#This Row],[FECHA ENTREGA]]&Tabla2[[#This Row],[HORA ENTREGA]]) -> 460560,333333333333333 | AL79: =IFERROR(HYPERLINK("https://wa.me/"&Tabla2[[#This Row],[CONTACTO]]&"?text="&Tabla2[[#This Row],[Mensaje]]),"") -> https://wa.me/56978089957?text=Hola!%0AServicio del día 03-02%0A *Cliente:* INVERSIERRA S A */ Cont: * SEGU4764515*/ HR Entrega: *08:00* /Dirección: *QUILICURA
A80: =ROW(A79) -> 79 | B80: =IF(J80=J79,B79+1,1) -> 31 | C80: INVERSIERRA S A | D80: IMPO | E80: 871760 | F80: TIIU4544389 | G80: 40 HC | H80: 26000 | I80: FRAGUA | J80: 46056 | K80: 0.5 | M80: GERARDO GALAZ | N80: =IFERROR(VLOOKUP(M80,Data!$J$1:$K$58,2,0),"") -> 56950103942 | O80: LFHK-36 | Q80: QUILICURA | R80: MEDLOG SAI | Y80: ENTREGADO | AA80: 0.54652778 | AC80: 46056 | AD80: =IF(Tabla2[[#This Row],[HORA ENTREGA]]="DIRECTO","On time", IF(AA80<>"",IF(Tabla2[[#This Row],[Fecha Real Entrega]]<Tabla2[[#This Row],[FECHA ENTREGA]],"On time",IF(Tabla2[[#This Row],[Hora Real Entrega]]<=Tabla2[[#This Row],[HORA ENTREGA]]+(15/1440),"On time","Off time")),"Sin llegada")) -> Off time | AE80: =MID(Tabla2[[#This Row],[TIPO]],1,3) -> 40 | AF80: ="Hola!" & "%0A" & "Servicio del día " &TEXT(Tabla2[[#This Row],[FECHA ENTREGA]],"dd-mm") & "%0A" & " *Cliente:* " &Tabla2[[#This Row],[CLIENTE]] & " */ Cont: * "&Tabla2[[#This Row],[CONTENEDOR]] & "*/ HR Entrega: *" & TEXT(Tabla2[[#This Row],[HORA ENTREGA]],"hh:mm") & "* /Dirección: *" & Tabla2[[#This Row],[Dirección Entrega]] -> Hola!%0AServicio del día 03-02%0A *Cliente:* INVERSIERRA S A */ Cont: * TIIU4544389*/ HR Entrega: *12:00* /Dirección: *QUILICURA | AG80: =IFERROR(HYPERLINK("https://wa.me/"&Tabla2[[#This Row],[CONTACTO]]&"?text="&Tabla2[[#This Row],[Mensaje]],"Enviar mensaje"),"") -> Enviar mensaje | AH80: =CONCATENATE(A80,F80) -> 79TIIU4544389 | AI80: =CONCATENATE("ENT-",A80) -> ENT-79 | AJ80: =IF(Tabla2[[#This Row],[Op]]<>"","ENTREGA","") -> ENTREGA | AK80: =(Tabla2[[#This Row],[FECHA ENTREGA]]&Tabla2[[#This Row],[HORA ENTREGA]]) -> 460560,5 | AL80: =IFERROR(HYPERLINK("https://wa.me/"&Tabla2[[#This Row],[CONTACTO]]&"?text="&Tabla2[[#This Row],[Mensaje]]),"") -> https://wa.me/56950103942?text=Hola!%0AServicio del día 03-02%0A *Cliente:* INVERSIERRA S A */ Cont: * TIIU4544389*/ HR Entrega: *12:00* /Dirección: *QUILICURA
A81: =ROW(A80) -> 80 | B81: =IF(J81=J80,B80+1,1) -> 32 | C81: LAMAIGNERE CHILE S.A. | D81: IMPO | E81: 187906 | F81: ECMU5095006 | G81: 40 HC | H81: 30000 | I81: FRAGUA | J81: 46056 | K81: 0.41666667 | M81: JUAN SANHUEZA | N81: =IFERROR(VLOOKUP(M81,Data!$J$1:$K$58,2,0),"") -> 56967398822 | O81: LGGR-16 | Q81: AV. MARTA OSSA RUIZ 601 (CAMINO CASAS VIEJAS); MAIPU | R81: CIS | Y81: ENTREGADO | AA81: 0.50694444 | AC81: 46056 | AD81: =IF(Tabla2[[#This Row],[HORA ENTREGA]]="DIRECTO","On time", IF(AA81<>"",IF(Tabla2[[#This Row],[Fecha Real Entrega]]<Tabla2[[#This Row],[FECHA ENTREGA]],"On time",IF(Tabla2[[#This Row],[Hora Real Entrega]]<=Tabla2[[#This Row],[HORA ENTREGA]]+(15/1440),"On time","Off time")),"Sin llegada")) -> Off time | AE81: =MID(Tabla2[[#This Row],[TIPO]],1,3) -> 40 | AF81: ="Hola!" & "%0A" & "Servicio del día " &TEXT(Tabla2[[#This Row],[FECHA ENTREGA]],"dd-mm") & "%0A" & " *Cliente:* " &Tabla2[[#This Row],[CLIENTE]] & " */ Cont: * "&Tabla2[[#This Row],[CONTENEDOR]] & "*/ HR Entrega: *" & TEXT(Tabla2[[#This Row],[HORA ENTREGA]],"hh:mm") & "* /Dirección: *" & Tabla2[[#This Row],[Dirección Entrega]] -> Hola!%0AServicio del día 03-02%0A *Cliente:* LAMAIGNERE CHILE S.A. */ Cont: * ECMU5095006*/ HR Entrega: *10:00* /Dirección: *AV. MARTA OSSA RUIZ 601 (CAMINO CASAS VIEJAS); MAIPU | AG81: =IFERROR(HYPERLINK("https://wa.me/"&Tabla2[[#This Row],[CONTACTO]]&"?text="&Tabla2[[#This Row],[Mensaje]],"Enviar mensaje"),"") -> Enviar mensaje | AH81: =CONCATENATE(A81,F81) -> 80ECMU5095006 | AI81: =CONCATENATE("ENT-",A81) -> ENT-80 | AJ81: =IF(Tabla2[[#This Row],[Op]]<>"","ENTREGA","") -> ENTREGA | AK81: =(Tabla2[[#This Row],[FECHA ENTREGA]]&Tabla2[[#This Row],[HORA ENTREGA]]) -> 460560,416666666666667 | AL81: =IFERROR(HYPERLINK("https://wa.me/"&Tabla2[[#This Row],[CONTACTO]]&"?text="&Tabla2[[#This Row],[Mensaje]]),"") -> https://wa.me/56967398822?text=Hola!%0AServicio del día 03-02%0A *Cliente:* LAMAIGNERE CHILE S.A. */ Cont: * ECMU5095006*/ HR Entrega: *10:00* /Dirección: *AV. MARTA OSSA RUIZ 601 (CAMINO CASAS VIEJAS); MAIPU
A82: =ROW(A81) -> 81 | B82: =IF(J82=J81,B81+1,1) -> 33 | C82: LAMAIGNERE CHILE S.A. | D82: IMPO | E82: 187967 | F82: FFAU3979718 | G82: 40 HC | H82: 30000 | I82: FRAGUA | J82: 46056 | K82: 0.5 | M82: MIGUEL CACERES LOYOLA | N82: =IFERROR(VLOOKUP(M82,Data!$J$1:$K$58,2,0),"") -> 56967387744 | O82: LXCB-59 | Q82: AV. MARTA OSSA RUIZ 601 (CAMINO CASAS VIEJAS); MAIPU | R82: MEDLOG VALP | Y82: ENTREGADO | AA82: 0.5625 | AC82: 46056 | AD82: =IF(Tabla2[[#This Row],[HORA ENTREGA]]="DIRECTO","On time", IF(AA82<>"",IF(Tabla2[[#This Row],[Fecha Real Entrega]]<Tabla2[[#This Row],[FECHA ENTREGA]],"On time",IF(Tabla2[[#This Row],[Hora Real Entrega]]<=Tabla2[[#This Row],[HORA ENTREGA]]+(15/1440),"On time","Off time")),"Sin llegada")) -> Off time | AE82: =MID(Tabla2[[#This Row],[TIPO]],1,3) -> 40 | AF82: ="Hola!" & "%0A" & "Servicio del día " &TEXT(Tabla2[[#This Row],[FECHA ENTREGA]],"dd-mm") & "%0A" & " *Cliente:* " &Tabla2[[#This Row],[CLIENTE]] & " */ Cont: * "&Tabla2[[#This Row],[CONTENEDOR]] & "*/ HR Entrega: *" & TEXT(Tabla2[[#This Row],[HORA ENTREGA]],"hh:mm") & "* /Dirección: *" & Tabla2[[#This Row],[Dirección Entrega]] -> Hola!%0AServicio del día 03-02%0A *Cliente:* LAMAIGNERE CHILE S.A. */ Cont: * FFAU3979718*/ HR Entrega: *12:00* /Dirección: *AV. MARTA OSSA RUIZ 601 (CAMINO CASAS VIEJAS); MAIPU | AG82: =IFERROR(HYPERLINK("https://wa.me/"&Tabla2[[#This Row],[CONTACTO]]&"?text="&Tabla2[[#This Row],[Mensaje]],"Enviar mensaje"),"") -> Enviar mensaje | AH82: =CONCATENATE(A82,F82) -> 81FFAU3979718 | AI82: =CONCATENATE("ENT-",A82) -> ENT-81 | AJ82: =IF(Tabla2[[#This Row],[Op]]<>"","ENTREGA","") -> ENTREGA | AK82: =(Tabla2[[#This Row],[FECHA ENTREGA]]&Tabla2[[#This Row],[HORA ENTREGA]]) -> 460560,5 | AL82: =IFERROR(HYPERLINK("https://wa.me/"&Tabla2[[#This Row],[CONTACTO]]&"?text="&Tabla2[[#This Row],[Mensaje]]),"") -> https://wa.me/56967387744?text=Hola!%0AServicio del día 03-02%0A *Cliente:* LAMAIGNERE CHILE S.A. */ Cont: * FFAU3979718*/ HR Entrega: *12:00* /Dirección: *AV. MARTA OSSA RUIZ 601 (CAMINO CASAS VIEJAS); MAIPU
A83: =ROW(A82) -> 82 | B83: =IF(J83=J82,B82+1,1) -> 34 | C83: LANCO & HARRIS SURAMERICA SPA | D83: IMPO | E83: 298527 | F83: SIMU2614503 | G83: 20 DV | H83: 23000 | I83: 02/02- 21:19 | J83: 46056 | K83: 0.33333333 | M83: CRISTIAN ARAYA | N83: =IFERROR(VLOOKUP(M83,Data!$J$1:$K$58,2,0),"") -> 56950923536 | O83: LPYJ-43 | Q83: CALLE CHORRILLOS 1 PARC.19B, LAMPA | R83: SHIPPER OWN | X83: RAMPLA CORTA | Y83: ENTREGADO | Z83: RAMPLA QUEDO EN CLIENTE / DESCARGA MIERC.04-02 | AA83: 0.41805556 | AC83: 46056 | AD83: =IF(Tabla2[[#This Row],[HORA ENTREGA]]="DIRECTO","On time", IF(AA83<>"",IF(Tabla2[[#This Row],[Fecha Real Entrega]]<Tabla2[[#This Row],[FECHA ENTREGA]],"On time",IF(Tabla2[[#This Row],[Hora Real Entrega]]<=Tabla2[[#This Row],[HORA ENTREGA]]+(15/1440),"On time","Off time")),"Sin llegada")) -> Off time | AE83: =MID(Tabla2[[#This Row],[TIPO]],1,3) -> 20 | AF83: ="Hola!" & "%0A" & "Servicio del día " &TEXT(Tabla2[[#This Row],[FECHA ENTREGA]],"dd-mm") & "%0A" & " *Cliente:* " &Tabla2[[#This Row],[CLIENTE]] & " */ Cont: * "&Tabla2[[#This Row],[CONTENEDOR]] & "*/ HR Entrega: *" & TEXT(Tabla2[[#This Row],[HORA ENTREGA]],"hh:mm") & "* /Dirección: *" & Tabla2[[#This Row],[Dirección Entrega]] -> Hola!%0AServicio del día 03-02%0A *Cliente:* LANCO & HARRIS SURAMERICA SPA */ Cont: * SIMU2614503*/ HR Entrega: *08:00* /Dirección: *CALLE CHORRILLOS 1 PARC.19B, LAMPA | AG83: =IFERROR(HYPERLINK("https://wa.me/"&Tabla2[[#This Row],[CONTACTO]]&"?text="&Tabla2[[#This Row],[Mensaje]],"Enviar mensaje"),"") -> Enviar mensaje | AH83: =CONCATENATE(A83,F83) -> 82SIMU2614503 | AI83: =CONCATENATE("ENT-",A83) -> ENT-82 | AJ83: =IF(Tabla2[[#This Row],[Op]]<>"","ENTREGA","") -> ENTREGA | AK83: =(Tabla2[[#This Row],[FECHA ENTREGA]]&Tabla2[[#This Row],[HORA ENTREGA]]) -> 460560,333333333333333 | AL83: =IFERROR(HYPERLINK("https://wa.me/"&Tabla2[[#This Row],[CONTACTO]]&"?text="&Tabla2[[#This Row],[Mensaje]]),"") -> https://wa.me/56950923536?text=Hola!%0AServicio del día 03-02%0A *Cliente:* LANCO & HARRIS SURAMERICA SPA */ Cont: * SIMU2614503*/ HR Entrega: *08:00* /Dirección: *CALLE CHORRILLOS 1 PARC.19B, LAMPA
A84: =ROW(A83) -> 83 | B84: =IF(J84=J83,B83+1,1) -> 35 | C84: OXIQUIM S A | D84: IMPO | E84: 1178054 | F84: TGCU2050334 | G84: 20 DV | H84: 19000 | I84: 02/02 - 12:46 | J84: 46056 | K84: 0.35416667 | M84: SAMUEL SALAS | N84: =IFERROR(VLOOKUP(M84,Data!$J$1:$K$58,2,0),"") -> 56950981572 | O84: THYG-63 | Q84: CAÑAVERAL 901; QUILICURA | R84: - | Y84: ENTREGADO | AA84: 0.32986111 | AC84: 46056 | AD84: =IF(Tabla2[[#This Row],[HORA ENTREGA]]="DIRECTO","On time", IF(AA84<>"",IF(Tabla2[[#This Row],[Fecha Real Entrega]]<Tabla2[[#This Row],[FECHA ENTREGA]],"On time",IF(Tabla2[[#This Row],[Hora Real Entrega]]<=Tabla2[[#This Row],[HORA ENTREGA]]+(15/1440),"On time","Off time")),"Sin llegada")) -> On time | AE84: =MID(Tabla2[[#This Row],[TIPO]],1,3) -> 20 | AF84: ="Hola!" & "%0A" & "Servicio del día " &TEXT(Tabla2[[#This Row],[FECHA ENTREGA]],"dd-mm") & "%0A" & " *Cliente:* " &Tabla2[[#This Row],[CLIENTE]] & " */ Cont: * "&Tabla2[[#This Row],[CONTENEDOR]] & "*/ HR Entrega: *" & TEXT(Tabla2[[#This Row],[HORA ENTREGA]],"hh:mm") & "* /Dirección: *" & Tabla2[[#This Row],[Dirección Entrega]] -> Hola!%0AServicio del día 03-02%0A *Cliente:* OXIQUIM S A */ Cont: * TGCU2050334*/ HR Entrega: *08:30* /Dirección: *CAÑAVERAL 901; QUILICURA | AG84: =IFERROR(HYPERLINK("https://wa.me/"&Tabla2[[#This Row],[CONTACTO]]&"?text="&Tabla2[[#This Row],[Mensaje]],"Enviar mensaje"),"") -> Enviar mensaje | AH84: =CONCATENATE(A84,F84) -> 83TGCU2050334 | AI84: =CONCATENATE("ENT-",A84) -> ENT-83 | AJ84: =IF(Tabla2[[#This Row],[Op]]<>"","ENTREGA","") -> ENTREGA | AK84: =(Tabla2[[#This Row],[FECHA ENTREGA]]&Tabla2[[#This Row],[HORA ENTREGA]]) -> 460560,354166666666667 | AL84: =IFERROR(HYPERLINK("https://wa.me/"&Tabla2[[#This Row],[CONTACTO]]&"?text="&Tabla2[[#This Row],[Mensaje]]),"") -> https://wa.me/56950981572?text=Hola!%0AServicio del día 03-02%0A *Cliente:* OXIQUIM S A */ Cont: * TGCU2050334*/ HR Entrega: *08:30* /Dirección: *CAÑAVERAL 901; QUILICURA
A85: =ROW(A84) -> 84 | B85: =IF(J85=J84,B84+1,1) -> 36 | C85: OXIQUIM S A | D85: IMPO | E85: 483039 | F85: NYKU9776611 | G85: 20 DV | H85: 24000 | I85: FRAGUA | J85: 46056 | K85: 0.375 | M85: GUSTAVO BRIZUELA | N85: =IFERROR(VLOOKUP(M85,Data!$J$1:$K$58,2,0),"") -> 56976511010 | O85: LPYJ-44 | Q85: CAÑAVERAL 901; QUILICURA | R85: SITRANS SAI | X85: RAMPLA CORTA | Y85: ENTREGADO | AA85: 0.32291667 | AC85: 46056 | AD85: =IF(Tabla2[[#This Row],[HORA ENTREGA]]="DIRECTO","On time", IF(AA85<>"",IF(Tabla2[[#This Row],[Fecha Real Entrega]]<Tabla2[[#This Row],[FECHA ENTREGA]],"On time",IF(Tabla2[[#This Row],[Hora Real Entrega]]<=Tabla2[[#This Row],[HORA ENTREGA]]+(15/1440),"On time","Off time")),"Sin llegada")) -> On time | AE85: =MID(Tabla2[[#This Row],[TIPO]],1,3) -> 20 | AF85: ="Hola!" & "%0A" & "Servicio del día " &TEXT(Tabla2[[#This Row],[FECHA ENTREGA]],"dd-mm") & "%0A" & " *Cliente:* " &Tabla2[[#This Row],[CLIENTE]] & " */ Cont: * "&Tabla2[[#This Row],[CONTENEDOR]] & "*/ HR Entrega: *" & TEXT(Tabla2[[#This Row],[HORA ENTREGA]],"hh:mm") & "* /Dirección: *" & Tabla2[[#This Row],[Dirección Entrega]] -> Hola!%0AServicio del día 03-02%0A *Cliente:* OXIQUIM S A */ Cont: * NYKU9776611*/ HR Entrega: *09:00* /Dirección: *CAÑAVERAL 901; QUILICURA | AG85: =IFERROR(HYPERLINK("https://wa.me/"&Tabla2[[#This Row],[CONTACTO]]&"?text="&Tabla2[[#This Row],[Mensaje]],"Enviar mensaje"),"") -> Enviar mensaje | AH85: =CONCATENATE(A85,F85) -> 84NYKU9776611 | AI85: =CONCATENATE("ENT-",A85) -> ENT-84 | AJ85: =IF(Tabla2[[#This Row],[Op]]<>"","ENTREGA","") -> ENTREGA | AK85: =(Tabla2[[#This Row],[FECHA ENTREGA]]&Tabla2[[#This Row],[HORA ENTREGA]]) -> 460560,375 | AL85: =IFERROR(HYPERLINK("https://wa.me/"&Tabla2[[#This Row],[CONTACTO]]&"?text="&Tabla2[[#This Row],[Mensaje]]),"") -> https://wa.me/56976511010?text=Hola!%0AServicio del día 03-02%0A *Cliente:* OXIQUIM S A */ Cont: * NYKU9776611*/ HR Entrega: *09:00* /Dirección: *CAÑAVERAL 901; QUILICURA
A86: =ROW(A85) -> 85 | B86: =IF(J86=J85,B85+1,1) -> 37 | C86: OXIQUIM S A | D86: IMPO | E86: 482965 | F86: MEDU5891375 | G86: 20 DV | H86: 28000 | I86: FRAGUA | J86: 46056 | K86: 0.41666667 | M86: JOSE SALAZAR | N86: =IFERROR(VLOOKUP(M86,Data!$J$1:$K$58,2,0),"") -> 56973887427 | O86: TRKJ-65 | Q86: CAÑAVERAL 901; QUILICURA | R86: MEDLOG SAI | Y86: ENTREGADO | AA86: 0.39791667 | AC86: 46056 | AD86: =IF(Tabla2[[#This Row],[HORA ENTREGA]]="DIRECTO","On time", IF(AA86<>"",IF(Tabla2[[#This Row],[Fecha Real Entrega]]<Tabla2[[#This Row],[FECHA ENTREGA]],"On time",IF(Tabla2[[#This Row],[Hora Real Entrega]]<=Tabla2[[#This Row],[HORA ENTREGA]]+(15/1440),"On time","Off time")),"Sin llegada")) -> On time | AE86: =MID(Tabla2[[#This Row],[TIPO]],1,3) -> 20 | AF86: ="Hola!" & "%0A" & "Servicio del día " &TEXT(Tabla2[[#This Row],[FECHA ENTREGA]],"dd-mm") & "%0A" & " *Cliente:* " &Tabla2[[#This Row],[CLIENTE]] & " */ Cont: * "&Tabla2[[#This Row],[CONTENEDOR]] & "*/ HR Entrega: *" & TEXT(Tabla2[[#This Row],[HORA ENTREGA]],"hh:mm") & "* /Dirección: *" & Tabla2[[#This Row],[Dirección Entrega]] -> Hola!%0AServicio del día 03-02%0A *Cliente:* OXIQUIM S A */ Cont: * MEDU5891375*/ HR Entrega: *10:00* /Dirección: *CAÑAVERAL 901; QUILICURA | AG86: =IFERROR(HYPERLINK("https://wa.me/"&Tabla2[[#This Row],[CONTACTO]]&"?text="&Tabla2[[#This Row],[Mensaje]],"Enviar mensaje"),"") -> Enviar mensaje | AH86: =CONCATENATE(A86,F86) -> 85MEDU5891375 | AI86: =CONCATENATE("ENT-",A86) -> ENT-85 | AJ86: =IF(Tabla2[[#This Row],[Op]]<>"","ENTREGA","") -> ENTREGA | AK86: =(Tabla2[[#This Row],[FECHA ENTREGA]]&Tabla2[[#This Row],[HORA ENTREGA]]) -> 460560,416666666666667 | AL86: =IFERROR(HYPERLINK("https://wa.me/"&Tabla2[[#This Row],[CONTACTO]]&"?text="&Tabla2[[#This Row],[Mensaje]]),"") -> https://wa.me/56973887427?text=Hola!%0AServicio del día 03-02%0A *Cliente:* OXIQUIM S A */ Cont: * MEDU5891375*/ HR Entrega: *10:00* /Dirección: *CAÑAVERAL 901; QUILICURA
A87: =ROW(A86) -> 86 | B87: =IF(J87=J86,B86+1,1) -> 38 | C87: RENDIC S.A. | D87: IMPO | E87: 102583 | F87: ONEU9138635 | G87: 40 RF | H87: 26000 | I87: 0.75 | J87: 46056 | K87: 0 | M87: RODRIGO AÑAZCO | N87: =IFERROR(VLOOKUP(M87,Data!$J$1:$K$58,2,0),"") -> 56992164782 | O87: LGGR-14 | Q87: CD LO AGUIRRE | R87: - | Y87: ENTREGADO | AA87: 0.73611111 | AC87: 46056 | AD87: =IF(Tabla2[[#This Row],[HORA ENTREGA]]="DIRECTO","On time", IF(AA87<>"",IF(Tabla2[[#This Row],[Fecha Real Entrega]]<Tabla2[[#This Row],[FECHA ENTREGA]],"On time",IF(Tabla2[[#This Row],[Hora Real Entrega]]<=Tabla2[[#This Row],[HORA ENTREGA]]+(15/1440),"On time","Off time")),"Sin llegada")) -> Off time | AE87: =MID(Tabla2[[#This Row],[TIPO]],1,3) -> 40 | AF87: ="Hola!" & "%0A" & "Servicio del día " &TEXT(Tabla2[[#This Row],[FECHA ENTREGA]],"dd-mm") & "%0A" & " *Cliente:* " &Tabla2[[#This Row],[CLIENTE]] & " */ Cont: * "&Tabla2[[#This Row],[CONTENEDOR]] & "*/ HR Entrega: *" & TEXT(Tabla2[[#This Row],[HORA ENTREGA]],"hh:mm") & "* /Dirección: *" & Tabla2[[#This Row],[Dirección Entrega]] -> Hola!%0AServicio del día 03-02%0A *Cliente:* RENDIC S.A. */ Cont: * ONEU9138635*/ HR Entrega: *00:00* /Dirección: *CD LO AGUIRRE | AG87: =IFERROR(HYPERLINK("https://wa.me/"&Tabla2[[#This Row],[CONTACTO]]&"?text="&Tabla2[[#This Row],[Mensaje]],"Enviar mensaje"),"") -> Enviar mensaje | AH87: =CONCATENATE(A87,F87) -> 86ONEU9138635 | AI87: =CONCATENATE("ENT-",A87) -> ENT-86 | AJ87: =IF(Tabla2[[#This Row],[Op]]<>"","ENTREGA","") -> ENTREGA | AK87: =(Tabla2[[#This Row],[FECHA ENTREGA]]&Tabla2[[#This Row],[HORA ENTREGA]]) -> 460560 | AL87: =IFERROR(HYPERLINK("https://wa.me/"&Tabla2[[#This Row],[CONTACTO]]&"?text="&Tabla2[[#This Row],[Mensaje]]),"") -> https://wa.me/56992164782?text=Hola!%0AServicio del día 03-02%0A *Cliente:* RENDIC S.A. */ Cont: * ONEU9138635*/ HR Entrega: *00:00* /Dirección: *CD LO AGUIRRE
A88: =ROW(A87) -> 87 | B88: =IF(J88=J87,B87+1,1) -> 39 | C88: RENDIC S.A. | D88: IMPO | E88: 101911 | F88: TIIU4302702 | G88: 40 HC | H88: 29000 | I88: FRAGUA | J88: 46056 | K88: 0.29166667 | M88: HELBERTH CASTRO | N88: =IFERROR(VLOOKUP(M88,Data!$J$1:$K$58,2,0),"") -> 56967256951 | O88: RFZW-96 | Q88: Avenida Miraflores 9700-Bodega 4C, PUDAHUEL | R88: MEDLOG SAI | Y88: ENTREGADO | AA88: 0.27430556 | AC88: 46056 | AD88: =IF(Tabla2[[#This Row],[HORA ENTREGA]]="DIRECTO","On time", IF(AA88<>"",IF(Tabla2[[#This Row],[Fecha Real Entrega]]<Tabla2[[#This Row],[FECHA ENTREGA]],"On time",IF(Tabla2[[#This Row],[Hora Real Entrega]]<=Tabla2[[#This Row],[HORA ENTREGA]]+(15/1440),"On time","Off time")),"Sin llegada")) -> On time | AE88: =MID(Tabla2[[#This Row],[TIPO]],1,3) -> 40 | AF88: ="Hola!" & "%0A" & "Servicio del día " &TEXT(Tabla2[[#This Row],[FECHA ENTREGA]],"dd-mm") & "%0A" & " *Cliente:* " &Tabla2[[#This Row],[CLIENTE]] & " */ Cont: * "&Tabla2[[#This Row],[CONTENEDOR]] & "*/ HR Entrega: *" & TEXT(Tabla2[[#This Row],[HORA ENTREGA]],"hh:mm") & "* /Dirección: *" & Tabla2[[#This Row],[Dirección Entrega]] -> Hola!%0AServicio del día 03-02%0A *Cliente:* RENDIC S.A. */ Cont: * TIIU4302702*/ HR Entrega: *07:00* /Dirección: *Avenida Miraflores 9700-Bodega 4C, PUDAHUEL | AG88: =IFERROR(HYPERLINK("https://wa.me/"&Tabla2[[#This Row],[CONTACTO]]&"?text="&Tabla2[[#This Row],[Mensaje]],"Enviar mensaje"),"") -> Enviar mensaje | AH88: =CONCATENATE(A88,F88) -> 87TIIU4302702 | AI88: =CONCATENATE("ENT-",A88) -> ENT-87 | AJ88: =IF(Tabla2[[#This Row],[Op]]<>"","ENTREGA","") -> ENTREGA | AK88: =(Tabla2[[#This Row],[FECHA ENTREGA]]&Tabla2[[#This Row],[HORA ENTREGA]]) -> 460560,291666666666667 | AL88: =IFERROR(HYPERLINK("https://wa.me/"&Tabla2[[#This Row],[CONTACTO]]&"?text="&Tabla2[[#This Row],[Mensaje]]),"") -> https://wa.me/56967256951?text=Hola!%0AServicio del día 03-02%0A *Cliente:* RENDIC S.A. */ Cont: * TIIU4302702*/ HR Entrega: *07:00* /Dirección: *Avenida Miraflores 9700-Bodega 4C, PUDAHUEL
A89: =ROW(A88) -> 88 | B89: =IF(J89=J88,B88+1,1) -> 40 | C89: RENDIC S.A. | D89: IMPO | E89: 102460 | F89: CAAU8406757 | G89: 40 HC | H89: 31000 | I89: FRAGUA | J89: 46056 | K89: 0.29166667 | M89: ROBERTO CARREÑO | N89: =IFERROR(VLOOKUP(M89,Data!$J$1:$K$58,2,0),"") -> 56967384794 | O89: RVFP-32 | Q89: Avenida Miraflores 9700-Bodega 4C, PUDAHUEL | R89: CIS | Y89: ENTREGADO | AA89: 0.25694444 | AC89: 46056 | AD89: =IF(Tabla2[[#This Row],[HORA ENTREGA]]="DIRECTO","On time", IF(AA89<>"",IF(Tabla2[[#This Row],[Fecha Real Entrega]]<Tabla2[[#This Row],[FECHA ENTREGA]],"On time",IF(Tabla2[[#This Row],[Hora Real Entrega]]<=Tabla2[[#This Row],[HORA ENTREGA]]+(15/1440),"On time","Off time")),"Sin llegada")) -> On time | AE89: =MID(Tabla2[[#This Row],[TIPO]],1,3) -> 40 | AF89: ="Hola!" & "%0A" & "Servicio del día " &TEXT(Tabla2[[#This Row],[FECHA ENTREGA]],"dd-mm") & "%0A" & " *Cliente:* " &Tabla2[[#This Row],[CLIENTE]] & " */ Cont: * "&Tabla2[[#This Row],[CONTENEDOR]] & "*/ HR Entrega: *" & TEXT(Tabla2[[#This Row],[HORA ENTREGA]],"hh:mm") & "* /Dirección: *" & Tabla2[[#This Row],[Dirección Entrega]] -> Hola!%0AServicio del día 03-02%0A *Cliente:* RENDIC S.A. */ Cont: * CAAU8406757*/ HR Entrega: *07:00* /Dirección: *Avenida Miraflores 9700-Bodega 4C, PUDAHUEL | AG89: =IFERROR(HYPERLINK("https://wa.me/"&Tabla2[[#This Row],[CONTACTO]]&"?text="&Tabla2[[#This Row],[Mensaje]],"Enviar mensaje"),"") -> Enviar mensaje | AH89: =CONCATENATE(A89,F89) -> 88CAAU8406757 | AI89: =CONCATENATE("ENT-",A89) -> ENT-88 | AJ89: =IF(Tabla2[[#This Row],[Op]]<>"","ENTREGA","") -> ENTREGA | AK89: =(Tabla2[[#This Row],[FECHA ENTREGA]]&Tabla2[[#This Row],[HORA ENTREGA]]) -> 460560,291666666666667 | AL89: =IFERROR(HYPERLINK("https://wa.me/"&Tabla2[[#This Row],[CONTACTO]]&"?text="&Tabla2[[#This Row],[Mensaje]]),"") -> https://wa.me/56967384794?text=Hola!%0AServicio del día 03-02%0A *Cliente:* RENDIC S.A. */ Cont: * CAAU8406757*/ HR Entrega: *07:00* /Dirección: *Avenida Miraflores 9700-Bodega 4C, PUDAHUEL
A90: =ROW(A89) -> 89 | B90: =IF(J90=J89,B89+1,1) -> 41 | C90: RENDIC S.A. | D90: IMPO | E90: 102395 | F90: OERU4135805 | G90: 40 RF | H90: 266000 | I90: 02/02 - 17:00 | J90: 46056 | K90: 0.33333333 | M90: RODRIGO AÑAZCO | N90: =IFERROR(VLOOKUP(M90,Data!$J$1:$K$58,2,0),"") -> 56992164782 | O90: PJBT-99 | Q90: AVDA EL VENSTIQUERO 1260,RENCA | R90: CONTOPSA SAI | Y90: ENTREGADO | AA90: 0.31944444 | AC90: 46056 | AD90: =IF(Tabla2[[#This Row],[HORA ENTREGA]]="DIRECTO","On time", IF(AA90<>"",IF(Tabla2[[#This Row],[Fecha Real Entrega]]<Tabla2[[#This Row],[FECHA ENTREGA]],"On time",IF(Tabla2[[#This Row],[Hora Real Entrega]]<=Tabla2[[#This Row],[HORA ENTREGA]]+(15/1440),"On time","Off time")),"Sin llegada")) -> On time | AE90: =MID(Tabla2[[#This Row],[TIPO]],1,3) -> 40 | AF90: ="Hola!" & "%0A" & "Servicio del día " &TEXT(Tabla2[[#This Row],[FECHA ENTREGA]],"dd-mm") & "%0A" & " *Cliente:* " &Tabla2[[#This Row],[CLIENTE]] & " */ Cont: * "&Tabla2[[#This Row],[CONTENEDOR]] & "*/ HR Entrega: *" & TEXT(Tabla2[[#This Row],[HORA ENTREGA]],"hh:mm") & "* /Dirección: *" & Tabla2[[#This Row],[Dirección Entrega]] -> Hola!%0AServicio del día 03-02%0A *Cliente:* RENDIC S.A. */ Cont: * OERU4135805*/ HR Entrega: *08:00* /Dirección: *AVDA EL VENSTIQUERO 1260,RENCA | AG90: =IFERROR(HYPERLINK("https://wa.me/"&Tabla2[[#This Row],[CONTACTO]]&"?text="&Tabla2[[#This Row],[Mensaje]],"Enviar mensaje"),"") -> Enviar mensaje | AH90: =CONCATENATE(A90,F90) -> 89OERU4135805 | AI90: =CONCATENATE("ENT-",A90) -> ENT-89 | AJ90: =IF(Tabla2[[#This Row],[Op]]<>"","ENTREGA","") -> ENTREGA | AK90: =(Tabla2[[#This Row],[FECHA ENTREGA]]&Tabla2[[#This Row],[HORA ENTREGA]]) -> 460560,333333333333333 | AL90: =IFERROR(HYPERLINK("https://wa.me/"&Tabla2[[#This Row],[CONTACTO]]&"?text="&Tabla2[[#This Row],[Mensaje]]),"") -> https://wa.me/56992164782?text=Hola!%0AServicio del día 03-02%0A *Cliente:* RENDIC S.A. */ Cont: * OERU4135805*/ HR Entrega: *08:00* /Dirección: *AVDA EL VENSTIQUERO 1260,RENCA
A91: =ROW(A90) -> 90 | B91: =IF(J91=J90,B90+1,1) -> 42 | C91: RENDIC S.A. | D91: IMPO | E91: 102274 | F91: MEDU8869550 | G91: 40 HC | H91: 8000 | I91: FRAGUA | J91: 46056 | K91: 0.35416667 | M91: JOSE AGUILAR | N91: =IFERROR(VLOOKUP(M91,Data!$J$1:$K$58,2,0),"") -> 56961282379 | O91: TSYB-25 | Q91: PARCELA 109 A COQUIMBO | R91: MEDLOG STGO | Y91: ENTREGADO | AA91: 0.12847222 | AC91: 46056 | AD91: =IF(Tabla2[[#This Row],[HORA ENTREGA]]="DIRECTO","On time", IF(AA91<>"",IF(Tabla2[[#This Row],[Fecha Real Entrega]]<Tabla2[[#This Row],[FECHA ENTREGA]],"On time",IF(Tabla2[[#This Row],[Hora Real Entrega]]<=Tabla2[[#This Row],[HORA ENTREGA]]+(15/1440),"On time","Off time")),"Sin llegada")) -> On time | AE91: =MID(Tabla2[[#This Row],[TIPO]],1,3) -> 40 | AF91: ="Hola!" & "%0A" & "Servicio del día " &TEXT(Tabla2[[#This Row],[FECHA ENTREGA]],"dd-mm") & "%0A" & " *Cliente:* " &Tabla2[[#This Row],[CLIENTE]] & " */ Cont: * "&Tabla2[[#This Row],[CONTENEDOR]] & "*/ HR Entrega: *" & TEXT(Tabla2[[#This Row],[HORA ENTREGA]],"hh:mm") & "* /Dirección: *" & Tabla2[[#This Row],[Dirección Entrega]] -> Hola!%0AServicio del día 03-02%0A *Cliente:* RENDIC S.A. */ Cont: * MEDU8869550*/ HR Entrega: *08:30* /Dirección: *PARCELA 109 A COQUIMBO | AG91: =IFERROR(HYPERLINK("https://wa.me/"&Tabla2[[#This Row],[CONTACTO]]&"?text="&Tabla2[[#This Row],[Mensaje]],"Enviar mensaje"),"") -> Enviar mensaje | AH91: =CONCATENATE(A91,F91) -> 90MEDU8869550 | AI91: =CONCATENATE("ENT-",A91) -> ENT-90 | AJ91: =IF(Tabla2[[#This Row],[Op]]<>"","ENTREGA","") -> ENTREGA | AK91: =(Tabla2[[#This Row],[FECHA ENTREGA]]&Tabla2[[#This Row],[HORA ENTREGA]]) -> 460560,354166666666667 | AL91: =IFERROR(HYPERLINK("https://wa.me/"&Tabla2[[#This Row],[CONTACTO]]&"?text="&Tabla2[[#This Row],[Mensaje]]),"") -> https://wa.me/56961282379?text=Hola!%0AServicio del día 03-02%0A *Cliente:* RENDIC S.A. */ Cont: * MEDU8869550*/ HR Entrega: *08:30* /Dirección: *PARCELA 109 A COQUIMBO
A92: =ROW(A91) -> 91 | B92: =IF(J92=J91,B91+1,1) -> 43 | C92: RENDIC S.A. | D92: IMPO | E92: 102478 | F92: CAAU2353979 | G92: 20 DV | H92: 24000 | I92: FRAGUA | J92: 46056 | K92: 0.45833333 | N92: =IFERROR(VLOOKUP(M92,Data!$J$1:$K$58,2,0),"") | Q92: Avenida Miraflores 9700-Bodega 4C, PUDAHUEL | R92: CONTOPSA SAI | X92: RAMPLA CORTA | Y92: PENDIENTE | Z92: FUERA DE HORARIO / REPROGRAMADO | AD92: =IF(Tabla2[[#This Row],[HORA ENTREGA]]="DIRECTO","On time", IF(AA92<>"",IF(Tabla2[[#This Row],[Fecha Real Entrega]]<Tabla2[[#This Row],[FECHA ENTREGA]],"On time",IF(Tabla2[[#This Row],[Hora Real Entrega]]<=Tabla2[[#This Row],[HORA ENTREGA]]+(15/1440),"On time","Off time")),"Sin llegada")) -> Sin llegada | AE92: =MID(Tabla2[[#This Row],[TIPO]],1,3) -> 20 | AF92: ="Hola!" & "%0A" & "Servicio del día " &TEXT(Tabla2[[#This Row],[FECHA ENTREGA]],"dd-mm") & "%0A" & " *Cliente:* " &Tabla2[[#This Row],[CLIENTE]] & " */ Cont: * "&Tabla2[[#This Row],[CONTENEDOR]] & "*/ HR Entrega: *" & TEXT(Tabla2[[#This Row],[HORA ENTREGA]],"hh:mm") & "* /Dirección: *" & Tabla2[[#This Row],[Dirección Entrega]] -> Hola!%0AServicio del día 03-02%0A *Cliente:* RENDIC S.A. */ Cont: * CAAU2353979*/ HR Entrega: *11:00* /Dirección: *Avenida Miraflores 9700-Bodega 4C, PUDAHUEL | AG92: =IFERROR(HYPERLINK("https://wa.me/"&Tabla2[[#This Row],[CONTACTO]]&"?text="&Tabla2[[#This Row],[Mensaje]],"Enviar mensaje"),"") -> Enviar mensaje | AH92: =CONCATENATE(A92,F92) -> 91CAAU2353979 | AI92: =CONCATENATE("ENT-",A92) -> ENT-91 | AJ92: =IF(Tabla2[[#This Row],[Op]]<>"","ENTREGA","") -> ENTREGA | AK92: =(Tabla2[[#This Row],[FECHA ENTREGA]]&Tabla2[[#This Row],[HORA ENTREGA]]) -> 460560,458333333333333 | AL92: =IFERROR(HYPERLINK("https://wa.me/"&Tabla2[[#This Row],[CONTACTO]]&"?text="&Tabla2[[#This Row],[Mensaje]]),"") -> https://wa.me/?text=Hola!%0AServicio del día 03-02%0A *Cliente:* RENDIC S.A. */ Cont: * CAAU2353979*/ HR Entrega: *11:00* /Dirección: *Avenida Miraflores 9700-Bodega 4C, PUDAHUEL
A93: =ROW(A92) -> 92 | B93: =IF(J93=J92,B92+1,1) -> 44 | C93: SUMINISTROS TELEFONICOS Y COMPUTACIONALES ESTEC LT | D93: IMPO | E93: 312782 | F93: MSDU8246393 | G93: 40 HC | H93: 26000 | I93: FRAGUA | J93: 46056 | K93: 0.29166667 | M93: JUAN SALINAS | N93: =IFERROR(VLOOKUP(M93,Data!$J$1:$K$58,2,0),"") -> 56978089148 | O93: HSWP-41 | Q93: AVENIDA PEDRO DE VALDIVIA 5964, MACUL | R93: MEDLOG STGO | Y93: ENTREGADO | AA93: 0.28194444 | AC93: 46056 | AD93: =IF(Tabla2[[#This Row],[HORA ENTREGA]]="DIRECTO","On time", IF(AA93<>"",IF(Tabla2[[#This Row],[Fecha Real Entrega]]<Tabla2[[#This Row],[FECHA ENTREGA]],"On time",IF(Tabla2[[#This Row],[Hora Real Entrega]]<=Tabla2[[#This Row],[HORA ENTREGA]]+(15/1440),"On time","Off time")),"Sin llegada")) -> On time | AE93: =MID(Tabla2[[#This Row],[TIPO]],1,3) -> 40 | AF93: ="Hola!" & "%0A" & "Servicio del día " &TEXT(Tabla2[[#This Row],[FECHA ENTREGA]],"dd-mm") & "%0A" & " *Cliente:* " &Tabla2[[#This Row],[CLIENTE]] & " */ Cont: * "&Tabla2[[#This Row],[CONTENEDOR]] & "*/ HR Entrega: *" & TEXT(Tabla2[[#This Row],[HORA ENTREGA]],"hh:mm") & "* /Dirección: *" & Tabla2[[#This Row],[Dirección Entrega]] -> Hola!%0AServicio del día 03-02%0A *Cliente:* SUMINISTROS TELEFONICOS Y COMPUTACIONALES ESTEC LT */ Cont: * MSDU8246393*/ HR Entrega: *07:00* /Dirección: *AVENIDA PEDRO DE VALDIVIA 5964, MACUL | AG93: =IFERROR(HYPERLINK("https://wa.me/"&Tabla2[[#This Row],[CONTACTO]]&"?text="&Tabla2[[#This Row],[Mensaje]],"Enviar mensaje"),"") -> Enviar mensaje | AH93: =CONCATENATE(A93,F93) -> 92MSDU8246393 | AI93: =CONCATENATE("ENT-",A93) -> ENT-92 | AJ93: =IF(Tabla2[[#This Row],[Op]]<>"","ENTREGA","") -> ENTREGA | AK93: =(Tabla2[[#This Row],[FECHA ENTREGA]]&Tabla2[[#This Row],[HORA ENTREGA]]) -> 460560,291666666666667 | AL93: =IFERROR(HYPERLINK("https://wa.me/"&Tabla2[[#This Row],[CONTACTO]]&"?text="&Tabla2[[#This Row],[Mensaje]]),"") -> https://wa.me/56978089148?text=Hola!%0AServicio del día 03-02%0A *Cliente:* SUMINISTROS TELEFONICOS Y COMPUTACIONALES ESTEC LT */ Cont: * MSDU8246393*/ HR Entrega: *07:00* /Dirección: *AVENIDA PEDRO DE VALDIVIA 5964, MACUL
A94: =ROW(A93) -> 93 | B94: =IF(J94=J93,B93+1,1) -> 45 | C94: SUPERMERCADO DEL NEUMATICO LTDA | D94: IMPO | E94: 293983 | F94: CMAU4671742 | G94: 40 HC | H94: 19000 | I94: FRAGUA | J94: 46056 | K94: 0.33333333 | M94: PEDRO JOSE CARRILLO | N94: =IFERROR(VLOOKUP(M94,Data!$J$1:$K$58,2,0),"") -> 56984880436 | O94: HLGX-83 | Q94: VELASQUEZ | R94: CIS | Y94: ENTREGADO | AA94: 0.32986111 | AC94: 46056 | AD94: =IF(Tabla2[[#This Row],[HORA ENTREGA]]="DIRECTO","On time", IF(AA94<>"",IF(Tabla2[[#This Row],[Fecha Real Entrega]]<Tabla2[[#This Row],[FECHA ENTREGA]],"On time",IF(Tabla2[[#This Row],[Hora Real Entrega]]<=Tabla2[[#This Row],[HORA ENTREGA]]+(15/1440),"On time","Off time")),"Sin llegada")) -> On time | AE94: =MID(Tabla2[[#This Row],[TIPO]],1,3) -> 40 | AF94: ="Hola!" & "%0A" & "Servicio del día " &TEXT(Tabla2[[#This Row],[FECHA ENTREGA]],"dd-mm") & "%0A" & " *Cliente:* " &Tabla2[[#This Row],[CLIENTE]] & " */ Cont: * "&Tabla2[[#This Row],[CONTENEDOR]] & "*/ HR Entrega: *" & TEXT(Tabla2[[#This Row],[HORA ENTREGA]],"hh:mm") & "* /Dirección: *" & Tabla2[[#This Row],[Dirección Entrega]] -> Hola!%0AServicio del día 03-02%0A *Cliente:* SUPERMERCADO DEL NEUMATICO LTDA */ Cont: * CMAU4671742*/ HR Entrega: *08:00* /Dirección: *VELASQUEZ | AG94: =IFERROR(HYPERLINK("https://wa.me/"&Tabla2[[#This Row],[CONTACTO]]&"?text="&Tabla2[[#This Row],[Mensaje]],"Enviar mensaje"),"") -> Enviar mensaje | AH94: =CONCATENATE(A94,F94) -> 93CMAU4671742 | AI94: =CONCATENATE("ENT-",A94) -> ENT-93 | AJ94: =IF(Tabla2[[#This Row],[Op]]<>"","ENTREGA","") -> ENTREGA | AK94: =(Tabla2[[#This Row],[FECHA ENTREGA]]&Tabla2[[#This Row],[HORA ENTREGA]]) -> 460560,333333333333333 | AL94: =IFERROR(HYPERLINK("https://wa.me/"&Tabla2[[#This Row],[CONTACTO]]&"?text="&Tabla2[[#This Row],[Mensaje]]),"") -> https://wa.me/56984880436?text=Hola!%0AServicio del día 03-02%0A *Cliente:* SUPERMERCADO DEL NEUMATICO LTDA */ Cont: * CMAU4671742*/ HR Entrega: *08:00* /Dirección: *VELASQUEZ
A95: =ROW(A94) -> 94 | B95: =IF(J95=J94,B94+1,1) -> 46 | C95: SUPERMERCADO DEL NEUMATICO LTDA | D95: IMPO | E95: 293983 | F95: PRSU8861909 | G95: 40 HC | H95: 16000 | I95: 02/02 - 16:06 | J95: 46056 | K95: 0.47916667 | M95: CESAR VALDES | N95: =IFERROR(VLOOKUP(M95,Data!$J$1:$K$58,2,0),"") -> 56967386251 | O95: PJBV-11 | Q95: VELASQUEZ | R95: - | Y95: ENTREGADO | AA95: 0.54583333 | AC95: 46056 | AD95: =IF(Tabla2[[#This Row],[HORA ENTREGA]]="DIRECTO","On time", IF(AA95<>"",IF(Tabla2[[#This Row],[Fecha Real Entrega]]<Tabla2[[#This Row],[FECHA ENTREGA]],"On time",IF(Tabla2[[#This Row],[Hora Real Entrega]]<=Tabla2[[#This Row],[HORA ENTREGA]]+(15/1440),"On time","Off time")),"Sin llegada")) -> Off time | AE95: =MID(Tabla2[[#This Row],[TIPO]],1,3) -> 40 | AF95: ="Hola!" & "%0A" & "Servicio del día " &TEXT(Tabla2[[#This Row],[FECHA ENTREGA]],"dd-mm") & "%0A" & " *Cliente:* " &Tabla2[[#This Row],[CLIENTE]] & " */ Cont: * "&Tabla2[[#This Row],[CONTENEDOR]] & "*/ HR Entrega: *" & TEXT(Tabla2[[#This Row],[HORA ENTREGA]],"hh:mm") & "* /Dirección: *" & Tabla2[[#This Row],[Dirección Entrega]] -> Hola!%0AServicio del día 03-02%0A *Cliente:* SUPERMERCADO DEL NEUMATICO LTDA */ Cont: * PRSU8861909*/ HR Entrega: *11:30* /Dirección: *VELASQUEZ | AG95: =IFERROR(HYPERLINK("https://wa.me/"&Tabla2[[#This Row],[CONTACTO]]&"?text="&Tabla2[[#This Row],[Mensaje]],"Enviar mensaje"),"") -> Enviar mensaje | AH95: =CONCATENATE(A95,F95) -> 94PRSU8861909 | AI95: =CONCATENATE("ENT-",A95) -> ENT-94 | AJ95: =IF(Tabla2[[#This Row],[Op]]<>"","ENTREGA","") -> ENTREGA | AK95: =(Tabla2[[#This Row],[FECHA ENTREGA]]&Tabla2[[#This Row],[HORA ENTREGA]]) -> 460560,479166666666667 | AL95: =IFERROR(HYPERLINK("https://wa.me/"&Tabla2[[#This Row],[CONTACTO]]&"?text="&Tabla2[[#This Row],[Mensaje]]),"") -> https://wa.me/56967386251?text=Hola!%0AServicio del día 03-02%0A *Cliente:* SUPERMERCADO DEL NEUMATICO LTDA */ Cont: * PRSU8861909*/ HR Entrega: *11:30* /Dirección: *VELASQUEZ
A96: =ROW(A95) -> 95 | B96: =IF(J96=J95,B95+1,1) -> 1 | C96: A R G TRAILERS SPA | D96: IMPO | E96: 70085 | F96: APHU7235894 | G96: 40 HC | H96: 25000 | I96: 03/02 - 20:22 | J96: 46057 | K96: 0.35416667 | M96: SEBASTIAN CUETO | N96: =IFERROR(VLOOKUP(M96,Data!$J$1:$K$58,2,0),"") -> 56931745801 | O96: RVFP-34 | Q96: GOREN - LA PRIMAVERA 361; LAMPA | R96: CIS | Y96: ENTREGADO | AA96: 0.32777778 | AC96: 46057 | AD96: =IF(Tabla2[[#This Row],[HORA ENTREGA]]="DIRECTO","On time", IF(AA96<>"",IF(Tabla2[[#This Row],[Fecha Real Entrega]]<Tabla2[[#This Row],[FECHA ENTREGA]],"On time",IF(Tabla2[[#This Row],[Hora Real Entrega]]<=Tabla2[[#This Row],[HORA ENTREGA]]+(15/1440),"On time","Off time")),"Sin llegada")) -> On time | AE96: =MID(Tabla2[[#This Row],[TIPO]],1,3) -> 40 | AF96: ="Hola!" & "%0A" & "Servicio del día " &TEXT(Tabla2[[#This Row],[FECHA ENTREGA]],"dd-mm") & "%0A" & " *Cliente:* " &Tabla2[[#This Row],[CLIENTE]] & " */ Cont: * "&Tabla2[[#This Row],[CONTENEDOR]] & "*/ HR Entrega: *" & TEXT(Tabla2[[#This Row],[HORA ENTREGA]],"hh:mm") & "* /Dirección: *" & Tabla2[[#This Row],[Dirección Entrega]] -> Hola!%0AServicio del día 04-02%0A *Cliente:* A R G TRAILERS SPA */ Cont: * APHU7235894*/ HR Entrega: *08:30* /Dirección: *GOREN - LA PRIMAVERA 361; LAMPA | AG96: =IFERROR(HYPERLINK("https://wa.me/"&Tabla2[[#This Row],[CONTACTO]]&"?text="&Tabla2[[#This Row],[Mensaje]],"Enviar mensaje"),"") -> Enviar mensaje | AH96: =CONCATENATE(A96,F96) -> 95APHU7235894 | AI96: =CONCATENATE("ENT-",A96) -> ENT-95 | AJ96: =IF(Tabla2[[#This Row],[Op]]<>"","ENTREGA","") -> ENTREGA | AK96: =(Tabla2[[#This Row],[FECHA ENTREGA]]&Tabla2[[#This Row],[HORA ENTREGA]]) -> 460570,354166666666667 | AL96: =IFERROR(HYPERLINK("https://wa.me/"&Tabla2[[#This Row],[CONTACTO]]&"?text="&Tabla2[[#This Row],[Mensaje]]),"") -> https://wa.me/56931745801?text=Hola!%0AServicio del día 04-02%0A *Cliente:* A R G TRAILERS SPA */ Cont: * APHU7235894*/ HR Entrega: *08:30* /Dirección: *GOREN - LA PRIMAVERA 361; LAMPA
A97: =ROW(A96) -> 96 | B97: =IF(J97=J96,B96+1,1) -> 2 | C97: A R G TRAILERS SPA | D97: IMPO | E97: 70085 | F97: TIIU6306374 | G97: 40 HC | H97: 16000 | I97: 03/02 - 13:37 | J97: 46057 | K97: 0.35416667 | M97: JAIME PINTO YAÑEZ | N97: =IFERROR(VLOOKUP(M97,Data!$J$1:$K$58,2,0),"") -> 56956654384 | O97: LPYG-88 | Q97: GOREN - LA PRIMAVERA 361; LAMPA | R97: CIS | Y97: ENTREGADO | AA97: 0.35069444 | AC97: 46057 | AD97: =IF(Tabla2[[#This Row],[HORA ENTREGA]]="DIRECTO","On time", IF(AA97<>"",IF(Tabla2[[#This Row],[Fecha Real Entrega]]<Tabla2[[#This Row],[FECHA ENTREGA]],"On time",IF(Tabla2[[#This Row],[Hora Real Entrega]]<=Tabla2[[#This Row],[HORA ENTREGA]]+(15/1440),"On time","Off time")),"Sin llegada")) -> On time | AE97: =MID(Tabla2[[#This Row],[TIPO]],1,3) -> 40 | AF97: ="Hola!" & "%0A" & "Servicio del día " &TEXT(Tabla2[[#This Row],[FECHA ENTREGA]],"dd-mm") & "%0A" & " *Cliente:* " &Tabla2[[#This Row],[CLIENTE]] & " */ Cont: * "&Tabla2[[#This Row],[CONTENEDOR]] & "*/ HR Entrega: *" & TEXT(Tabla2[[#This Row],[HORA ENTREGA]],"hh:mm") & "* /Dirección: *" & Tabla2[[#This Row],[Dirección Entrega]] -> Hola!%0AServicio del día 04-02%0A *Cliente:* A R G TRAILERS SPA */ Cont: * TIIU6306374*/ HR Entrega: *08:30* /Dirección: *GOREN - LA PRIMAVERA 361; LAMPA | AG97: =IFERROR(HYPERLINK("https://wa.me/"&Tabla2[[#This Row],[CONTACTO]]&"?text="&Tabla2[[#This Row],[Mensaje]],"Enviar mensaje"),"") -> Enviar mensaje | AH97: =CONCATENATE(A97,F97) -> 96TIIU6306374 | AI97: =CONCATENATE("ENT-",A97) -> ENT-96 | AJ97: =IF(Tabla2[[#This Row],[Op]]<>"","ENTREGA","") -> ENTREGA | AK97: =(Tabla2[[#This Row],[FECHA ENTREGA]]&Tabla2[[#This Row],[HORA ENTREGA]]) -> 460570,354166666666667 | AL97: =IFERROR(HYPERLINK("https://wa.me/"&Tabla2[[#This Row],[CONTACTO]]&"?text="&Tabla2[[#This Row],[Mensaje]]),"") -> https://wa.me/56956654384?text=Hola!%0AServicio del día 04-02%0A *Cliente:* A R G TRAILERS SPA */ Cont: * TIIU6306374*/ HR Entrega: *08:30* /Dirección: *GOREN - LA PRIMAVERA 361; LAMPA
A98: =ROW(A97) -> 97 | B98: =IF(J98=J97,B97+1,1) -> 3 | C98: A R G TRAILERS SPA | D98: IMPO | E98: 70085 | F98: TCNU3850894 | G98: 40 HC | H98: 23000 | I98: 03/02 - 10:04 | J98: 46057 | K98: 0.35416667 | M98: PEDRO JOSE CARRILLO | N98: =IFERROR(VLOOKUP(M98,Data!$J$1:$K$58,2,0),"") -> 56984880436 | O98: HLGX-83 | Q98: GOREN - LA PRIMAVERA 361; LAMPA | R98: CIS | Y98: ENTREGADO | AA98: 0.33680556 | AC98: 46057 | AD98: =IF(Tabla2[[#This Row],[HORA ENTREGA]]="DIRECTO","On time", IF(AA98<>"",IF(Tabla2[[#This Row],[Fecha Real Entrega]]<Tabla2[[#This Row],[FECHA ENTREGA]],"On time",IF(Tabla2[[#This Row],[Hora Real Entrega]]<=Tabla2[[#This Row],[HORA ENTREGA]]+(15/1440),"On time","Off time")),"Sin llegada")) -> On time | AE98: =MID(Tabla2[[#This Row],[TIPO]],1,3) -> 40 | AF98: ="Hola!" & "%0A" & "Servicio del día " &TEXT(Tabla2[[#This Row],[FECHA ENTREGA]],"dd-mm") & "%0A" & " *Cliente:* " &Tabla2[[#This Row],[CLIENTE]] & " */ Cont: * "&Tabla2[[#This Row],[CONTENEDOR]] & "*/ HR Entrega: *" & TEXT(Tabla2[[#This Row],[HORA ENTREGA]],"hh:mm") & "* /Dirección: *" & Tabla2[[#This Row],[Dirección Entrega]] -> Hola!%0AServicio del día 04-02%0A *Cliente:* A R G TRAILERS SPA */ Cont: * TCNU3850894*/ HR Entrega: *08:30* /Dirección: *GOREN - LA PRIMAVERA 361; LAMPA | AG98: =IFERROR(HYPERLINK("https://wa.me/"&Tabla2[[#This Row],[CONTACTO]]&"?text="&Tabla2[[#This Row],[Mensaje]],"Enviar mensaje"),"") -> Enviar mensaje | AH98: =CONCATENATE(A98,F98) -> 97TCNU3850894 | AI98: =CONCATENATE("ENT-",A98) -> ENT-97 | AJ98: =IF(Tabla2[[#This Row],[Op]]<>"","ENTREGA","") -> ENTREGA | AK98: =(Tabla2[[#This Row],[FECHA ENTREGA]]&Tabla2[[#This Row],[HORA ENTREGA]]) -> 460570,354166666666667 | AL98: =IFERROR(HYPERLINK("https://wa.me/"&Tabla2[[#This Row],[CONTACTO]]&"?text="&Tabla2[[#This Row],[Mensaje]]),"") -> https://wa.me/56984880436?text=Hola!%0AServicio del día 04-02%0A *Cliente:* A R G TRAILERS SPA */ Cont: * TCNU3850894*/ HR Entrega: *08:30* /Dirección: *GOREN - LA PRIMAVERA 361; LAMPA
A99: =ROW(A98) -> 98 | B99: =IF(J99=J98,B98+1,1) -> 4 | C99: ALCA SPA | D99: IMPO | E99: 366202 | F99: TCLU9594452 | G99: 40 HC | H99: 10000 | I99: 03/02 - 9:24 | J99: 46057 | K99: 0.45833333 | M99: GERARDO GALAZ | N99: =IFERROR(VLOOKUP(M99,Data!$J$1:$K$58,2,0),"") -> 56950103942 | O99: LFHK-36 | Q99: LAS GARZAS 851 QUILICURA, CD FRIO ICOFRUT | R99: DYC STGO | Y99: ENTREGADO | AA99: 0.69097222 | AC99: 46057 | AD99: =IF(Tabla2[[#This Row],[HORA ENTREGA]]="DIRECTO","On time", IF(AA99<>"",IF(Tabla2[[#This Row],[Fecha Real Entrega]]<Tabla2[[#This Row],[FECHA ENTREGA]],"On time",IF(Tabla2[[#This Row],[Hora Real Entrega]]<=Tabla2[[#This Row],[HORA ENTREGA]]+(15/1440),"On time","Off time")),"Sin llegada")) -> Off time | AE99: =MID(Tabla2[[#This Row],[TIPO]],1,3) -> 40 | AF99: ="Hola!" & "%0A" & "Servicio del día " &TEXT(Tabla2[[#This Row],[FECHA ENTREGA]],"dd-mm") & "%0A" & " *Cliente:* " &Tabla2[[#This Row],[CLIENTE]] & " */ Cont: * "&Tabla2[[#This Row],[CONTENEDOR]] & "*/ HR Entrega: *" & TEXT(Tabla2[[#This Row],[HORA ENTREGA]],"hh:mm") & "* /Dirección: *" & Tabla2[[#This Row],[Dirección Entrega]] -> Hola!%0AServicio del día 04-02%0A *Cliente:* ALCA SPA */ Cont: * TCLU9594452*/ HR Entrega: *11:00* /Dirección: *LAS GARZAS 851 QUILICURA, CD FRIO ICOFRUT | AG99: =IFERROR(HYPERLINK("https://wa.me/"&Tabla2[[#This Row],[CONTACTO]]&"?text="&Tabla2[[#This Row],[Mensaje]],"Enviar mensaje"),"") -> Enviar mensaje | AH99: =CONCATENATE(A99,F99) -> 98TCLU9594452 | AI99: =CONCATENATE("ENT-",A99) -> ENT-98 | AJ99: =IF(Tabla2[[#This Row],[Op]]<>"","ENTREGA","") -> ENTREGA | AK99: =(Tabla2[[#This Row],[FECHA ENTREGA]]&Tabla2[[#This Row],[HORA ENTREGA]]) -> 460570,458333333333333 | AL99: =IFERROR(HYPERLINK("https://wa.me/"&Tabla2[[#This Row],[CONTACTO]]&"?text="&Tabla2[[#This Row],[Mensaje]]),"") -> https://wa.me/56950103942?text=Hola!%0AServicio del día 04-02%0A *Cliente:* ALCA SPA */ Cont: * TCLU9594452*/ HR Entrega: *11:00* /Dirección: *LAS GARZAS 851 QUILICURA, CD FRIO ICOFRUT
A100: =ROW(A99) -> 99 | B100: =IF(J100=J99,B99+1,1) -> 5 | C100: ALCA SPA | D100: IMPO | E100: 366284 | F100: SZLU9399825 | G100: 40 RF | H100: 26000 | I100: 03/02 - 14:04 | J100: 46057 | K100: 0.47916667 | M100: IVAN VASQUEZ URBINA | N100: =IFERROR(VLOOKUP(M100,Data!$J$1:$K$58,2,0),"") -> 56968463649 | O100: LGGR-12 | Q100: Camino del Cerro 4868 Huechuraba | R100: CONTOPSA SAI | Y100: ENTREGADO | AA100: 0.54444444 | AC100: 46057 | AD100: =IF(Tabla2[[#This Row],[HORA ENTREGA]]="DIRECTO","On time", IF(AA100<>"",IF(Tabla2[[#This Row],[Fecha Real Entrega]]<Tabla2[[#This Row],[FECHA ENTREGA]],"On time",IF(Tabla2[[#This Row],[Hora Real Entrega]]<=Tabla2[[#This Row],[HORA ENTREGA]]+(15/1440),"On time","Off time")),"Sin llegada")) -> Off time | AE100: =MID(Tabla2[[#This Row],[TIPO]],1,3) -> 40 | AF100: ="Hola!" & "%0A" & "Servicio del día " &TEXT(Tabla2[[#This Row],[FECHA ENTREGA]],"dd-mm") & "%0A" & " *Cliente:* " &Tabla2[[#This Row],[CLIENTE]] & " */ Cont: * "&Tabla2[[#This Row],[CONTENEDOR]] & "*/ HR Entrega: *" & TEXT(Tabla2[[#This Row],[HORA ENTREGA]],"hh:mm") & "* /Dirección: *" & Tabla2[[#This Row],[Dirección Entrega]] -> Hola!%0AServicio del día 04-02%0A *Cliente:* ALCA SPA */ Cont: * SZLU9399825*/ HR Entrega: *11:30* /Dirección: *Camino del Cerro 4868 Huechuraba | AG100: =IFERROR(HYPERLINK("https://wa.me/"&Tabla2[[#This Row],[CONTACTO]]&"?text="&Tabla2[[#This Row],[Mensaje]],"Enviar mensaje"),"") -> Enviar mensaje | AH100: =CONCATENATE(A100,F100) -> 99SZLU9399825 | AI100: =CONCATENATE("ENT-",A100) -> ENT-99 | AJ100: =IF(Tabla2[[#This Row],[Op]]<>"","ENTREGA","") -> ENTREGA | AK100: =(Tabla2[[#This Row],[FECHA ENTREGA]]&Tabla2[[#This Row],[HORA ENTREGA]]) -> 460570,479166666666667 | AL100: =IFERROR(HYPERLINK("https://wa.me/"&Tabla2[[#This Row],[CONTACTO]]&"?text="&Tabla2[[#This Row],[Mensaje]]),"") -> https://wa.me/56968463649?text=Hola!%0AServicio del día 04-02%0A *Cliente:* ALCA SPA */ Cont: * SZLU9399825*/ HR Entrega: *11:30* /Dirección: *Camino del Cerro 4868 Huechuraba
...

Sheet Facturación

Sheet Estatus
A1: CLIENTE | B1: (Varios elementos)
